[{"job_id": "100003009052993", "location_code": "hk", "company": "TZ (Taizhong) Hong Kong International Limited", "job_title": "Clerk / Trading Clerk", "description": "\n\u8077\u8cac :\u5916\u52e4\u5de5\u4f5c\uff0c\u5982\u5230\u9280\u884c\u3001\u90f5\u5c40\u8207\u5916\u51fa\u6536\u767c\u6587\u4ef6\uff0c\u4e00\u822c\u8fa6\u516c\u5ba4\u52a9\u7406\u5de5\u4f5c\uff0c\u8ca0\u8cac\u4e00\u822c\u8fa6\u516c\u5ba4\u8336\u6c34\u5de5\u4f5c\uff0c\u6309\u516c\u53f8\u6307\u793a\u5b89\u6392\u5de5\u4f5c\u3002\n\n\u8cc7\u6b77 :\u5c0f\u4e09\u7a0b\u5ea6; 1\u5e74\u7d93\u9a57; \u826f\u597d\u7cb5\u8a9e\u512a\u5148; \u4e00\u822c\u82f1\u8a9e; \u61c2\u8b80\u5beb\u4e2d\u6587; \u61c2\u95b1\u8b80\u82f1\u6587\n\n\u5f85\u9047 :\u6bcf\u6708$10,000 - $12,000, \u6709\u91ab\u7642\u4fdd\u96aa, \u661f\u671f\u4e00\u81f3\u4e94: \u4e0a\u53489\u6642\u81f3\u4e0b\u53486\u6642, \u6bcf\u9031\u5de5\u4f5c5\u5929, \u5f48\u6027\u7528\u81b3\u6642\u9593\n\n\u7533\u8acb\u9808\u77e5 :\u6c42\u8077\u8005\u53ef\u96fb\u90f5(Apply Now)\u5c65\u6b77\u8868\u7d66\u5fb7\u749f\u6cf0\u5be6\u696d\u6709\u9650\u516c\u53f8\u3002\u5982\u8981\u7d22\u53d6\u6536\u96c6\u500b\u4eba\u8cc7\u6599\u8072\u660e, \u8acb\u8207\u5289\u5c0f\u59d0(Email)\u806f\u7d61\u3002\n\n", "employment_types": ["Full Time"], "selling_points": [], "locations": ["Admiralty"], "categories": ["Admin & HR", "Clerical / Admin Staff", "Others", "Trading"], "post_time": "2022-01-17T05:32:01Z", "salary": {"currency": null, "max": null, "min": null, "period": "monthly", "term": null}, "salary_visible": false, "title_keywords": ["clerk"], "responsibilities": [], "requirements": {"degrees": [], "majors": [], "languages": [], "language_level": [], "hard_skills": [], "soft_skills": [], "languages_combined": []}, "experience_required": {"duration": [], "field": []}}, {"job_id": "100003009053001", "location_code": "hk", "company": "Bright Sun Global Enterprise Limited", "job_title": "Personal Assistant to Director", "description": "We are now inviting candidate of high calibre to join us in the following capacity in our Iron & Steel Division.\n\nJob Duties:\n\nTo handle import / export shipping documents\nTo support sales staff to contact customers or suppliers as necessary\nTo perform general administrative and clerical support for the division, such as car booking, meeting room booking, expense claims, arrange hotel booking and business trip etc.\nTo perform other ad-hoc projects and tasks as assigned\nRequirements:\n\nAt least 2 \u2013 5 years\u2019 relevant working experience in shipping area\nExperience in SAP system is preferable\nStrong communication & interpersonal skills\nAble to work under pressure and complete the jobs within time constraint\nGood command of English and Mandarin\nGood command of Microsoft Office Tools (e.g. Word, Excel) and Chinese Typing\nDiploma graduate, commercial studies\n\nInterested parties please apply with your full resume stating present and expected salary.\n\nAll information will be kept confidential and used for recruitment purpose only. Although we endeavour to respond to every applicant, this may not always be possible so if you receive no response within 60 days, please consider your application for this specific vacancy to be unsuccessful.\n\n", "employment_types": ["Full Time"], "selling_points": [], "locations": ["Kowloon Bay"], "categories": ["Admin & HR", "Personal / Executive Assistant", "Others", "Trading"], "post_time": "2022-01-17T06:47:26Z", "salary": {"currency": null, "max": null, "min": null, "period": "monthly", "term": null}, "salary_visible": false, "title_keywords": ["director", "personal assistant"], "responsibilities": ["shipping documents", "business trip", "contact", "administrative and clerical support", "booking", "ad-hoc projects"], "requirements": {"degrees": ["diploma"], "majors": [], "languages": ["english", "chinese", "mandarin"], "language_level": ["good command"], "hard_skills": ["excel", "sap", "microsoft office", "typing", "word"], "soft_skills": ["communication", "interpersonal skills", "work under pressure"], "languages_combined": [{"language": "english", "language_level": ["good command"]}, {"language": "chinese", "language_level": []}, {"language": "mandarin", "language_level": ["good command"]}]}, "experience_required": {"duration": ["5 years"], "field": ["relevant working experience"]}}, {"job_id": "100003009053867", "location_code": "hk", "company": "Dickinson Garment Factory Limited", "job_title": "\u8fa6\u516c\u5ba4\u52a9\u7406**", "description": "Requirements:\nUniversity Degree / High Diploma with two years working experience. Fresh Graduate will also be considered.\nWorking experience in L/C application, import and export bills processing or trading operation is preferred.\nHighly independent, attentive to details, self-motivated and willing to learn.\nProficient in MS office (Word and Excel) and Chinese word processing.\nGood command of both written and spoken English and Chinese. Fluency in Putonghua is a must.\nImmediately available is preferred.\n\nJob responsibilities:\n\nHandle and process full set of bills transaction, coordinate with banks for L/C opening and T/T payment.\nAssist to follow up with supplier and purchaser, including contract review, payment and shipping document organization.\nHandle general office administrative tasks.\nProvide assistance to trading and accounting department,\u00a0handle other ad-hoc tasks as assigned.\n\nBenefits:\n\n5-days work\n13 month salary\nMedical and dental insurance\nLunch Allowance\n\nInterested parties, please submit the full resume with current and expected salary and the date of availability by clicking\u00a0\"Apply Now\" button.\u00a0All information collected will be used for recruitment only and treated in strict confidence.", "employment_types": ["Full Time"], "selling_points": [], "locations": ["Kwun Tong"], "categories": ["Admin & HR", "Clerical / Admin Staff", "Others", "Others", "Trading"], "post_time": "2022-01-17T07:39:39Z", "salary": {"currency": null, "max": null, "min": null, "period": "monthly", "term": null}, "salary_visible": false, "title_keywords": ["\u8fa6\u516c\u5ba4\u52a9\u7406"], "responsibilities": ["ad-hoc tasks", "review", "coordinate with", "payment", "administrative tasks", "provide assistance", "shipping document"], "requirements": {"degrees": ["high diploma", "university degree", "fresh graduate"], "majors": [], "languages": ["putonghua", "english", "chinese"], "language_level": ["fluency", "good command", "proficient"], "hard_skills": ["excel", "chinese word processing", "word", "import and export", "c", "processing", "ms office"], "soft_skills": ["highly independent", "self-motivated", "willing to learn", "attentive to details"], "languages_combined": [{"language": "putonghua", "language_level": ["fluency"]}, {"language": "english", "language_level": ["good command"]}, {"language": "chinese", "language_level": ["good command", "proficient"]}]}, "experience_required": {"duration": ["two years"], "field": ["operation", "trading"]}}, {"job_id": "100003009055919", "location_code": "hk", "company": "YONGTONG (HONGKONG) INDUSTRIES LTD", "job_title": "Trade Operations Specialist", "description": "Job Description:\n\nFull spectrum of Trade Operations & Bills Operations (Contract, L/C etc.)\nCommunicate with banking officers in Hong Kong (operation level)\nWork closely with operation/business teams in Mainland China and Hong Kong\nPerform ad-hoc tasks as assigned by the manager\n\nRequirements:\n\nGood command of English and Chinese\u00a0\nProficiency in Microsoft Word, Excel & Chinese Word Processing\nSelf-motivated and strong sense of responsibility\nCandidates with relative working experience are preferred, fresh graduates are also welcomed\nSalary is negotiable based on the candidate's experience, educational background\u00a0and\u00a0abilities.\u00a0\u00a0\n\n\u62db\u8058\u570b\u969b\u8cbf\u6613\u5be6\u52d9\u5c08\u54e1\uff0c\u4e3b\u8981\u8ca0\u8cac\u570b\u969b\u8cbf\u6613\u5be6\u52d9\u5168\u7dda\u64cd\u4f5c\uff08\u5408\u540c\u3001\u4fe1\u7528\u8b49\u7b49\uff09\uff0c\u4e3b\u8981\u8207\u9999\u6e2f\u9280\u884c\u4eba\u54e1\u53ca\u5167\u5730\u516c\u53f8\u540c\u4e8b\u5c0d\u63a5\uff08\u64cd\u4f5c\u5c64\u9762\uff09\u3002\u8981\u6c42\u54c1\u884c\u7aef\u6b63\uff0c\u8cac\u4efb\u5fc3\u5f37\uff0c\u5de5\u4f5c\u8a8d\u771f\u7d30\u7dfb\uff0c\u82f1\u6587\u6c34\u5e73\u8f03\u9ad8\uff0c\u6297\u58d3\u80fd\u529b\u8f03\u597d\u3002\u6b61\u8fce\u6709\u7d93\u9a57\u4eba\u58eb\u53ca\u512a\u79c0\u61c9\u5c46\u7562\u696d\u751f\u61c9\u8058\u3002\u5de5\u4f5c\u5730\u9ede\u5728\u7063\u4ed4\u3002\u85aa\u8cc7\u53ef\u8b70\u3002", "employment_types": ["Full Time", "Permanent"], "selling_points": [], "locations": ["Wan Chai"], "categories": ["Transportation & Logistics", "Documentary Credit / Bills Processing", "Banking / Finance", "Order Processing & Operation / Settlement", "Others", "Trading"], "post_time": "2022-01-18T03:05:46Z", "salary": {"currency": null, "max": null, "min": null, "period": "monthly", "term": null}, "salary_visible": false, "title_keywords": ["specialist", "operations"], "responsibilities": ["communicate with", "operations", "ad-hoc tasks", "teams", "banking"], "requirements": {"degrees": [], "majors": [], "languages": ["english", "chinese"], "language_level": ["proficiency", "good command"], "hard_skills": ["excel", "microsoft word", "chinese word processing"], "soft_skills": ["self-motivated", "sense of responsibility"], "languages_combined": [{"language": "english", "language_level": ["good command"]}, {"language": "chinese", "language_level": ["proficiency", "good command"]}]}, "experience_required": {"duration": [], "field": []}}, {"job_id": "100003009053427", "location_code": "hk", "company": "Spread Logistics Limited", "job_title": "\u96fb\u5b50\u96f6\u4ef6\u52a0\u5de5\u5c08\u54e1", "description": "Job Descriptions:\n\nLiaise with overseas clients and factories independently\nIndependently in handling projects follow up from sampling development to production\nHandle orders and monitor production process\nPrepare quotations, sampling and monthly reports\nOccasional travel to overseas if needed\n\nRequirements:\n\nHigh Diploma or above with 2 years relevant working experience\nWith solid printing knowledge\u00a0for garment accessories is preferred\nFluent language skills (written and oral) in English, Mandarin and Cantonese\nAble to work independent, detailed oriented, well organized & under pressure within a tight schedule\nProficient in MS office and English + Chinese word processing\nGood team player and work independently\n\nSalary Range: Negotiable\n\nBenefits:\n\n-Bank holiday\n\n-12~25 days annual leave or above\n\n-5 days working per week\n\n-Medical scheme\n\n-13 months salary\n\n-Performance based Bonus (not guarantee)\n\nWe provide attractive remuneration packages to the right candidates. Interested parties please send following by clicking \"APPLY NOW\".\n\nDetailed curriculum vitae/resume\nDate of availability\nExpected salary\n\n(All personal data provided will be treated in strict confidence and used for recruitment purposed only.)", "employment_types": ["Full Time"], "selling_points": [], "locations": ["Not Specified"], "categories": ["Others", "Trading"], "post_time": "2022-01-17T06:58:39Z", "salary": {"currency": null, "max": null, "min": null, "period": "monthly", "term": null}, "salary_visible": false, "title_keywords": [], "responsibilities": ["liaise with", "monitor", "production process", "monthly reports"], "requirements": {"degrees": ["high diploma or above"], "majors": [], "languages": ["cantonese", "english", "chinese", "mandarin"], "language_level": ["proficient", "fluent"], "hard_skills": ["chinese word processing", "ms office"], "soft_skills": ["oral", "good team player", "under pressure", "independent", "detailed oriented", "work independently", "well organized"], "languages_combined": [{"language": "cantonese", "language_level": ["fluent"]}, {"language": "english", "language_level": ["proficient", "fluent"]}, {"language": "chinese", "language_level": ["proficient"]}, {"language": "mandarin", "language_level": ["fluent"]}]}, "experience_required": {"duration": ["2 years"], "field": ["relevant working experience"]}}, {"job_id": "100003009053033", "location_code": "hk", "company": "PS Group International Ltd", "job_title": "Japanese Translator **URGENT**", "description": "Degree holder or at least 1 year relevant experience\nArrangement of samples, costing and follow up orders\nProactive & independent, aggressive & capable to cooperate with a team\nGood command of English & Mandarin\nAbility to work independently with overseas customers\nTo be responsible, hardworking and willing to work under pressure\nLess experience will consider to assist Merchandisers on paper work\n\n\nInterested parties, please apply by click Apply Now\n\nPersonal data will be used for recruitment purpose only.\n", "employment_types": ["Full Time"], "selling_points": ["Hair/Beauty Group", "5 Day Week", "Stable Working Environment"], "locations": ["North Point"], "categories": ["Others", "Trading", "Professional Services", "Translation", "E-commerce", "Marketing - Brand / Product Management"], "post_time": "2022-01-17T05:16:00Z", "salary": {"currency": null, "max": null, "min": null, "period": "monthly", "term": null}, "salary_visible": false, "title_keywords": ["translator"], "responsibilities": ["follow up orders", "cooperate with", "work under pressure"], "requirements": {"degrees": ["degree holder"], "majors": [], "languages": ["english", "mandarin"], "language_level": ["good command"], "hard_skills": [], "soft_skills": ["work independently", "independent", "capable", "responsible", "proactive", "hardworking", "work under pressure"], "languages_combined": [{"language": "english", "language_level": ["good command"]}, {"language": "mandarin", "language_level": ["good command"]}]}, "experience_required": {"duration": ["at least 1 year"], "field": ["relevant experience"]}}, {"job_id": "100003009051259", "location_code": "hk", "company": "\u624d\u8cc7\u6709\u9650\u516c\u53f8", "job_title": "\u8cbf\u6613\u98df\u54c1\u6587\u54e1", "description": "Responsibilities:\n\n\u00a0\u00a0\u00a0\u00a0\u00a0\u00a0\u00a0\u00a0 Coordinate the product development of apparel packaging items.\n\u00a0\u00a0\u00a0\u00a0\u00a0\u00a0\u00a0\u00a0 Manage project priorities to meet assigned timelines and goals.\n\u00a0\u00a0\u00a0\u00a0\u00a0\u00a0\u00a0\u00a0 Monitor supplier performance and quality standards to achieve improved results.\n\u00a0\u00a0\u00a0\u00a0\u00a0\u00a0\u00a0\u00a0 Work with product development team to help identify and resolve any label\n\u00a0 \u00a0 \u00a0 \u00a0 \u00a0and trim performance limitations.\n\u00a0\u00a0\u00a0\u00a0\u00a0\u00a0\u00a0\u00a0 Ensure all labels and trims meet regulatory requirements under global\n\u00a0 \u00a0 \u00a0 \u00a0 \u00a0regulations such as, but not limited to, REACH, CPSIA, Toxics in Packaging,\n\u00a0 \u00a0 \u00a0 \u00a0 \u00a0and customer specific requirement.\n\nRequirements:\n\n\u00a0\u00a0\u00a0\u00a0\u00a0\u00a0\u00a0\u00a0 1-2 years working experience, from the 3rd party lab ( BV, ITS, SGS\u2026)\n\u00a0\u00a0\u00a0\u00a0\u00a0\u00a0\u00a0\u00a0 Knowledge of CSR, HIGG & FSC is an advantage.\n\u00a0\u00a0\u00a0\u00a0\u00a0\u00a0\u00a0\u00a0 Excellent interpersonal and organizational skills;\n\u00a0 \u00a0 \u00a0 \u00a0 \u00a0must work well in a team-oriented environment.\n\u00a0\u00a0\u00a0\u00a0\u00a0\u00a0\u00a0\u00a0 Strong English verbal and written communication skills.\n\u00a0\u00a0\u00a0\u00a0\u00a0\u00a0\u00a0\u00a0 Self-motivated, detail-oriented, with strong analytical and communication skills.\n\u00a0\u00a0\u00a0\u00a0\u00a0\u00a0\u00a0\u00a0 Fresh graduates will also be considered.", "employment_types": ["Full Time"], "selling_points": [], "locations": ["Central"], "categories": ["Others", "Trading"], "post_time": "2022-01-15T06:50:19Z", "salary": {"currency": null, "max": null, "min": null, "period": "monthly", "term": null}, "salary_visible": false, "title_keywords": [], "responsibilities": ["regulations", "regulatory requirements", "quality", "monitor", "coordinate"], "requirements": {"degrees": [], "majors": [], "languages": ["english"], "language_level": [], "hard_skills": [], "soft_skills": ["communication skills", "organizational skills", "self-motivated", "detail-oriented", "interpersonal"], "languages_combined": [{"language": "english", "language_level": []}]}, "experience_required": {"duration": ["1-2 years"], "field": []}}, {"job_id": "100003009051683", "location_code": "hk", "company": "Special Happy Limited", "job_title": "Merchandiser / Junior Merchandiser", "description": "\n\u8077\u8cac :\u5728\u667a\u80fd\u5316\u5de5\u5177\u53ca\u7cfb\u7d71\u7684\u5354\u52a9\u4e0b\u9032\u884c\u96fb\u5b50\u96f6\u4ef6\u52a0\u5de5\u8cbc\u6a19\u751f\u7522, \u7cfb\u7d71\u4f9d\u6bcf\u65e5\u5de5\u4f5c\u91cf\u6838\u7b97\u7e3e\u6548\uff0c\u4e26\u63d0\u4f9b\u54e1\u5de5\u96a8\u6642\u67e5\u770b\u5373\u6642\u6578\u64da, \u4f9d\u6642\u5b8c\u6210\u4e3b\u7ba1\u5206\u914d\u7684\u5de5\u4f5c\u4e8b\u9805 (\u5728\u8077\u57f9\u8a13\u53ca\u826f\u597d\u6649\u5347\u6a5f\u6703\uff0c\u7a4d\u6548\u734e\u91d1)\n\n\u8cc7\u6b77 :\u6c92\u6709\u5b78\u6b77\u8981\u6c42; 1\u5e74\u7d93\u9a57; \u4e00\u822c\u7cb5\u8a9e; \u4e00\u822c\u666e\u901a\u8a71; \u61c2\u95b1\u8b80\u4e2d\u6587; \u5b88\u6642, \u6709\u8cac\u4efb\u611f, \u826f\u597d\u5de5\u4f5c\u614b\u5ea6, \u5177\u5718\u9ad4\u7cbe\u795e, \u80fd\u5373\u6642\u4e0a\u73ed\u512a\u5148, \u9700\u61c9\u4ed8\u9ad4\u529b\u52de\u52d5\u5de5\u4f5c, \u6301\u93df\u8eca\u724c\u512a\u5148\n\n\u5f85\u9047 :\u6bcf\u6708$12,000 - $18,000, \u6709\u6bcf\u6708\u52e4\u5de5\u734e\u91d1$500, \u5e74\u504710\u5929, \u9280\u884c\u5047\u671f, \u914c\u60c5\u6027\u82b1\u7d05, \u91ab\u7642\u798f\u5229, \u7a7f\u68ad\u5df4\u58eb\u670d\u52d9, \u661f\u671f\u4e00\u81f3\u516d: \u4e0a\u53489\u6642\u81f3\u4e0b\u53486\u6642, \u6bcf\u9031\u5de5\u4f5c6\u5929\n\n\u7533\u8acb\u9808\u77e5 :\u6c42\u8077\u8005\u53ef\u81f4\u96fb29423822\u8207\u5eb7\u5b8f\u7269\u6d41\u6709\u9650\u516c\u53f8\u5289\u5c0f\u59d0\u806f\u7d61\u3002\n\n", "employment_types": ["Full Time", "Permanent"], "selling_points": [], "locations": ["Tsuen Wan Area"], "categories": ["Merchandising & Purchasing", "Sundries", "Others", "Others", "Trading"], "post_time": "2022-01-16T21:50:45Z", "salary": {"currency": null, "max": null, "min": null, "period": "monthly", "term": null}, "salary_visible": false, "title_keywords": ["merchandiser", "junior merchandiser"], "responsibilities": [], "requirements": {"degrees": [], "majors": [], "languages": [], "language_level": [], "hard_skills": [], "soft_skills": [], "languages_combined": []}, "experience_required": {"duration": [], "field": []}}, {"job_id": "100003009055210", "location_code": "hk", "company": "Nexgen Packaging, Limited", "job_title": "Product Development Executive", "description": "Job Responsibilities:\n1. Responsible for full range of order management operations and activities, incl. handle all necessary documents and maintain all relevant data in ERP.\n2. Process New Product Integration (NPI), Engineering Change Notice (ECN) & transfer order in ERP system.\n3. Responsible and follow up all demand signals orders and agreement. (consignment, delivery schedule, KANBAN, outline frame contract)\n4. Ensure customer requirements are answered and delivered on-time through internal coordination.\n5. Support all activities related to claim handling relevant for order management.\n6. Report impacting and repeating factory issues to supplier management.\n7. Prepare and update Customer Specific Information (Ordering) for supervisor approval.\n8. Monitoring order booking performance for assigned customers and closely work with customer to get an update forecast and share to supplier if required.\n9. Monitor and follow up on order status to ensure on-time, correct and in-full shipment.\n10. Other tasks assigned by supervisor.\n\nJob Requirements:\n1. Professional education in technical or related field.\n2. Minimum 2-3 years of work experience in PCB related business environment.\u00a0\n3. Strong communication skills and fluent in Cantonese, English and Mandarin.\u00a0\u00a0\n4. Proficiency in all MS Office applications, ERP system experience.", "employment_types": ["Full Time"], "selling_points": [], "locations": ["Cheung Sha Wan"], "categories": ["Others", "Trading"], "post_time": "2022-01-18T01:46:21Z", "salary": {"currency": null, "max": null, "min": null, "period": "monthly", "term": null}, "salary_visible": false, "title_keywords": ["product development", "executive"], "responsibilities": ["order management", "management", "data", "operations", "monitoring", "monitor", "delivery schedule", "other tasks", "maintain", "booking", "coordination", "forecast", "report"], "requirements": {"degrees": [], "majors": [], "languages": ["cantonese", "english", "mandarin"], "language_level": ["fluent"], "hard_skills": ["erp system", "ms office"], "soft_skills": ["business environment", "communication skills"], "languages_combined": [{"language": "cantonese", "language_level": ["fluent"]}, {"language": "english", "language_level": ["fluent"]}, {"language": "mandarin", "language_level": ["fluent"]}]}, "experience_required": {"duration": ["minimum 2-3 years"], "field": ["related", "erp system", "business"]}}, {"job_id": "100003009051943", "location_code": "hk", "company": "CML EurAsia", "job_title": "Purchasing Executive", "description": "Responsibilities:\n\nFormulate marketing strategies and implement marketing plan to drive business and build corporate and brand image\nResponsible for translation and interpretation between Japanese, English and Chinese\nPlan, execute & evaluate the effectiveness of marketing campaigns that fully integrate above- and below-the-line activities and PR initiative\nSales presentation of marketing materials for various social media channels and other relevant media formats\nWork closely with internal departments and external agencies to ensure the smooth execution of marketing programs\n\nRequirements:\n\nDegree or or above in\u00a0 Japanese\u00a0translation related disciplines\nAt least 2 years marketing or translation & interpretation experience, relevant in beauty service or retail industry is definitely an advantage\nGood command of both spoken and written English, Chinese, Japanese.\u00a0 Business level in Japanese (JLPT N1 or above).\u00a0\nHighly committed and eager to drive forward initiatives and achieving results\nSelf-motivated, detail-oriented and ability to work under pressure\nGood team player with excellent communication and interpersonal skills\n\nBenefits:\n\n5-day work week(half day work on Saturday once per month)\nMarriage and Compassionate Leave\nFree hair cut & chemical service\nStaff discount\u00a0\u00a0", "employment_types": ["Full Time", "Permanent"], "selling_points": [], "locations": ["Hung Hom"], "categories": ["Manufacturing", "Production Planning / Control", "Merchandising & Purchasing", "Electronics", "Others", "Trading"], "post_time": "2022-01-17T01:35:40Z", "salary": {"currency": null, "max": null, "min": null, "period": "monthly", "term": null}, "salary_visible": false, "title_keywords": ["purchasing executive"], "responsibilities": ["social media", "marketing strategies", "evaluate", "marketing plan", "plan", "marketing campaigns", "marketing materials"], "requirements": {"degrees": ["degree"], "majors": ["related disciplines"], "languages": ["japanese", "english", "chinese"], "language_level": ["good command"], "hard_skills": ["translation"], "soft_skills": ["self-motivated", "good team player", "detail-oriented", "committed", "communication and interpersonal skills", "work under pressure"], "languages_combined": [{"language": "japanese", "language_level": ["good command"]}, {"language": "english", "language_level": ["good command"]}, {"language": "chinese", "language_level": ["good command"]}]}, "experience_required": {"duration": ["at least 2 years"], "field": ["retail industry", "marketing", "beauty"]}}, {"job_id": "100003009045660", "location_code": "hk", "company": "Merchant Ambassador (Holdings) Limited", "job_title": "Merchandiser", "description": "Main responsibilities would be:\n\nFull supervision and handling of our retail clients, mainly consisting of large multinational chain stores.\nMerchandiser role at MA is independent beginning-to-end handling of client\u2019s accounts, from quotes to shipment.\nHandling new enquiries: costing analysis, quote preparations, samples, and supervising OEM developments.\nPreparation of various order documents e.g. P/I, P/O\u2019s, vendor registration documents.\nOverseeing & organizing pre-production scheduling, lab testing issues, artwork development, and factory audit issues. Must have experience in supervising all these tasks.\nHandle full set of shipping and payment documents including L/C.\nSupervising our China based staff and vendors to ensure orders on track.\nDaily communications with customers for ongoing orders and new opportunities.\nStrong experience in merchandising role for international trading company is a must, with strength in all areas from marketing, operations, documents, logistics, payments.\nExperience handling large western retailer accounts, especially for European market, are highly desirable.\nExperience in toys industry/trading is highly desirable.\nEnergetic individual required with great communication skills in English + Cantonese + Mandarin, both verbal and written.\nMust be able to work independently, have strong \u2018multi-tasking\u2019 abilities, resourceful & pro-active.\nStrong computer skills in regular MS Office programs.\nMust be professional, high-calibre, with consistently high performance throughout career.\nImmediately available is required.\n\nPlease include resume, reference letters, and expected salary.\u00a0 Information collected will be solely for recruitment purpose.", "employment_types": ["Full Time"], "selling_points": [], "locations": ["Wong Tai Sin Area"], "categories": ["Merchandising & Purchasing", "Toy", "Others", "Others", "Trading"], "post_time": "2022-01-13T08:17:40Z", "salary": {"currency": null, "max": null, "min": null, "period": "monthly", "term": null}, "salary_visible": false, "title_keywords": ["merchandiser"], "responsibilities": ["communications with", "supervising", "shipping", "artwork development", "operations", "merchandising", "audit", "letters", "testing", "communication", "scheduling", "payment", "logistics", "payments", "recruitment", "costing analysis", "pre-production"], "requirements": {"degrees": [], "majors": [], "languages": ["cantonese", "english", "mandarin"], "language_level": [], "hard_skills": ["analysis", "vendor", "c", "computer skills", "ms office"], "soft_skills": ["communication skills", "work independently", "independent", "resourceful", "multi-tasking", "pro-active", "energetic"], "languages_combined": [{"language": "cantonese", "language_level": []}, {"language": "english", "language_level": []}, {"language": "mandarin", "language_level": []}]}, "experience_required": {"duration": [], "field": ["toys", "merchandising", "marketing", "logistics", "trading"]}}, {"job_id": "100003009045543", "location_code": "hk", "company": "Express Luck Technology Limited", "job_title": "\u8239\u52d9\u53ca\u6703\u8a08\u6587\u54e1", "description": "*\u5de5\u4f5c\u7bc4\u7587\u00a0 - \u8655\u7406\u8cbf\u6613\u6587\u4ef6\u00a0 - \u5916\u51fa\u5de5\u4f5c (\u5230\u9280\u884c\u53ca\u90f5\u5c40\u5bc4\u4ef6)\u00a0 - \u8655\u7406\u65e5\u5e38\u6703\u8a08\u5e33\u76ee (\u5165\u5e33, \u92b7\u552e\u7d00\u9304, \u4ed8\u6b3e\u53ca\u6536\u6b3e\u7d00\u9304\u7b49)\u00a0 - \u5354\u52a9\u8655\u7406\u884c\u653f\u5de5\u4f5c.\u5de5\u4f5c\u7d30\u5fc3\u3001\u52e4\u596e\u6709\u8cac\u4efb\u611f.\n*\u7d93\u9a57\u53ca\u5b78\u6b77\u00a0 - \u6703\u8a08\u7d93\u9a57\u512a\u5148\u00a0 - \u5b78\u6b77\u4e2d\u4e94\u6216\u4ee5\u4e0a\u00a0 - \u6e96\u6642\u53ca\u53ef\u7368\u7acb\u5de5\u4f5c.\n*\u719f\u8b58MS Excel \u53caMS Word, \u61c2\u4e2d\u6587\u8f38\u5165\u6cd5\u00a0 - \u6709\u8655\u7406\u8239\u52d9\u6587\u4ef6\u53caLC\u7d93\u9a57\u00a0 - \u61c2Peachtree \u6703\u8a08\u8edf\u4ef6\u512a\u5148\u00a0 - \u61c2\u82f1\u6587\u53ca\u666e\u901a\u8a71.\n*\u5f85\u9047:\u00a0 - \u5168\u8077\u5de5\u4f5c\u00a0 - 5.5\u5929\u5de5\u4f5c\u9031\u00a0 - \u9280\u884c\u5047\u671f\u00a0 - 7\u5929\u6709\u85aa\u5e74\u5047 \u2022\u00a0\u5e74\u7d42\u696d\u7e3e\u734e\u91d1", "employment_types": ["Full Time"], "selling_points": [], "locations": ["Shatin Area"], "categories": ["Others", "Trading"], "post_time": "2022-01-13T08:05:39Z", "salary": {"currency": null, "max": null, "min": null, "period": "monthly", "term": null}, "salary_visible": false, "title_keywords": [], "responsibilities": [], "requirements": {"degrees": [], "majors": [], "languages": [], "language_level": [], "hard_skills": ["excel", "word"], "soft_skills": [], "languages_combined": []}, "experience_required": {"duration": [], "field": []}}, {"job_id": "100003009047448", "location_code": "hk", "company": "Dah Chong Hong, Limited", "job_title": "Assistant Trading Officer / Trainee (Fresh Graduate Welcome)", "description": "\u5730\u9ede\uff1a\u6c99\u7530\u884c\u696d\u00a0 : \u8cbf\u6613\n\u5de5\u4f5c\u5167\u5bb9\u53ca\u8077\u8cac\uff1a\u4e00\u822c\u8239\u52d9\u6587\u54e1\u5de5\u4f5c, \u61c2\u51fa\u53e3\u4fe1\u7528\u8a3c, \u9280\u884c\u5165\u55ae.\u00a0\u5b89\u6392\u8a02\u8ca8\u53ca\u8239\u671f\u8ddf\u9032\u8a02\u55ae\u53ca\u4ea4\u8ca8\u8655\u7406\u8239\u52d9\u6587\u4ef6, \u6838\u5c0d\u63d0\u55ae, \u7522\u5730\u4f86\u6e90\u8a3c {\u8239\u904b, \u7a7a\u904b\u6587\u4ef6}\u5831\u95dc\u8239\u52d9\u8cbf\u6613\u5de5\u4f5c (\u5305\u62ec\u51fa\u8ca8\u6587\u4ef6\u53ca\u4fe1\u4ef6\u6587\u66f8\u8655\u7406, \u7269\u6d41\u5b89\u6392)\u9700\u5354\u52a9\u6703\u8a08\u90e8\u5de5\u4f5c\u53ca\u8655\u7406\u4e00\u822c\u884c\u653f\u5de5\u4f5c.\u00a0\n\u8077\u4f4d\u8981\u6c42\uff1a\u5c08\u4e0a\u6559\u80b2\uff1a\u6587\u6191/\u8b49\u66f83\u5e74\u7d93\u9a57\u826f\u597d\u7cb5\u8a9e\u512a\u5148\u4e00\u822c\u666e\u901a\u8a71\u826f\u597d\u82f1\u8a9e\u512a\u5148\u61c2\u8b80\u5beb\u4e2d\u6587\u61c2\u8b80\u5beb\u82f1\u6587\u61c2\u96fb\u5b50\u5831\u95dc\u61c2Microsoft Office\u61c2\u8655\u7406\u51fa\u5165\u53e3\u6587\u4ef6\u5177\u6709\u4e00\u822c\u6703\u8a08\u77e5\u8b58\u61c2\u4e2d\u82f1\u6587\u96fb\u8166\u64cd\u4f5c\u80fd\u7368\u7acb\u8655\u7406\u4e8b\u60c5\u548c\u80fd\u5728\u58d3\u529b\u4e0b\u5de5\u4f5c\u70ba\u4eba\u53ef\u9760\u6709\u8cac\u4efb\u5fc3\u9700\u6709\u6703\u8a08\u76f8\u95dc\u7d93\u9a57\n\u85aa\u91d1\u3001\u798f\u5229\u53ca\u5de5\u4f5c\u6642\u9593\uff1a\u85aa\u91d1\u9762\u8b70\u6709\u9280\u884c\u5047\u671f\u00a0\u661f\u671f\u4e00\u81f3\u4e94: \u4e0a\u53489\u6642\u81f3\u4e0b\u53486\u6642\u53ca\u661f\u671f\u516d[\u8f2a\u73ed]: \u4e0a\u53489\u6642\u81f3\u4e0b\u53481\u6642\u6bcf\u9031\u5de5\u4f5c5\u5929\u81f35\u5929\u534a\u6bcf\u5929\u5de5\u4f5c 9 \u5c0f\u6642", "employment_types": ["Full Time", "Permanent"], "selling_points": [], "locations": ["Kowloon Bay"], "categories": ["Merchandising & Purchasing", "Procurement / Purchasing / Sourcing", "Sales, CS & Business Devpt", "Channel / Distribution", "Others", "Trading"], "post_time": "2022-01-14T03:06:58Z", "salary": {"currency": null, "max": null, "min": null, "period": "monthly", "term": null}, "salary_visible": false, "title_keywords": ["officer", "assistant", "trainee"], "responsibilities": [], "requirements": {"degrees": [], "majors": [], "languages": [], "language_level": [], "hard_skills": [], "soft_skills": [], "languages_combined": []}, "experience_required": {"duration": [], "field": []}}, {"job_id": "100003009049524", "location_code": "hk", "company": "Brother Machinery (Asia) Limited", "job_title": "Customer Service Officer / After Sales Coordinator / Sales Associate / Sales Assistant", "description": "Responsibilities\n\n\nResponsible for the coordination of the assigned food category sourcing and trading,\nNegotiate better prices with vendors and\u00a0business correspondence,\u00a0\nLiaise with customers and suppliers\nPrepare market analysis reports to explore new business development\nWork closely with internal department to ensure operation efficiency\n\nRequirement\n\nUniversity graduate or above in Business Administration or equivalent;\n1 to 2 years working experience is preferred;\nHardworking, independent and self-motivated with excellent communication skills\nProficient in written and spoken English and Chinese;\nProficiency in MS Office (Word, Excel, PowerPoint);\nFresh graduate will be considered.\nPlease send your application with resume and expected salary to The HR Manager, Dah Chong Hong, Ltd, 8/F, DCH Building, 20 Kai Cheung Road, Kowloon Bay by post or click\u00a0\"Apply Now\".\n\nInformation provided will be for the purpose of selection within the company and only shortlisted candidates will be contacted. All applications will be retained for a maximum period of 6 months.\u00a0", "employment_types": ["Full Time", "Permanent"], "selling_points": [], "locations": ["Kwai Hing"], "categories": ["Sales, CS & Business Devpt", "Customer Service - Supervisor / Officer", "Transportation & Logistics", "Shipping", "Others", "Trading"], "post_time": "2022-01-15T03:50:29Z", "salary": {"currency": null, "max": null, "min": null, "period": "monthly", "term": null}, "salary_visible": false, "title_keywords": ["sales coordinator", "sales assistant", "customer service officer", "sales associate"], "responsibilities": ["liaise with", "market analysis", "reports", "coordination"], "requirements": {"degrees": ["university graduate or above", "fresh graduate"], "majors": ["business administration"], "languages": ["english", "chinese"], "language_level": ["proficient"], "hard_skills": ["excel", "word", "powerpoint", "ms office"], "soft_skills": ["communication skills", "self-motivated", "independent", "hardworking"], "languages_combined": [{"language": "english", "language_level": ["proficient"]}, {"language": "chinese", "language_level": ["proficient"]}]}, "experience_required": {"duration": ["1 to 2 years"], "field": []}}, {"job_id": "100003009049888", "location_code": "hk", "company": "Benetton Asia Pacific Limited", "job_title": "Shipping Clerk", "description": "Build and maintain strong relationship with clients to provide excellence after sales service and support\nDaily operations including customer enquiries follow up, and orders in ERP system, etc.\nCo-ordinate closely with internal suppliers to meet delivery schedule and quality sales services.\nParts inventory control for maintain a stable supply within reasonable stock level.\nArrange logistics (delivery, shipping, import and export declarations)\nProvide administration and secretarial support\nAssist in ad hoc duties assigned by manager\n\nTraining & Development\nProvide in house E-learning platform and study subsidy for job related topics\n\nOur Ideal Candidate\n\n\n3 years or above sales associate / coordinator experience / fresh graduate with potential will also be considered\nGood command of written and spoken English\u00a0\nAttention to details, self-motivated, sensible in problem solving and able to work independently\nGood PC skills (Excel and Outlook) with Chinese types & MS Office\nExperience of ERP system (SAP, Salesforce etc) will be advantage\nImmediate availability is preferred\n\nStaff Benefits\n\n5 days work\nBank Holiday\nFlexible Working Hours\nWork From Home\nTransportation Allowance\nMedical & Dental Insurance\nBody check\n\nInterested?\nIf you are interested please send your\u00a0full resume,\u00a0current\u00a0and\u00a0expected salary\u00a0and\u00a0availability\u00a0by clicking \"APPLY NOW\".\n\n*Personal data provided are treated in strictest confidence and for recruitment purposes only.\u00a0 All information will be destroyed after the process completed.*", "employment_types": ["Full Time", "Permanent"], "selling_points": ["5-Day Work Week", "Flexible working hour", "Family care leave"], "locations": ["Kowloon Bay"], "categories": ["Transportation & Logistics", "Shipping", "Supply Chain", "Others", "Trading"], "post_time": "2022-01-14T09:24:00Z", "salary": {"currency": null, "max": null, "min": null, "period": "monthly", "term": null}, "salary_visible": false, "title_keywords": ["shipping clerk"], "responsibilities": ["ad hoc duties", "shipping", "customer enquiries", "quality", "delivery schedule", "daily operations", "maintain", "inventory control", "logistics", "secretarial support", "administration"], "requirements": {"degrees": ["fresh graduate"], "majors": [], "languages": ["english", "chinese"], "language_level": ["good command", "good"], "hard_skills": ["excel", "salesforce", "sap", "import and export", "problem solving", "erp system", "outlook", "pc skills", "ms office"], "soft_skills": ["self-motivated", "work independently", "problem solving", "learning", "attention to details", "stable", "ideal"], "languages_combined": [{"language": "english", "language_level": ["good command", "good"]}, {"language": "chinese", "language_level": ["good"]}]}, "experience_required": {"duration": ["3 years"], "field": ["erp system"]}}, {"job_id": "100003009050718", "location_code": "hk", "company": "", "job_title": "Sales Co-Ordinator (5 days work)", "description": "Responsibilities\n\n\nResponsible for general shipping document control and I/E declaration\nCommunicate with internal department, suppliers and Italy headquarter\nFollowing with suppliers as control shipment in all shipping method\nHandling correspondence with external vendors & suppliers\nAssist in daily administrative duties of the department\n\nJob Requirements\n\nHKCEE/HKDSE or above\n2-3 years shipping experience and familiar in Garment field at buying office is preferable\nExperience in dealing with the factory and forwarding agent\nAble to work independent and under pressure\nFamiliar with MS Excel and Word\nProficiency in English and Mandarin, good writing skills is preferred\nResponsible and committed. Details Oriented with good numerical sense\nFresh graduate will also be considered\nImmediate available is highly preferred\n\nWe offer 5-day work week, extended paternity leave, family care leave, birthday leave and good career development opportunities in a young and dynamic environment. Interested parties, please send your resume, quoting the reference no. and stating your current & expected salary to Benetton Asia Pacific Limited by clicking\u00a0 \"Apply Now\".\n\n(Personal data collected will be used for recruitment purpose only)", "employment_types": ["Full Time", "Permanent"], "selling_points": ["Chance of promotion", "experience is preferable", "Form 6 or above"], "locations": ["Kwun Tong"], "categories": ["Others", "Trading"], "post_time": "2022-01-14T11:13:58Z", "salary": {"currency": null, "max": null, "min": null, "period": "monthly", "term": null}, "salary_visible": false, "title_keywords": ["sales"], "responsibilities": ["communicate with", "control", "shipping", "administrative duties", "shipping document"], "requirements": {"degrees": ["hkdse", "fresh graduate"], "majors": [], "languages": ["english", "mandarin"], "language_level": ["proficiency", "good"], "hard_skills": ["ms excel", "dynamic", "word", "writing skills"], "soft_skills": ["dynamic environment", "independent", "under pressure", "responsible", "writing skills", "committed"], "languages_combined": [{"language": "english", "language_level": ["proficiency", "good"]}, {"language": "mandarin", "language_level": ["proficiency", "good"]}]}, "experience_required": {"duration": ["2-3 years"], "field": ["garment"]}}, {"job_id": "100003009051486", "location_code": "hk", "company": "Kingly Agents Limited", "job_title": "CLERK", "description": "We are looking for a Sales Assistant to work at Kwun Tong with the following requirement:\n\nMinimum 2 year experience in similar field\nExperience with ERP system and/or other database system is a plus\nGood written and spoken English and Chinese\nMature person and able to work independently\nProficient in MS Office\nImmediate availability preferred\n\n\u00a0Job description:\u00a0 1. Responsibilities for sales support;\u00a0\n\u00a0 \u00a0 \u00a0 \u00a0 \u00a0 \u00a0 \u00a0 \u00a0 \u00a0 \u00a0 \u00a0 \u00a0 \u00a0 \u00a0 \u00a02. prepare sales quotations and shipping documents\n\u00a0 \u00a0 \u00a0 \u00a0 \u00a0 \u00a0 \u00a0 \u00a0 \u00a0 \u00a0 \u00a0 \u00a0 \u00a0 \u00a0 \u00a03. Communicate with customers where need\n\u00a0 \u00a0 \u00a0 \u00a0 \u00a0 \u00a0 \u00a0 \u00a0 \u00a0 \u00a0 \u00a0 \u00a0 \u00a0 \u00a0 \u00a04. Liaise with factory for sales order follow up\n\u00a0 \u00a0 \u00a0 \u00a0 \u00a0 \u00a0 \u00a0 \u00a0 \u00a0 \u00a0 \u00a0 \u00a0 \u00a0 \u00a0 \u00a05. Assist with delivery arrangements\n\u00a0 \u00a0 \u00a0 \u00a0 \u00a0 \u00a0 \u00a0 \u00a0 \u00a0 \u00a0 \u00a0 \u00a0 \u00a0 \u00a0 \u00a06. Other ad hoc duties\n\u00a0 \u00a0 \u00a0 \u00a0 \u00a0 \u00a0 \u00a0\n\nInterested candidates, please contact us at 37602888 for company details before applying.", "employment_types": ["Full Time"], "selling_points": [], "locations": ["Kwai Tsing Area"], "categories": ["Admin & HR", "Clerical / Admin Staff", "Sales, CS & Business Devpt", "Others", "Others", "Trading"], "post_time": "2022-01-16T04:13:46Z", "salary": {"currency": null, "max": null, "min": null, "period": "monthly", "term": null}, "salary_visible": false, "title_keywords": ["clerk"], "responsibilities": ["shipping documents", "communicate with", "ad hoc duties", "prepare sales", "database", "liaise with"], "requirements": {"degrees": [], "majors": [], "languages": ["english", "chinese"], "language_level": ["good"], "hard_skills": ["erp system", "sales support", "ms office", "plus"], "soft_skills": ["work independently", "mature"], "languages_combined": [{"language": "english", "language_level": ["good"]}, {"language": "chinese", "language_level": ["good"]}]}, "experience_required": {"duration": ["minimum 2 year"], "field": ["erp system", "database"]}}, {"job_id": "100003009045542", "location_code": "hk", "company": "Wilson Service Limited", "job_title": "\u8fa6\u516c\u5ba4\u52a9\u7406", "description": "CLERK\n\nForm 5 or above.\nGood communication skill\u00a0of Cantonese, English and Mandarin.\nCan\u00a0response\u00a0the client enquiry by phone, follow up the order and issue sales invoice.\nGood knowledge to use MS Office (Excel and Word).\nMature, independent and responsibility.\nBank holiday and annual performance bonus.\nKwai Chung area.\n\nPlease email your resume with expected salary to our email address.\n\nAll personal data provided by job applicants will be used for recruitment purpose only.\n\nDBcampaignaviation\n", "employment_types": ["Full Time"], "selling_points": [], "locations": ["Ngau Tau Kok"], "categories": ["Admin & HR", "Clerical / Admin Staff", "Others", "Others", "Trading"], "post_time": "2022-01-13T08:03:33Z", "salary": {"currency": null, "max": null, "min": null, "period": "monthly", "term": null}, "salary_visible": false, "title_keywords": ["\u8fa6\u516c\u5ba4\u52a9\u7406"], "responsibilities": ["communication", "personal data", "recruitment", "invoice"], "requirements": {"degrees": ["form 5 or above"], "majors": [], "languages": ["cantonese", "english", "mandarin"], "language_level": ["good"], "hard_skills": ["excel", "word", "ms office"], "soft_skills": ["communication skill", "independent", "mature"], "languages_combined": [{"language": "cantonese", "language_level": ["good"]}, {"language": "english", "language_level": ["good"]}, {"language": "mandarin", "language_level": ["good"]}]}, "experience_required": {"duration": [], "field": []}}, {"job_id": "100003008374626", "location_code": "hk", "company": "Daum (Hong Kong) Limited", "job_title": "Operation Assistant", "description": "\n\u8077\u8cac :\u63a5\u807d\u96fb\u8a71,\u4e00\u822c\u96fb\u8166\u6587\u66f8\u5de5\u4f5c\u53ca\u8655\u7406\u65e5\u5e38\u96fb\u90f5,\u4e2d\u82f1\u6587\u8cc7\u6599\u96fb\u8166\u8f38\u5165,\u9700\u5916\u51fa\u8655\u7406\u9280\u884c\u4e8b\u52d9\u53ca\u516c\u53f8\u4e8b\u5b9c\n\n\u8cc7\u6b77 :\u4e2d\u4e94\u7a0b\u5ea6; 1\u5e74\u7d93\u9a57; \u826f\u597d\u7cb5\u8a9e\u512a\u5148; \u4e00\u822c\u666e\u901a\u8a71; \u4e00\u822c\u82f1\u8a9e\u512a\u5148; \u61c2\u8b80\u5beb\u4e2d\u6587; \u7565\u61c2\u8b80\u5beb\u82f1\u6587; \u61c2\u96fb\u8166\u6587\u66f8\u8655\u7406; \u61c2Microsoft Office; \u61c2\u5009\u9821/\u901f\u6210\u8f38\u5165\u6cd5; \u5177\u57fa\u672c\u63a5\u807d\u96fb\u8a71\u6280\u5de7, \u80fd\u65bc\u58d3\u529b\u4e0b\u5de5\u4f5c, \u5de5\u4f5c\u7a4d\u6975, \u6709\u8cac\u4efb\u611f, \u5177\u7368\u7acb\u5de5\u4f5c\u53ca\u826f\u597d\u6e9d\u901a\u6280\u5de7\n\n\u5f85\u9047 :\u6bcf\u6708$12,000 - $13,000, \u6709\u5e74\u7d42\u734e\u91d1, \u661f\u671f\u4e00\u81f3\u4e94: \u4e0a\u53489\u6642\u534a\u81f3\u4e0b\u53486\u6642\u53ca\u661f\u671f\u516d: \u4e0a\u53489\u6642\u534a\u81f3\u4e0b\u53481\u6642, \u6bcf\u9031\u5de5\u4f5c5\u5929\u534a, \u6bcf\u5929\u5de5\u4f5c 8.5 \u5c0f\u6642\n\n\u7533\u8acb\u9808\u77e5 :\u6c42\u8077\u8005\u53ef\u96fb\u90f5(Apply Now)\u5c65\u6b77\u8868\u7d66\u5a01\u4fe1\u670d\u52d9\u6709\u9650\u516c\u53f8\u3002\u5982\u8981\u7d22\u53d6\u6536\u96c6\u500b\u4eba\u8cc7\u6599\u8072\u660e, \u8acb\u8207\u90ed\u5148\u751f(Email)\u806f\u7d61\u3002\n\n", "employment_types": ["Full Time", "Permanent", "Contract", "Internship"], "selling_points": ["Administrative, Stock, Logistic", "Keen to learn, flexible, good at organizing data", "Team player"], "locations": ["Wan Chai Area"], "categories": ["Admin & HR", "Administration / Operation Manager", "Transportation & Logistics", "Inventory / Warehousing", "Others", "Trading"], "post_time": "2022-01-14T07:33:38Z", "salary": {"currency": null, "max": null, "min": null, "period": "monthly", "term": null}, "salary_visible": false, "title_keywords": ["operation assistant"], "responsibilities": [], "requirements": {"degrees": [], "majors": [], "languages": [], "language_level": [], "hard_skills": [], "soft_skills": [], "languages_combined": []}, "experience_required": {"duration": [], "field": []}}, {"job_id": "100003009045439", "location_code": "hk", "company": "Ji Xiang Exchange Remittance Limited", "job_title": "\u898b\u7fd2\u627e\u63db\u54e1/\u7d93\u9a57\u627e\u63db\u54e1", "description": "JOB DESCRIPTION\n\nWhat you will do:\n\nAdministrative:\n- Managing and displaying products in the showroom\n- Data entering \u2013 orders, shipments, customer database, invoices\n- Preparing petty cash list\n- Filing and recording all the office utilities and fee bill\n- Responsible for all-rounded administration work in the office\nStock management:\n- Preparing bar code labels for new stocks\n- Stock taking every 4 months\n- Updating stock ad consignment records\nLogistic:\n- Managing and unpacking the new arrival goods in warehouse/ office\n- Arranging to shipment to our customers from different markets\nAd-hoc duties of assisting sales and marketing projects assigned\n\nREQUIREMENT\n- Undergraduate / fresh graduates are welcome\n- 1- 2 years working experiences\n- Proficient in using Microsoft Words, Excels (Vlookup, Iferror, etc)\n-\u00a0Good spoken and written in Cantonese/ English/ Mandarin\n- Keen to learn, detail-minded, and a good team player with good communication and interpersonal skills\n\nBENEFITS\n- Career progression opportunities\n- Free medical package\n- 13th month\n- 5 days working", "employment_types": ["Full Time"], "selling_points": [], "locations": ["Sheung Wan"], "categories": ["Others", "Trading", "Others"], "post_time": "2022-01-13T07:51:35Z", "salary": {"currency": null, "max": null, "min": null, "period": "monthly", "term": null}, "salary_visible": false, "title_keywords": [], "responsibilities": ["stock management", "invoices", "data", "marketing projects", "database", "ad-hoc duties", "administration"], "requirements": {"degrees": [], "majors": [], "languages": ["cantonese", "english", "mandarin"], "language_level": ["good"], "hard_skills": ["vlookup", "words"], "soft_skills": ["detail-minded", "keen", "good team player", "communication and interpersonal skills"], "languages_combined": [{"language": "cantonese", "language_level": ["good"]}, {"language": "english", "language_level": ["good"]}, {"language": "mandarin", "language_level": ["good"]}]}, "experience_required": {"duration": ["1- 2 years"], "field": []}}, {"job_id": "100003009050001", "location_code": "hk", "company": "Shun Hing Electronic Trading Co Ltd", "job_title": "Marketing Executive", "description": "\n\u8077\u8cac :\u670d\u52d9\u9867\u5ba2, \u8ca0\u8cac\u5916\u5e63\u514c\u63db\u53ca\u532f\u6b3e\u670d\u52d9, \u4e00\u822c\u73fe\u91d1\u8655\u7406\u5de5\u4f5c, \u5982\u73fe\u91d1\u9a57\u8b49\u3001\u9ede\u7b97\u53ca\u5206\u985e\u3001\u89e3\u7b54\u5ba2\u6236\u67e5\u8a62\u3001\u4e00\u822c\u6587\u66f8\u5de5\u4f5c\n\n\u8cc7\u6b77 :\u4e2d\u4e09\u7a0b\u5ea6; 1\u5e74\u7d93\u9a57; \u826f\u597d\u7cb5\u8a9e; \u4e00\u822c\u666e\u901a\u8a71; \u4e00\u822c\u82f1\u8a9e; \u61c2\u8b80\u5beb\u4e2d\u6587; \u7565\u61c2\u8b80\u5beb\u82f1\u6587; \u61c2\u96fb\u8166\u6587\u66f8\u8655\u7406; \u61c2MS Excel; \u61c2\u4e2d\u6587\u6253\u5b57; \u5177\u6709\u57fa\u672c\u96fb\u8166\u64cd\u4f5c\u77e5\u8b58\n\n\u5f85\u9047 :\u6bcf\u6708$12,000 - $16,000, \u6709\u6bcf\u6708\u52e4\u5de5\u734e\u91d1$500, \u661f\u671f\u4e00\u81f3\u516d: \u4e0a\u53489\u6642\u81f3\u4e0b\u53487\u6642, \u6bcf\u9031\u5de5\u4f5c6\u5929, \u6bcf\u5929\u5de5\u4f5c 10 \u5c0f\u6642\n\n\u7533\u8acb\u9808\u77e5 :\u6c42\u8077\u8005\u53ef\u81f4\u96fb60550569\u8207\u5409\u7965\u627e\u63db\u532f\u6b3e\u6709\u9650\u516c\u53f8\u5433\u5c0f\u59d0\u806f\u7d61\u3002\n\n", "employment_types": ["Full Time", "Permanent"], "selling_points": [], "locations": ["Tsim Sha Tsui"], "categories": ["Others", "Trading"], "post_time": "2022-01-14T09:37:17Z", "salary": {"currency": null, "max": null, "min": null, "period": "monthly", "term": null}, "salary_visible": false, "title_keywords": ["marketing executive"], "responsibilities": [], "requirements": {"degrees": [], "majors": [], "languages": [], "language_level": [], "hard_skills": ["excel"], "soft_skills": [], "languages_combined": []}, "experience_required": {"duration": [], "field": []}}, {"job_id": "100003009049551", "location_code": "hk", "company": "Tin Hang Technology Limited", "job_title": "Accounts Clerk", "description": "Marketing Executive\n\nResponsibilities:\n\nPlan and execute marketing campaign of brand image and product promotion as well as Shun Hing Cooking Centre\nWork closely with sales divisions and develop marketing activities\nWork closely with business partners and clients to arrange marketing activities\nKeep monitoring of competitors\u2019 promotion activities to get updated market information\n\nRequirements:\n\nDegree Holder in Business, Marketing or related discipline\nMinimum 2 years\u2019 working experience in sales & marketing field\nGood interpersonal skills with analytical mindset\nProficient in computer application\nGood command of English and Chinese\nIELTS score 6.5 or above preferable\nCandidates with more experience will be considered as Senior Marketing Executive.\n\n\n\nWe offer 5-day work week. Please apply by sending your full resume with indication of current & expected salary to:\n\n\nBy Email:\n[Apply Now\u00a0]\n\nBy Post:\nGroup Human Resources Manager\nShun Hing Electronic Holdings Ltd.\n14/F & 15/F., New East Ocean Centre\n9 Science Museum Road\nTsimshatsui East\nKowloon\n\nFor more information about our Group, please visit our website:\u00a0http://www.shunhinggroup.com\n\nData collected will be used for recruitment purpose only. It may be transferred to other companies of the Group to see if suitable vacancies arise. Applicants not contacted within 6 weeks may consider their application unsuccessful. The information will be destroyed.", "employment_types": ["Full Time"], "selling_points": [], "locations": ["Sheung Wan"], "categories": ["Accounting", "Others", "Others", "Trading"], "post_time": "2022-01-14T08:57:59Z", "salary": {"currency": null, "max": null, "min": null, "period": "monthly", "term": null}, "salary_visible": false, "title_keywords": ["accounts clerk"], "responsibilities": ["monitoring", "market information", "plan", "develop"], "requirements": {"degrees": ["degree holder"], "majors": ["business", "marketing"], "languages": ["english", "chinese"], "language_level": ["good command"], "hard_skills": [], "soft_skills": ["interpersonal skills"], "languages_combined": [{"language": "english", "language_level": ["good command"]}, {"language": "chinese", "language_level": ["good command"]}]}, "experience_required": {"duration": ["minimum 2 years"], "field": ["marketing"]}}, {"job_id": "100003009048088", "location_code": "hk", "company": "Active Components (HK) Ltd", "job_title": "Senior Logistics Officer", "description": "Job Responsibilities:\n\nHandle general accounting duties, with emphasis on A/R and G/L\nPrepare vouchers and accruals as assigned\nAssist in system implementation\nHandle data entries, filling and documentation\n\nSkills &\u00a0Requirements:\n\nF.5 or Diploma holder in Accountancy\nLCC Intermediate with 1 year working experience\nGood PC skill of MS Word, Excel & Chinese Word Processing\nResponsible and hard working\nFair in Mandarin /English\nImmediate available is highly preferred", "employment_types": ["Full Time", "Permanent"], "selling_points": [], "locations": ["Kwun Tong"], "categories": ["Transportation & Logistics", "Inventory / Warehousing", "Supply Chain", "Others", "Trading"], "post_time": "2022-01-14T04:49:22Z", "salary": {"currency": null, "max": null, "min": null, "period": "monthly", "term": null}, "salary_visible": false, "title_keywords": ["senior logistics officer"], "responsibilities": ["documentation", "general accounting duties", "implementation", "data"], "requirements": {"degrees": ["diploma holder"], "majors": ["accountancy"], "languages": ["english", "chinese", "mandarin"], "language_level": ["good"], "hard_skills": ["excel", "chinese word processing", "pc skill", "lcc", "ms word"], "soft_skills": ["hard working", "responsible"], "languages_combined": [{"language": "english", "language_level": []}, {"language": "chinese", "language_level": ["good"]}, {"language": "mandarin", "language_level": []}]}, "experience_required": {"duration": ["1 year"], "field": []}}, {"job_id": "100003009048382", "location_code": "hk", "company": "G.A. Operations Hong Kong Limited", "job_title": "Merchandiser - Technical in Fashion & Textiles", "description": "Responsibilities\n\n\u00a0\u00a0\u00a0\u00a0\u00a0\u00a0\u00a0\u00a0 Setting up freight pattern/freight guideline for suppliers and customers\n\u00a0\u00a0\u00a0\u00a0\u00a0\u00a0\u00a0\u00a0 Cost control/negotiation on freight with 3PL\n\u00a0\u00a0\u00a0\u00a0\u00a0\u00a0\u00a0\u00a0 Overseeing incoming and outgoing shipments\n\u00a0\u00a0\u00a0\u00a0\u00a0\u00a0\u00a0\u00a0 Organizing regular container shipment from HK\n\u00a0\u00a0\u00a0\u00a0\u00a0\u00a0\u00a0\u00a0 Overseeing warehouse in HK\n\u00a0\u00a0\u00a0\u00a0\u00a0\u00a0\u00a0\u00a0 Generating freight related reports\n\u00a0\u00a0\u00a0\u00a0\u00a0\u00a0\u00a0\u00a0 Liaising with factories, forwarders and internal departments (HK and oversea)\n\nRequirements\n\n\nDegree or above\nExperience in related field and ERP system is highly preferred\nProficient in MS Office\nGood command of written and spoken English, Cantonese and Mandarin\nAble to work independently, proactive and being a good team player\nImmediate availability/Short-notice is preferred\n\nPlease submit your resume with expected salary and availability by clicking \"Apply now\".", "employment_types": ["Full Time", "Permanent"], "selling_points": [], "locations": ["Kowloon Bay"], "categories": ["Others", "Trading"], "post_time": "2022-01-14T06:27:11Z", "salary": {"currency": null, "max": null, "min": null, "period": "monthly", "term": null}, "salary_visible": false, "title_keywords": ["merchandiser"], "responsibilities": ["reports", "liaising with", "cost control"], "requirements": {"degrees": ["degree or above"], "majors": [], "languages": ["cantonese", "english", "mandarin"], "language_level": ["good command"], "hard_skills": ["erp system", "ms office"], "soft_skills": ["good team player", "work independently", "proactive"], "languages_combined": [{"language": "cantonese", "language_level": ["good command"]}, {"language": "english", "language_level": ["good command"]}, {"language": "mandarin", "language_level": ["good command"]}]}, "experience_required": {"duration": [], "field": ["related", "erp system"]}}, {"job_id": "100003009043238", "location_code": "hk", "company": "HTIC Limited", "job_title": "Experienced Shipping Clerk/Officer", "description": "Handle full set shipping documents\nCan work independently\nGood computer skills, analytical\nForm 5 or above\nAt least 3-4 years shipping experience\nGood communication skills in English and Mandarin\u00a0\u00a0\u00a0\u00a0\u00a0\u00a0", "employment_types": ["Full Time"], "selling_points": [], "locations": ["Others"], "categories": ["Others", "Trading"], "post_time": "2022-01-12T10:19:30Z", "salary": {"currency": null, "max": null, "min": null, "period": "monthly", "term": null}, "salary_visible": false, "title_keywords": ["experienced shipping clerk", "officer"], "responsibilities": ["shipping documents", "shipping", "communication"], "requirements": {"degrees": ["form 5 or above"], "majors": [], "languages": ["english", "mandarin"], "language_level": ["good"], "hard_skills": ["computer skills"], "soft_skills": ["communication skills", "work independently"], "languages_combined": [{"language": "english", "language_level": ["good"]}, {"language": "mandarin", "language_level": ["good"]}]}, "experience_required": {"duration": ["at least 3-4 years"], "field": []}}, {"job_id": "100003009048845", "location_code": "hk", "company": "Merlion Resources Holdings Limited", "job_title": "Office Clerk", "description": "Job Description\n\nResponsible for data inputting, emails reply, filing and preparation of invoice.\nDirect communicate with clients for merchandise follow up.\nGeneral clerical duties.\nSelf-motivated, detail-minded, able to work independently and responsible\n\u00a0Office in Wanchai.\n\u00a0Full Time:\u00a0 9:30am - 6:00pm\u00a0 \u00a0Mon- Fri\nImmediately available preferred\n\nRequirements\n\nUniversity graduated\u00a0\nProficient in spoken and written English and Mandarin preferable.\nGood telephone manner and interpersonal skill\nStrong ability in team player with positive attitude to work with different parties\nProficient in Microsoft Office and Excel\nImmediately available preferred", "employment_types": ["Full Time", "Permanent"], "selling_points": ["Fresh graduated degree", "Physical trade learning opportunities", "Salary $14K or above, 5 days working"], "locations": ["Wan Chai"], "categories": ["Admin & HR", "Clerical / Admin Staff", "Others", "Trading"], "post_time": "2022-01-15T03:50:35Z", "salary": {"currency": "HKD", "max": 16999, "min": 14000, "period": "monthly", "term": null}, "salary_visible": true, "title_keywords": ["office clerk"], "responsibilities": ["communicate with", "preparation of invoice", "data"], "requirements": {"degrees": [], "majors": [], "languages": ["english", "mandarin"], "language_level": ["proficient"], "hard_skills": ["excel", "microsoft office"], "soft_skills": ["positive attitude", "team player", "telephone manner", "interpersonal skill"], "languages_combined": [{"language": "english", "language_level": ["proficient"]}, {"language": "mandarin", "language_level": ["proficient"]}]}, "experience_required": {"duration": [], "field": []}}, {"job_id": "100003009044100", "location_code": "hk", "company": "Formica (Asia) Ltd", "job_title": "Sales Supervisor/Specialist", "description": "Formica (Asia) Limited, the world\u2019s best known decorative material manufacturer is looking for high calibers to fill up the following position:\n\nJob Responsibilities:\n\n- Responsible for selling and promote products (e.g. HPL, Cubicle System, Countertop Surfacing)\n\n- Good communication with customers (e.g. contractors, designers, architects)\n\n- Provide high quality service to customers\n\n- Work closely with team members to achieve sales target\n\nRequirements:\n\nSales Supervisor: 5 years of sales experience in building material industry is a must\n\nEducation for Sales Supervisor: Degree Holder preferable\n\nSales Specialist:\u00a02 years of sales experience in building material industry preferred\n\nEducation for Sales Specialist: Tertiary Education preferable\n\nGood command in English, Chinese and Putonghua\n\nProactive and aggressive with outgoing personality\n\nRecent graduates will be considered", "employment_types": ["Full Time"], "selling_points": ["famous building materials banding", "1.5 months year end bonus", "performance incentive"], "locations": ["North Point"], "categories": ["Marketing / Public Relations", "Marketing - Direct Marketing", "Others", "Trading", "Sales, CS & Business Devpt", "Direct Sales"], "post_time": "2022-01-13T03:03:50Z", "salary": {"currency": null, "max": null, "min": null, "period": "monthly", "term": null}, "salary_visible": false, "title_keywords": ["specialist", "sales supervisor"], "responsibilities": ["communication", "sales target", "quality", "promote products"], "requirements": {"degrees": ["degree holder"], "majors": [], "languages": ["putonghua", "english", "chinese"], "language_level": ["good command"], "hard_skills": [], "soft_skills": ["outgoing personality", "proactive"], "languages_combined": [{"language": "putonghua", "language_level": ["good command"]}, {"language": "english", "language_level": ["good command"]}, {"language": "chinese", "language_level": ["good command"]}]}, "experience_required": {"duration": ["5 years", "2 years"], "field": []}}, {"job_id": "100003009045175", "location_code": "hk", "company": "Fung Yuen Nursery Home For The Aged Limited", "job_title": "\u8fa6\u516c\u5ba4\u52a9\u7406", "description": "We would like to invite an open-minded and resilient person who is willing to adapt to new challenges and to improve and achieve company and team goals to join us. The job incumbent will provide technical services to support the Research and Development and the Production teams.\n\nKey Responsibilities:\n\n\nResponsible for editing of Tech Pack (BOM) including the encoding and uploading\u00a0of raw materials in the system\nGarment engineering analysis and review in SMS and Production stages to check if\u00a0any discrepancies from Tech Pack\nMake sure the implementation of technical procedures based on the business needs\nHandle care label approval including washing care instructions\nWorkmanship checking and uploading to suppliers\nJob Requirements:\n\nDiploma holder or above in Textile & Fashion or related disciplines\n2 - 3 years of relevant technical experience\nProactive, meticulous, organized, self-motivated and good teamwork\nGood communication, time management and multi-tasking skills\nProficiency in Microsoft Excel, Word, PowerPoint and Chinese Word Processing\nGood written and spoken English & Chinese", "employment_types": ["Full Time"], "selling_points": [], "locations": ["Shau Kei Wan"], "categories": ["Admin & HR", "Clerical / Admin Staff", "Others", "Others", "Trading"], "post_time": "2022-01-13T07:23:00Z", "salary": {"currency": null, "max": null, "min": null, "period": "monthly", "term": null}, "salary_visible": false, "title_keywords": ["\u8fa6\u516c\u5ba4\u52a9\u7406"], "responsibilities": ["analysis", "review", "procedures", "implementation", "checking", "editing"], "requirements": {"degrees": ["diploma holder"], "majors": ["related disciplines"], "languages": ["english", "chinese"], "language_level": ["proficiency", "good"], "hard_skills": ["chinese word processing", "word", "powerpoint", "microsoft excel"], "soft_skills": ["organized", "meticulous", "self-motivated", "teamwork", "communication", "time management", "multi-tasking skills", "proactive"], "languages_combined": [{"language": "english", "language_level": ["good"]}, {"language": "chinese", "language_level": ["proficiency", "good"]}]}, "experience_required": {"duration": ["2 - 3 years"], "field": []}}, {"job_id": "100003009044513", "location_code": "hk", "company": "Global Packaging Limited", "job_title": "Account Executive", "description": "Job Descriptions:\n\nLiaise with overseas clients and factories independently\nIndependently in handling projects follow up from sampling development to production\nHandle orders and monitor production process\nPrepare quotations, sampling and monthly reports\nOccasional travel to overseas if needed\n\nRequirements:\n\nHigh Diploma or above with 2 years relevant working experience\nWith solid printing knowledge\u00a0for garment accessories is preferred\nFluent language skills (written and oral) in English, Mandarin and Cantonese\nAble to work independent, detailed oriented, well organized & under pressure within a tight schedule\nProficient in MS office and English + Chinese word processing\nGood team player and work independently\n\nSalary Range: Negotiable\n\nBenefits:\n\n-Bank holiday\n\n-12~25 days annual leave or above\n\n-5 days working per week\n\n-Medical scheme\n\n-13 months salary\n\n-Performance based Bonus (not guarantee)\n\nWe provide attractive remuneration packages to the right candidates. Interested parties please send following by clicking \"APPLY NOW\".\n\nDetailed curriculum vitae/resume\nDate of availability\nExpected salary\n\n(All personal data provided will be treated in strict confidence and used for recruitment purposed only.)", "employment_types": ["Full Time"], "selling_points": ["High Diploma or above with 2 years relevant work", "With solid printing knowledge is preferred", "5 days working"], "locations": ["Kwai Hing"], "categories": ["Merchandising & Purchasing", "Others", "Manufacturing", "Printing", "Others", "Trading"], "post_time": "2022-01-14T01:23:12Z", "salary": {"currency": null, "max": null, "min": null, "period": "monthly", "term": null}, "salary_visible": false, "title_keywords": ["account executive"], "responsibilities": ["liaise with", "monitor", "production process", "monthly reports"], "requirements": {"degrees": ["high diploma or above"], "majors": [], "languages": ["cantonese", "english", "chinese", "mandarin"], "language_level": ["proficient", "fluent"], "hard_skills": ["chinese word processing", "ms office"], "soft_skills": ["oral", "good team player", "under pressure", "independent", "detailed oriented", "work independently", "well organized"], "languages_combined": [{"language": "cantonese", "language_level": ["fluent"]}, {"language": "english", "language_level": ["proficient", "fluent"]}, {"language": "chinese", "language_level": ["proficient"]}, {"language": "mandarin", "language_level": ["fluent"]}]}, "experience_required": {"duration": ["2 years"], "field": ["relevant working experience"]}}, {"job_id": "100003009052569", "location_code": "hk", "company": "Mitsui & Co (HK) Ltd", "job_title": "Sales Administrator", "description": "We are now inviting candidate of high calibre to join us in the following capacity in our Iron & Steel Division.\n\nJob Duties:\n\nTo handle import / export shipping documents\nTo support sales staff to contact customers or suppliers as necessary\nTo perform general administrative and clerical support for the division, such as car booking, meeting room booking, expense claims, arrange hotel booking and business trip etc.\nTo perform other ad-hoc projects and tasks as assigned\nRequirements:\n\nAt least 2 \u2013 5 years\u2019 relevant working experience in shipping area\nExperience in SAP system is preferable\nStrong communication & interpersonal skills\nAble to work under pressure and complete the jobs within time constraint\nGood command of English and Mandarin\nGood command of Microsoft Office Tools (e.g. Word, Excel) and Chinese Typing\nDiploma graduate, commercial studies\n\nInterested parties please apply with your full resume stating present and expected salary.\n\nAll information will be kept confidential and used for recruitment purpose only. Although we endeavour to respond to every applicant, this may not always be possible so if you receive no response within 60 days, please consider your application for this specific vacancy to be unsuccessful.\n\n", "employment_types": ["Full Time", "Permanent"], "selling_points": [], "locations": ["Admiralty"], "categories": ["Sales, CS & Business Devpt", "Others", "Others", "Trading", "Sales Administration"], "post_time": "2022-01-17T03:26:34Z", "salary": {"currency": null, "max": null, "min": null, "period": "monthly", "term": null}, "salary_visible": false, "title_keywords": ["sales administrator"], "responsibilities": ["shipping documents", "business trip", "contact", "administrative and clerical support", "booking", "ad-hoc projects"], "requirements": {"degrees": ["diploma"], "majors": [], "languages": ["english", "chinese", "mandarin"], "language_level": ["good command"], "hard_skills": ["excel", "sap", "microsoft office", "typing", "word"], "soft_skills": ["communication", "interpersonal skills", "work under pressure"], "languages_combined": [{"language": "english", "language_level": ["good command"]}, {"language": "chinese", "language_level": []}, {"language": "mandarin", "language_level": ["good command"]}]}, "experience_required": {"duration": ["5 years"], "field": ["relevant working experience"]}}, {"job_id": "100003009056681", "location_code": "hk", "company": "Global Packaging Limited", "job_title": "Account Executive", "description": "Job Descriptions:\n\nLiaise with overseas clients and factories independently\nIndependently in handling projects follow up from sampling development to production\nHandle orders and monitor production process\nPrepare quotations, sampling and monthly reports\nOccasional travel to overseas if needed\n\nRequirements:\n\nHigh Diploma or above with 2 years relevant working experience\nWith solid printing knowledge\u00a0for garment accessories is preferred\nFluent language skills (written and oral) in English, Mandarin and Cantonese\nAble to work independent, detailed oriented, well organized & under pressure within a tight schedule\nProficient in MS office and English + Chinese word processing\nGood team player and work independently\n\nSalary Range: Negotiable\n\nBenefits:\n\n-Bank holiday\n\n-12~25 days annual leave or above\n\n-5 days working per week\n\n-Medical scheme\n\n-13 months salary\n\n-Performance based Bonus (not guarantee)\n\nWe provide attractive remuneration packages to the right candidates. Interested parties please send following by clicking \"APPLY NOW\".\n\nDetailed curriculum vitae/resume\nDate of availability\nExpected salary\n\n(All personal data provided will be treated in strict confidence and used for recruitment purposed only.)", "employment_types": ["Full Time"], "selling_points": ["High Diploma or above with 2 years relevant work", "With solid printing knowledge is preferred", "5 days working"], "locations": ["Kwai Hing"], "categories": ["Merchandising & Purchasing", "Others", "Manufacturing", "Printing", "Others", "Trading"], "post_time": "2022-01-18T05:44:24Z", "salary": {"currency": null, "max": null, "min": null, "period": "monthly", "term": null}, "salary_visible": false, "title_keywords": ["account executive"], "responsibilities": ["liaise with", "monitor", "production process", "monthly reports"], "requirements": {"degrees": ["high diploma or above"], "majors": [], "languages": ["cantonese", "english", "chinese", "mandarin"], "language_level": ["proficient", "fluent"], "hard_skills": ["chinese word processing", "ms office"], "soft_skills": ["oral", "good team player", "under pressure", "independent", "detailed oriented", "work independently", "well organized"], "languages_combined": [{"language": "cantonese", "language_level": ["fluent"]}, {"language": "english", "language_level": ["proficient", "fluent"]}, {"language": "chinese", "language_level": ["proficient"]}, {"language": "mandarin", "language_level": ["fluent"]}]}, "experience_required": {"duration": ["2 years"], "field": ["relevant working experience"]}}, {"job_id": "100003009045811", "location_code": "hk", "company": "iOne Financial Press Limited", "job_title": "Project Coordinator / Associate Sales", "description": "Job Objectives:\u00a0 Assist Sales Manager/Director in monitoring daily operational and administrative work. May have the opportunity to attend sales pitches for potential business when requested.\n\nProspects:\n\nWill have the opportunity to handle projects independently and deal with senior\u00a0 corporate executive directly.\n\u00a0Candidate who show proven ability may entitle an opportunity to transfer to more client \u2013 facing role.\n\u00a0The workplace environment will definitely train you up to be a professional corporate executive.\n\nKey Job Functions:\n\nTo assist in preparing all sales pitch documents, e.g., fee proposal, presentation booklet, printing samples, corporate gifts, client list, etc.\n\u00a0Assist Sales Manager/Director to monitor live projects, in term of scheduling, services arrangement, compliant handling and final invoicing.\n\u00a0Input and update information in our ERP.\n\u00a0Communications with internal departments and external vendors to ensure project go smoothly.\n\u00a0To assist in marketing/sales events occasionally\n\nRequirement:\n\n\u00a0\u00a0\u00a0\u00a0\u00a0 Quick learner and good command of language ( especially Putonghua)\n\u00a0\u00a0\u00a0\u00a0\u00a0 Able to work under pressure and deadlines.\n\u00a0\u00a0\u00a0\u00a0\u00a0 Proficient in Microsoft Office\n\u00a0\u00a0\u00a0\u00a0\u00a0 Working attitude come first when compare to academic background\n\nWe offer 5-day work (except peak season), medical benefits and attractive package to successful candidate. Salary will be commensurate with qualifications and experiences. Interested parties please apply with full resume and expected salary by clicking \u201cApply Now\u201d.\n\n\nAll information provided will be treated as strictly confidential and is used for recruitment purposes only.", "employment_types": ["Full Time"], "selling_points": [], "locations": ["Central"], "categories": ["Others", "Trading"], "post_time": "2022-01-13T08:47:03Z", "salary": {"currency": null, "max": null, "min": null, "period": "monthly", "term": null}, "salary_visible": false, "title_keywords": ["associate", "project coordinator", "sales"], "responsibilities": ["communications with", "administrative work", "monitoring", "monitor", "invoicing", "scheduling", "work under pressure"], "requirements": {"degrees": [], "majors": [], "languages": ["putonghua"], "language_level": ["good command"], "hard_skills": ["go", "erp", "microsoft office"], "soft_skills": ["independently", "presentation", "quick learner", "work under pressure"], "languages_combined": [{"language": "putonghua", "language_level": ["good command"]}]}, "experience_required": {"duration": [], "field": []}}, {"job_id": "100003009045120", "location_code": "hk", "company": "Able Choice Personnel Consultancy", "job_title": "General Clerk", "description": "\n\u8077\u8cac :\u4e00\u822c\u8fa6\u516c\u5ba4\u52a9\u7406\u5de5\u4f5c\n\n\u8cc7\u6b77 :\u4e2d\u4e94\u7a0b\u5ea6; \u826f\u597d\u7cb5\u8a9e\u512a\u5148; \u4e00\u822c\u666e\u901a\u8a71; \u4e00\u822c\u82f1\u8a9e; \u61c2\u8b80\u5beb\u4e2d\u6587; \u7565\u61c2\u8b80\u5beb\u82f1\u6587\n\n\u5f85\u9047 :\u6bcf\u6708$15,000, \u4e0a\u53488\u6642\u81f3\u4e0b\u53486\u6642, \u6bcf\u9031\u5de5\u4f5c6\u5929,\u8f2a\u4f11, \u6bcf\u5929\u5de5\u4f5c 10 \u5c0f\u6642\n\n\u7533\u8acb\u9808\u77e5 :\u6c42\u8077\u8005\u53ef\u81f4\u96fb95864198\u8207\u9022\u6e90\u8b77\u8001\u9662\u6709\u9650\u516c\u53f8\u8b1d\u5973\u58eb\u806f\u7d61\u3002\n\n", "employment_types": ["Full Time", "Permanent"], "selling_points": ["DSE or above", "2 years clerical experience in Trading / Mfg", "Good English, Cantonese and Mandarin"], "locations": ["North Point"], "categories": ["Admin & HR", "Clerical / Admin Staff", "Receptionist", "Others", "Trading"], "post_time": "2022-01-13T07:18:42Z", "salary": {"currency": null, "max": null, "min": null, "period": "monthly", "term": null}, "salary_visible": false, "title_keywords": ["general clerk"], "responsibilities": [], "requirements": {"degrees": [], "majors": [], "languages": [], "language_level": [], "hard_skills": [], "soft_skills": [], "languages_combined": []}, "experience_required": {"duration": [], "field": []}}, {"job_id": "100003009036105", "location_code": "hk", "company": "Global Packaging Limited", "job_title": "Shipping & Administrative Clerk", "description": "Follow up shipment booking and handle all logistics activities with internal and external parties to ensure smooth delivery.\nSupport Sales team to obtain freight cost from logistics agent.\nAble to handle full set of shipping documents, Tradelink system, custom declaration and all related issues.\nOperate Hong Kong warehouse activities of dispatching, receiving, sorting, and distributing deliveries.\nSales sample arrangements.\nManage and prepare labels for goods outer cartons and samples that are shipping from the office.\nVarious office administrative duties such as handle telephone calls, local and international courier to support office daily operations.\nOther ad-hoc job duties if necessary.\n\nJob Requirements\n\n\u00a0Form 5 / DSE or above.\n\u00a02-3 years solid experience in shipment from China/HK to worldwide.\n\u00a0Knowledge of China customs clearance procedure.\n\u00a0Good command of both written and spoken English and Chinese, knowledge of Mandarin preferred.\n\u00a0Advanced computer skills including Chinese word processing, MS Word, Excel and emailing.\n\u00a0Able to work independently with high sense of responsibility, reliable, team player and a desire to drive excellent work.\n\nImmediately available is highly preferred.\n\nSalary Range: Negotiable\n\nBenefits:\n\n-\u00a0 \u00a0Bank holiday\n-\u00a0 \u00a012~25 days annual leave\n-\u00a0 \u00a05 days working per week\n-\u00a0 \u00a0Medical Scheme\n-\u00a0 \u00a013 months salary\n-\u00a0 \u00a0Performance based Bonus (not guarantee)\n\nWe provide attractive remuneration packages to the right candidates. Interested parties please send following by clicking \"APPLY NOW\".\n\n\nDetailed curriculum vitae/resume\nDate of availability\nExpected salary\n\n(All personal data provided will be treated in strict confidence and used for recruitment purposed only.)", "employment_types": ["Full Time"], "selling_points": ["Form 5 / DSE or above.", "With solid shipping knowledge is preferred", "5 days working"], "locations": ["Kwai Hing"], "categories": ["Transportation & Logistics", "Shipping", "Manufacturing", "Printing", "Others", "Trading"], "post_time": "2022-01-10T09:21:14Z", "salary": {"currency": null, "max": null, "min": null, "period": "monthly", "term": null}, "salary_visible": false, "title_keywords": ["shipping", "administrative clerk"], "responsibilities": ["ad-hoc"], "requirements": {"degrees": ["form 5", "dse"], "majors": [], "languages": ["english", "chinese", "mandarin"], "language_level": ["good command"], "hard_skills": ["excel", "chinese word processing", "computer skills", "ms word"], "soft_skills": ["work independently", "advanced", "high sense of responsibility", "team player", "reliable"], "languages_combined": [{"language": "english", "language_level": ["good command"]}, {"language": "chinese", "language_level": ["good command"]}, {"language": "mandarin", "language_level": ["good command"]}]}, "experience_required": {"duration": ["2-3 years"], "field": []}}, {"job_id": "100003009044388", "location_code": "hk", "company": "Michael Page", "job_title": "Product Manager - Sustainability", "description": "This role will be responsible for delivering B2B data products to solve supply chain issues and bring deficiencies to global trade.\n\nClient Details\n\nOur client create new solutions to shape the future of international trade.\n\nDescription\n\nYou will be involved in monitoring and achieving sustainability goals. You will be conduct user feedback sessions , product discovery and competitor analysis. You will be own the functionality on B2B platforms. You will explore potential data partnerships.\n\nProfile\n\nYou will have more than 4 years experience in delivering digital products and/or web-based software. You will be strong experience throughout the end-to-end product life-cycle. You will be master of the Scrum framework and agile methodologies using JIRA. If you are experience in Sustainability, B2B products, sustainable financing and/or supply chain product is an advantage.\n\nJob Offer\n\nAttractive package and great company culture are on the offer.\n\nTo apply online please click the 'Apply' button below. For a confidential discussion about this role please contact Christine Tsui on +852 2848 9584.", "employment_types": ["Full Time", "Permanent"], "selling_points": ["Apparel Industry", "B2B Data Products", "Global Trade"], "locations": ["Not Specified"], "categories": ["Manufacturing", "Product Development / Management", "Others", "Trading", "E-commerce", "Supply Chain"], "post_time": "2022-01-13T03:56:50Z", "salary": {"currency": null, "max": null, "min": null, "period": "monthly", "term": null}, "salary_visible": false, "title_keywords": ["product manager"], "responsibilities": ["software", "data", "analysis", "monitoring", "contact"], "requirements": {"degrees": ["master"], "majors": [], "languages": [], "language_level": [], "hard_skills": ["scrum framework", "analysis", "agile", "web"], "soft_skills": ["agile", "responsible"], "languages_combined": []}, "experience_required": {"duration": ["4 years"], "field": ["digital", "financing", "supply chain", "sustainability"]}}, {"job_id": "100003009033326", "location_code": "hk", "company": "Funko Far East Limited", "job_title": "Logistics Coordinator", "description": "Job Description\n\nReview vendors shipment forecast with forwarder\nOrders follow-up, liaising with customers & suppliers\nFollow up with forwarder to ensure on time delivery per shipment schedule\nReview Packing list and Invoice from Vendors\nFollow up customer approval for LCL shipment\nPrepare Commercial invoice\nUpdate system and on line shipment tracker\nSupport ad hoc assignment\n\nQualifications\n\nDSE or higher diploma\nAt least 2-Years relevant experience is required\nI/E shipping experience & knowledge in banking document\nAbility to handle full set shipping documents\nHard working, able to work under pressure and tight deadline\nGood working attitude. Helpful, organized, sensitive to figures, responsible and a good team player\nGood command in both written and spoken English and Mandarin\nGood computer Microsoft Office application skills (MS Word, Excel and Outlook)\u00a0\n\n\u00a0** Please show the expected salary on your resume for our consideration. Thank you.**", "employment_types": ["Full Time"], "selling_points": ["Orders follow-up with customers & suppliers", "Follow up with forwarder & prepare Inv / Pkg List", "5-day, flexihour, 13+, bonus, medical+den+life ins"], "locations": ["Tsim Sha Tsui"], "categories": ["Transportation & Logistics", "Shipping", "Supply Chain", "Others", "Trading"], "post_time": "2022-01-10T00:15:58Z", "salary": {"currency": null, "max": null, "min": null, "period": "monthly", "term": null}, "salary_visible": false, "title_keywords": ["logistics coordinator"], "responsibilities": ["shipping documents", "shipping", "invoice", "ad hoc assignment", "review", "ensure on time delivery", "liaising with", "packing list", "schedule", "forecast", "banking", "work under pressure"], "requirements": {"degrees": ["diploma", "dse"], "majors": [], "languages": ["english", "mandarin"], "language_level": ["good command"], "hard_skills": ["ms word", "excel", "outlook", "microsoft office"], "soft_skills": ["organized", "good working attitude", "good team player", "responsible", "hard working", "sensitive to figures", "work under pressure"], "languages_combined": [{"language": "english", "language_level": ["good command"]}, {"language": "mandarin", "language_level": ["good command"]}]}, "experience_required": {"duration": [], "field": ["relevant experience", "banking"]}}, {"job_id": "100003009035880", "location_code": "hk", "company": "Puleo Asia Limited", "job_title": "Merchandiser (Seasonal, Home Decorations & Gifts)", "description": "Responsibilities:\u00a0\n\nLiaise with overseas customers to help the supervisor in handling their inquires\nCapable to work independently with factories and internal parties, in order to help the supervisor follow-up on orders to ensure production quality and on-time delivery\nJob Requirements:\n\n\nTertiary education is preferred\nMinimum 3 years of merchandising and trading experiences is a must. Less experience will be considered as Assistant Merchandiser\nFluent in both written and spoken English and Chinese (Cantonese and Mandarin)\nWell organized, with good interpersonal and communication skill\nMature, stable, detail-minded, self-motivated and being a good team player, able to work under pressure and tight deadline\nAble to work in a fast pace environment and overtime\nExperience in working with major retailers in US & European markets is an advantage\nProficiency in on-hand computer skill : MS Excel, Chinese Word processing & Outlook Knowledge\nRequire to visit in China\nImmediate available is highly preferred\n\nWe offer competitive remuneration package. For Interested parties, please submit your resume by clicking ''Apply Now'' button as below.\u00a0\u00a0All the information provide by applicants will be used for\u00a0recruitment purpose only.\u00a0", "employment_types": ["Full Time", "Permanent"], "selling_points": [], "locations": ["Hung Hom"], "categories": ["Merchandising & Purchasing", "Others", "Others", "Trading"], "post_time": "2022-01-10T08:38:39Z", "salary": {"currency": null, "max": null, "min": null, "period": "monthly", "term": null}, "salary_visible": false, "title_keywords": ["merchandiser"], "responsibilities": ["liaise with", "quality", "internal parties"], "requirements": {"degrees": [], "majors": [], "languages": ["cantonese", "english", "chinese", "mandarin"], "language_level": ["proficiency", "fluent"], "hard_skills": ["chinese word processing", "ms excel", "computer skill", "outlook"], "soft_skills": ["detail-minded", "self-motivated", "good team player", "communication skill", "well organized", "mature", "stable", "interpersonal", "work under pressure"], "languages_combined": [{"language": "cantonese", "language_level": []}, {"language": "english", "language_level": ["fluent"]}, {"language": "chinese", "language_level": ["fluent", "proficiency"]}, {"language": "mandarin", "language_level": []}]}, "experience_required": {"duration": ["minimum 3 years"], "field": ["merchandising", "trading"]}}, {"job_id": "100003009047146", "location_code": "hk", "company": "CNA Metals China Limited", "job_title": "ACCOUNTING OFFICER", "description": "Job Description /Responsibilities:\n\n- Handle full set of books and daily accounting work including payment transactions, journal entries, AR, \u00a0\n\n\u00a0 AP and reconciliations of accounts.\n\n- Prepare monthly financial statements and management reports.\n\n- Prepare accounting schedules for year end audit\n\n- Assist audit assignments\n\n- To perform ad-hoc assignments as required by the company.\n\nRequirements:\n\n- Diploma or Degree holder or above with LCC&I intermediate level or above or equivalent.\n\n- Candidates from non-degree tertiary with accounting discipline are also welcome\n\n- At least 2-3 years solid experience in trading firm is preferable.\n\n- Experience in QuickBook system is an advantage\n\n- Knowledge on using MS Outlook, MS Word, MS Excel\n\n- Attentive, Independent and self-motivated with strong sense of responsibility.\n\n- Able to work independently and under pressure\n\n- Immediate available is preferred\n\nSalary: Negotiable\n\nPlease apply with full resume indicating position applied, present and expected salary\u00a0if you have interested in this work.\n\nAll the personal data collected will be dealt with strict confidential and we are compliance with Personal Data Ordinance.", "employment_types": ["Full Time", "Part Time", "Permanent"], "selling_points": [], "locations": ["Kwai Fong"], "categories": ["Others", "Trading"], "post_time": "2022-01-14T02:27:42Z", "salary": {"currency": null, "max": null, "min": null, "period": "monthly", "term": null}, "salary_visible": false, "title_keywords": ["accounting officer"], "responsibilities": ["ap", "ar", "schedules", "ad-hoc assignments", "daily accounting work", "payment transactions", "reconciliations of accounts", "audit", "prepare monthly financial statements", "management reports", "journal entries"], "requirements": {"degrees": ["diploma", "degree", "degree holder"], "majors": ["accounting"], "languages": [], "language_level": [], "hard_skills": ["ms excel", "outlook", "ms word"], "soft_skills": ["attentive", "self-motivated", "work independently", "independent", "under pressure", "sense of responsibility", "interested in"], "languages_combined": []}, "experience_required": {"duration": ["at least 2-3 years"], "field": ["trading"]}}, {"job_id": "100003009034545", "location_code": "hk", "company": "2H Corporate Nominees Limited", "job_title": "\u8fa6\u516c\u5ba4\u52a9\u7406", "description": "~DSE or above\n~2 years clerical experience in Trading / Manufacturer\n~Good English, Mandarin and Cantonese\u00a0", "employment_types": ["Full Time"], "selling_points": [], "locations": ["Kwun Tong"], "categories": ["Admin & HR", "Clerical / Admin Staff", "Others", "Others", "Trading"], "post_time": "2022-01-10T03:38:26Z", "salary": {"currency": null, "max": null, "min": null, "period": "monthly", "term": null}, "salary_visible": false, "title_keywords": ["\u8fa6\u516c\u5ba4\u52a9\u7406"], "responsibilities": [], "requirements": {"degrees": [], "majors": [], "languages": ["cantonese", "english", "mandarin"], "language_level": [], "hard_skills": [], "soft_skills": [], "languages_combined": [{"language": "cantonese", "language_level": []}, {"language": "english", "language_level": []}, {"language": "mandarin", "language_level": []}]}, "experience_required": {"duration": [], "field": ["trading", "clerical"]}}, {"job_id": "100003009037648", "location_code": "hk", "company": "JAS Forwarding (HK) Ltd", "job_title": "Ocean Export Executive / Assistant Supervisor", "description": "\n\u8077\u8cac :\u8ca0\u8cac\u4e00\u822c\u8fa6\u516c\u5ba4\u52a9\u7406\u5de5\u4f5c,\u5916\u52e4\u5de5\u4f5c,\u5916\u51fa\u6536\u767c\u6587\u4ef6\n\n\u8cc7\u6b77 :\u5c0f\u4e94\u7a0b\u5ea6; \u826f\u597d\u7cb5\u8a9e; \u4e00\u822c\u666e\u901a\u8a71; \u4e00\u822c\u82f1\u8a9e; \u61c2\u8b80\u5beb\u4e2d\u6587; \u61c2\u8b80\u5beb\u82f1\u6587; \u5de5\u4f5c\u4e3b\u52d5\u7a4d\u6975,\u9858\u610f\u5b78\u7fd2\n\n\u5f85\u9047 :\u6bcf\u6708$8,100 - $14,000, \u661f\u671f\u4e00\u81f3\u4e94: \u4e0a\u53489\u6642\u81f3\u4e0b\u53486\u6642\u53ca\u661f\u671f\u516d: \u4e0a\u53489\u6642\u81f3\u4e0b\u53481\u6642, \u6bcf\u9031\u5de5\u4f5c5\u5929\u534a\n\n\u7533\u8acb\u9808\u77e5 :\u6c42\u8077\u8005\u53ef\u96fb\u90f5(Apply Now)\u5c65\u6b77\u8868\u7d66\u6613\u8c6a\u4ee3\u7406\u6709\u9650\u516c\u53f8\u3002\u5982\u8981\u7d22\u53d6\u6536\u96c6\u500b\u4eba\u8cc7\u6599\u8072\u660e, \u8acb\u8207\u7f85\u5c0f\u59d0(Email)\u806f\u7d61\u3002\n\n", "employment_types": ["Full Time"], "selling_points": ["Ocean Freight Operations", "Freight Forwarding", "Document process"], "locations": ["Tsuen Wan Area"], "categories": ["Transportation & Logistics", "Freight Forwarding", "Shipping", "Others", "Trading"], "post_time": "2022-01-11T03:23:09Z", "salary": {"currency": null, "max": null, "min": null, "period": "monthly", "term": null}, "salary_visible": false, "title_keywords": ["executive", "assistant supervisor"], "responsibilities": [], "requirements": {"degrees": [], "majors": [], "languages": [], "language_level": [], "hard_skills": [], "soft_skills": [], "languages_combined": []}, "experience_required": {"duration": [], "field": []}}, {"job_id": "100003009044088", "location_code": "hk", "company": "Aline Company Limited", "job_title": "{URGENT} Assistant Accountant / Accounting Clerk - 5 days at Cheung Sha Wan Area", "description": "Summary:\n\nThe\u00a0Operation Executive / Assistant Ocean Export Supervisor is responsible for monitoring and supervising daily operations and data accuracy.\n\n\u00a0Responsibilities:\n\n\u00a0 \u00a0Handle customer complaints\n\u00a0 \u00a0Handle customer enquires\n\u00a0 \u00a0Assist manager to train & monitor discipline of staff\n\u00a0 \u00a0Communicate with carrier\u2019s customer service\n\u00a0 \u00a0Cooperate with subcontractor\u2019s operations\n\u00a0 \u00a0Problem solving with subcontractor\n\u00a0 \u00a0Communicate with JAS\u2019s overseas on advance level of operations\n\u00a0 \u00a0More Experience will be considerate as\u00a0Assistant Ocean Export Supervisor\n\n\u00a0Requirements:\n\n\u00a0 F.5 or above;\n\u00a0 Minimum 5 years related experience and/or training; or equivalent combination of education and experience.\n\u00a0 Good command in both spoken and written English, Chinese & Putonghua;\n\u00a0 Proficient with Microsoft office (MS Word, Excel, PowerPoint);\n\u00a0 Good communication and interpersonal skills, independent and mature, detail oriented and strong follow-up skills\n\u00a0 Cargo Wise systems knowledge is a plus\n\n\n\nWe offer attractive remuneration package including 13th month salary and fringe benefits for the right candidate.\n\n\nIf you are interested, please send your application together with a full particular of qualifications, experience, current and expected salary to\u00a0\"APPLY NOW\"\n\nAll information provided will be kept confidential and used only for the purpose of selection. Only short listed candidates will be contacted. All applications will be retained for a maximum period of three months.", "employment_types": ["Full Time", "Permanent"], "selling_points": ["1 years AC ex. with LCCI higher or  Diploma AC", "5 days, close to MTR station, Double Pay, Medical", "Immediate or 1 week notice is highly advantage"], "locations": ["Sham Shui Po Area"], "categories": ["Accounting", "Accounting Clerk / Supervisor", "Others", "Trading"], "post_time": "2022-01-13T03:02:00Z", "salary": {"currency": null, "max": null, "min": null, "period": "monthly", "term": null}, "salary_visible": false, "title_keywords": ["accounting clerk", "assistant accountant"], "responsibilities": ["communicate with", "customer complaints", "operations", "monitor", "customer service", "cooperate with"], "requirements": {"degrees": [], "majors": [], "languages": ["putonghua", "english", "chinese"], "language_level": ["good command"], "hard_skills": ["excel", "plus", "microsoft office", "powerpoint", "ms word"], "soft_skills": ["detail oriented", "communication and interpersonal skills", "independent", "mature"], "languages_combined": [{"language": "putonghua", "language_level": ["good command"]}, {"language": "english", "language_level": ["good command"]}, {"language": "chinese", "language_level": ["good command"]}]}, "experience_required": {"duration": ["minimum 5 years"], "field": ["related", "training", "education"]}}, {"job_id": "100003009033064", "location_code": "hk", "company": "PACK & VAC LIMITED", "job_title": "Sales Assistant / Document Clerk - 5 Days -", "description": "Job Responsibilities:\n\nPerform daily AR & AP accounting duties and assist in month-end closing\nChecking and matching invoices from venders\nIntercompany transactions booking,\nIssue Debit Note & Credit Note,\nSupport other ad-hoc assignments as assigned\nReport to Accounting Manager\n\nRequirements:\n\n1 year Accounting Experience (AR&AP), familiar with accounting software (any software is okey), MS Excel & Word.\nLCCI higher or Diploma in Accounting studies is preferable.\nFluent Cantonese, communication level of English & Mandarin.\nSelf initiative, independent, sense of responsibility, hardworking and willing to learn\nImmediately Available is highly advantage.\u00a0", "employment_types": ["Full Time"], "selling_points": ["Food packaging material sales", "13 month salary", "development opportunities"], "locations": ["Tsuen Wan Area"], "categories": ["Admin & HR", "Clerical / Admin Staff", "Sales, CS & Business Devpt", "Sales - Sales Management", "Others", "Trading"], "post_time": "2022-01-08T07:24:10Z", "salary": {"currency": "HKD", "max": 16999, "min": 14000, "period": "monthly", "term": null}, "salary_visible": true, "title_keywords": ["clerk", "sales assistant"], "responsibilities": ["ap", "ar", "invoices", "ad-hoc assignments", "checking", "transactions", "month-end closing", "booking", "accounting duties", "report"], "requirements": {"degrees": ["diploma"], "majors": ["accounting"], "languages": ["cantonese", "english", "mandarin"], "language_level": ["fluent"], "hard_skills": ["accounting software", "ms excel", "word"], "soft_skills": ["independent", "sense of responsibility", "willing to learn", "communication", "initiative", "hardworking"], "languages_combined": [{"language": "cantonese", "language_level": ["fluent"]}, {"language": "english", "language_level": []}, {"language": "mandarin", "language_level": []}]}, "experience_required": {"duration": ["1 year"], "field": ["accounting experience", "accounting"]}}, {"job_id": "100003009036112", "location_code": "hk", "company": "Global Packaging Limited", "job_title": "Account Executive", "description": "Job Descriptions:\n\nLiaise with overseas clients and factories independently\nIndependently in handling projects follow up from sampling development to production\nHandle orders and monitor production process\nPrepare quotations, sampling and monthly reports\nOccasional travel to overseas if needed\n\nRequirements:\n\nHigh Diploma or above with 2 years relevant working experience\nWith solid printing knowledge\u00a0for garment accessories is preferred\nFluent language skills (written and oral) in English, Mandarin and Cantonese\nAble to work independent, detailed oriented, well organized & under pressure within a tight schedule\nProficient in MS office and English + Chinese word processing\nGood team player and work independently\n\nSalary Range: Negotiable\n\nBenefits:\n\n-Bank holiday\n\n-12~25 days annual leave or above\n\n-5 days working per week\n\n-Medical scheme\n\n-13 months salary\n\n-Performance based Bonus (not guarantee)\n\nWe provide attractive remuneration packages to the right candidates. Interested parties please send following by clicking \"APPLY NOW\".\n\nDetailed curriculum vitae/resume\nDate of availability\nExpected salary\n\n(All personal data provided will be treated in strict confidence and used for recruitment purposed only.)", "employment_types": ["Full Time"], "selling_points": ["High Diploma or above with 2 years relevant work", "With solid printing knowledge is preferred", "5 days working"], "locations": ["Kwai Hing"], "categories": ["Merchandising & Purchasing", "Others", "Manufacturing", "Printing", "Others", "Trading"], "post_time": "2022-01-10T09:23:00Z", "salary": {"currency": null, "max": null, "min": null, "period": "monthly", "term": null}, "salary_visible": false, "title_keywords": ["account executive"], "responsibilities": ["liaise with", "monitor", "production process", "monthly reports"], "requirements": {"degrees": ["high diploma or above"], "majors": [], "languages": ["cantonese", "english", "chinese", "mandarin"], "language_level": ["proficient", "fluent"], "hard_skills": ["chinese word processing", "ms office"], "soft_skills": ["oral", "good team player", "under pressure", "independent", "detailed oriented", "work independently", "well organized"], "languages_combined": [{"language": "cantonese", "language_level": ["fluent"]}, {"language": "english", "language_level": ["proficient", "fluent"]}, {"language": "chinese", "language_level": ["proficient"]}, {"language": "mandarin", "language_level": ["fluent"]}]}, "experience_required": {"duration": ["2 years"], "field": ["relevant working experience"]}}, {"job_id": "100003009029967", "location_code": "hk", "company": "FSD EMENTAL INDUSTRIAL LIMITED", "job_title": "Shipping Clerk", "description": "\n\u8077\u8cac :\u8655\u7406\u8fa6\u516c\u5ba4\u96dc\u52d9\u53ca\u5916\u52e4\u4e8b\u52d9\uff1a\u5305\u62ec\u6587\u4ef6\u9001\u905e\u3001\u9280\u884c\u5165\u5e33\u3001\u524d\u5f80\u90f5\u5c40\u7b49\u3001\u8655\u7406\u7279\u6d3e\u5de5\u4f5c\u3001\u6216\u9700\u5354\u52a9\u6e05\u6f54\u5de5\u4f5c\u3001\u9700\u8981\u6642\u9700\u5354\u52a9\u540c\u4e8b\u642c\u52d5\u50a2\u4ff1\u3002\n\n\u8cc7\u6b77 :\u4e2d\u4e00\u7a0b\u5ea6; 5\u5e74\u7d93\u9a57; \u4e00\u822c\u7cb5\u8a9e; \u4e00\u822c\u666e\u901a\u8a71; \u4e00\u822c\u82f1\u8a9e; \u61c2\u95b1\u8b80\u4e2d\u6587; \u7565\u61c2\u8b80\u5beb\u82f1\u6587; \u80fd\u5373\u6642\u4e0a\u73ed\u512a\u5148\uff1b\u7565\u61c2\u5c0f\u7dad\u4fee\u77e5\u8b58\n\n\u5f85\u9047 :\u6bcf\u6708$11,000, \u6709\u9280\u884c\u5047\u671f \u53ca\u4f9b\u81b3\u98df, \u661f\u671f\u4e00\u81f3\u4e94: \u4e0a\u53488\u6642\u534a\u81f3\u4e0b\u53486\u6642, \u6bcf\u9031\u5de5\u4f5c5\u5929, \u6bcf\u5929\u5de5\u4f5c 8.5 \u5c0f\u6642\n\n\u7533\u8acb\u9808\u77e5 :\u6c42\u8077\u8005\u53ef\u81f4\u96fb24261021(Ext.610)\u8207TAK SING ALLIANCE LTD\u9673\u5c0f\u59d0\u806f\u7d61\u3002\n\n", "employment_types": ["Full Time"], "selling_points": ["Salary 15k-20k. 5 days work", "Near Ngau Tau Kok Station", "Bonus"], "locations": ["Ngau Tau Kok"], "categories": ["Others", "Trading"], "post_time": "2022-01-07T06:31:29Z", "salary": {"currency": null, "max": null, "min": null, "period": "monthly", "term": null}, "salary_visible": false, "title_keywords": ["shipping clerk"], "responsibilities": [], "requirements": {"degrees": [], "majors": [], "languages": [], "language_level": [], "hard_skills": [], "soft_skills": [], "languages_combined": []}, "experience_required": {"duration": [], "field": []}}, {"job_id": "100003009034302", "location_code": "hk", "company": "Tak Sing Alliance Ltd", "job_title": "\u8fa6\u516c\u5ba4\u52a9\u7406", "description": "Job Description ( Normally indoor work )\u00a0\n\n* Manage customer care - Delivery & stock ( ERP system with Indoor )\n\u00a0 ( we have driver self )\u00a0\n* base document follow up - Trading Document and ERP use\u00a0\n* Manage current customer follow up\u00a0\n* Almost document base on English\u00a0\n* Suitable for man\u00a0\n\nRequirements\n\n* Knowledge in MS word & Excel ( in Chinese * English )\n* Can communicate with Customer ( English & Cantonese )\n* If can do adobe photo shop ( basic level )\u00a0\n* 1 Year or Above Experience\n* Expected Salary must show on resume\n* Good communication skill with team\n\nBenefit\n\n* 13 month salary\u00a0\n* Team work incentive - End of year - Target with Goal\u00a0\n\n", "employment_types": ["Full Time"], "selling_points": [], "locations": ["Kwai Tsing Area"], "categories": ["Admin & HR", "Clerical / Admin Staff", "Others", "Others", "Trading"], "post_time": "2022-01-10T03:07:06Z", "salary": {"currency": null, "max": null, "min": null, "period": "monthly", "term": null}, "salary_visible": false, "title_keywords": ["\u8fa6\u516c\u5ba4\u52a9\u7406"], "responsibilities": [], "requirements": {"degrees": [], "majors": [], "languages": ["cantonese", "english", "chinese"], "language_level": [], "hard_skills": ["excel", "adobe", "basic", "ms word"], "soft_skills": ["communication skill"], "languages_combined": [{"language": "cantonese", "language_level": []}, {"language": "english", "language_level": []}, {"language": "chinese", "language_level": []}]}, "experience_required": {"duration": ["1 year"], "field": []}}, {"job_id": "100003009034213", "location_code": "hk", "company": "Worldtrans Air-Sea Service Ltd", "job_title": "\u8fa6\u516c\u5ba4\u52a9\u7406", "description": "\n\u8077\u8cac :\u8fa6\u516c\u5ba4\u6e05\u6f54\u5982\u8fa6\u516c\u5ba4\u6d17\u624b\u9593\u3001\u8336\u5177\u6e05\u6f54\u3001\u5438\u5875\u3001\u6bcf\u5929\u6e05\u7406\u5783\u573e\u7b52\u3001\u5de5\u4f5c\u67b1/\u6703\u8b70\u5ba4\u6253\u6383\uff0c\u4fdd\u6301\u5730\u65b9\u6574\u6f54\uff1b\u8ca0\u8cac\u4e00\u822c\u8fa6\u516c\u5ba4\u8336\u6c34\u5de5\u4f5c\uff1b\u5916\u52e4\u5de5\u4f5c, \u5982\u5230\u9280\u884c\u3001\u90f5\u5c40\u8207\u5916\u51fa\u6536\u767c\u6587\u4ef6, \u4e00\u822c\u8fa6\u516c\u5ba4\u5de5\u4f5c\uff0c \u5982\u5f71\u5370\u3001\u6383\u63cf\u53ca\u91d8\u88dd\u6587\u4ef6\n\n\u8cc7\u6b77 :\u6c92\u6709\u5b78\u6b77\u8981\u6c42; 1\u5e74\u7d93\u9a57; \u826f\u597d\u7cb5\u8a9e; \u4e00\u822c\u666e\u901a\u8a71; \u4e00\u822c\u82f1\u8a9e; \u61c2\u8b80\u5beb\u4e2d\u6587; \u61c2\u95b1\u8b80\u82f1\u6587; \u6709\u8cac\u4efb\u611f,\u52e4\u596e,\u5de5\u4f5c\u4e3b\u52d5,\u6709\u79ae\u8c8c,\u9858\u610f\u5b78\u7fd2\n\n\u5f85\u9047 :\u6bcf\u6708$10,000 - $14,000, \u6709\u5e74\u504712\u5929, \u5728\u8077\u57f9\u8a13 \u53ca\u8d85\u6642\u5de5\u4f5c\u6d25\u8cbc, \u661f\u671f\u4e00\u81f3\u4e94: \u4e0a\u53489\u6642\u81f3\u4e0b\u53486\u6642\u53ca\u661f\u671f\u516d: \u4e0a\u53489\u6642\u81f3\u4e0b\u53481\u6642, \u6bcf\u9031\u5de5\u4f5c5\u5929\u534a, \u6bcf\u5929\u5de5\u4f5c 9 \u5c0f\u6642\n\n\u7533\u8acb\u9808\u77e5 :\u6c42\u8077\u8005\u53ef\u96fb\u90f5(Apply Now)\u5c65\u6b77\u8868\u7d66\u5a01\u9a30\u806f\u904b\u6709\u9650\u516c\u53f8\u3002\u5982\u8981\u7d22\u53d6\u6536\u96c6\u500b\u4eba\u8cc7\u6599\u8072\u660e, \u8acb\u8207\u6881\u5c0f\u59d0(Email)\u806f\u7d61\u3002\n\n", "employment_types": ["Full Time"], "selling_points": [], "locations": ["To Kwa Wan"], "categories": ["Admin & HR", "Clerical / Admin Staff", "Others", "Others", "Trading"], "post_time": "2022-01-10T02:58:34Z", "salary": {"currency": null, "max": null, "min": null, "period": "monthly", "term": null}, "salary_visible": false, "title_keywords": ["\u8fa6\u516c\u5ba4\u52a9\u7406"], "responsibilities": [], "requirements": {"degrees": [], "majors": [], "languages": [], "language_level": [], "hard_skills": [], "soft_skills": [], "languages_combined": []}, "experience_required": {"duration": [], "field": []}}, {"job_id": "100003009018895", "location_code": "hk", "company": "Oriental Partners Ltd", "job_title": "Trading Executive", "description": "Shipping Clerk\n\nJob Highlights\n\nSalary 15k-20k. 5 days work\nNear Ngau Tau Kok Station\nBonus\nJob Description\n\nResponsibilities\n\nForm 7 or above\nAble to handle L/C banking documents independently\nHandle full set of I/E documents, Tradelink customs declaration\nWork with local HK transport companies to arrange pickup and drop-off to forwarders/Lines.\nAssist in administration work and filing duties\nAssist in ad-hoc assignments\n\nRequirements\n\n3-5 years working experience in Trading Accounting\nGood computer skills especially in Word, Excel.\nDetail-minded, careful, good team player\nCandidate with more experience will be considered as Senior Shipping Clerk / Shipping Manager.\n\n\u00a0We offer competitive package to the right candidate. Interest parties please send your full resume with expected salary by clicking \"Apply Now\"\n\n(Personal data collected will be used for recruitment purpose only)", "employment_types": ["Full Time"], "selling_points": [], "locations": ["Kwai Fong"], "categories": ["Others", "Trading"], "post_time": "2022-01-04T05:55:17Z", "salary": {"currency": null, "max": null, "min": null, "period": "monthly", "term": null}, "salary_visible": false, "title_keywords": ["executive"], "responsibilities": ["customs declaration", "tradelink", "ad-hoc assignments", "banking", "administration"], "requirements": {"degrees": [], "majors": [], "languages": [], "language_level": [], "hard_skills": ["excel", "computer skills", "word"], "soft_skills": ["detail-minded", "good team player", "careful"], "languages_combined": []}, "experience_required": {"duration": ["3-5 years"], "field": ["accounting", "trading"]}}, {"job_id": "100003009031906", "location_code": "hk", "company": "Brother Machinery (Asia) Limited", "job_title": "Customer Service Officer / After Sales Coordinator / Sales Associate / Sales Assistant", "description": "Build and maintain strong relationship with clients to provide excellence after sales service and support\nDaily operations including customer enquiries follow up, and orders in ERP system, etc.\nCo-ordinate closely with internal suppliers to meet delivery schedule and quality sales services.\nParts inventory control for maintain a stable supply within reasonable stock level.\nArrange logistics (delivery, shipping, import and export declarations)\nProvide administration and secretarial support\nAssist in ad hoc duties assigned by manager\n\nTraining & Development\nProvide in house E-learning platform and study subsidy for job related topics\n\nOur Ideal Candidate\n\n\n3 years or above sales associate / coordinator experience / fresh graduate with potential will also be considered\nGood command of written and spoken English\u00a0\nAttention to details, self-motivated, sensible in problem solving and able to work independently\nGood PC skills (Excel and Outlook) with Chinese types & MS Office\nExperience of ERP system (SAP, Salesforce etc) will be advantage\nImmediate availability is preferred\n\nStaff Benefits\n\n5 days work\nBank Holiday\nFlexible Working Hours\nWork From Home\nTransportation Allowance\nMedical & Dental Insurance\nBody check\n\nInterested?\nIf you are interested please send your\u00a0full resume,\u00a0current\u00a0and\u00a0expected salary\u00a0and\u00a0availability\u00a0by clicking \"APPLY NOW\".\n\n*Personal data provided are treated in strictest confidence and for recruitment purposes only.\u00a0 All information will be destroyed after the process completed.*", "employment_types": ["Full Time", "Permanent"], "selling_points": [], "locations": ["Kwai Hing"], "categories": ["Sales, CS & Business Devpt", "Customer Service - Supervisor / Officer", "Transportation & Logistics", "Shipping", "Others", "Trading"], "post_time": "2022-01-07T19:20:58Z", "salary": {"currency": null, "max": null, "min": null, "period": "monthly", "term": null}, "salary_visible": false, "title_keywords": ["sales coordinator", "sales assistant", "customer service officer", "sales associate"], "responsibilities": ["ad hoc duties", "shipping", "customer enquiries", "quality", "delivery schedule", "daily operations", "maintain", "inventory control", "logistics", "secretarial support", "administration"], "requirements": {"degrees": ["fresh graduate"], "majors": [], "languages": ["english", "chinese"], "language_level": ["good command", "good"], "hard_skills": ["excel", "salesforce", "sap", "import and export", "problem solving", "erp system", "outlook", "pc skills", "ms office"], "soft_skills": ["self-motivated", "work independently", "problem solving", "learning", "attention to details", "stable", "ideal"], "languages_combined": [{"language": "english", "language_level": ["good command", "good"]}, {"language": "chinese", "language_level": ["good"]}]}, "experience_required": {"duration": ["3 years"], "field": ["erp system"]}}, {"job_id": "100003009026918", "location_code": "hk", "company": "Sika Hongkong Limited", "job_title": "PURCHASING OFFICER", "description": "Responsibilities:\n\n\nHandle I/E shipping documents, L/C & Customs Clearance, invoice/delivery note/packing list, Tradelink, eRO System etc.\nEnsure all paperwork and purchase orders are completed accurately and in a timely manner\nCoordinate with sea/air forwarders, transportation companies, cargo agents and suppliers for shipment arrangement\nClosely communicate with sales teams, suppliers, and factories, monitor the stock inventory level, and replenish where necessary\nTrack and update the status of incoming/outgoing shipments schedule\nManage shipping orders and supplier invoices verification\nResponsible to cope with shipping process issues\n\n\u00a0Requirements\n\nF5 or above with minimum 5 years solid working experience in trading and manufacturing industry.\nAble to handle full set of shipments documents independently\nComputer knowledge in Microsoft Words, Excel, Outlook, and Chinese word processing is required\nKnowledge in ERP system (SAP is preferred)\nSelf-motivated, attention to detail and accuracy, well-organized, independent, and able to work under pressure\nGood in English and Mandarin\nExcellent team player\nReliable, positive, coordinate with different parties\nImmediate available is preferred\nInterested candidates please send your detailed resume with expected salary and availability via \u201cApply Now\u201d.", "employment_types": ["Full Time"], "selling_points": ["F5 or above, min. 5 years experience", "Handle full set shipments documents independently", "Immediate available is preferred"], "locations": ["Shatin Area"], "categories": ["Building & Construction", "Building / Construction / QS", "Merchandising & Purchasing", "Procurement / Purchasing / Sourcing", "Others", "Trading"], "post_time": "2022-01-06T08:52:46Z", "salary": {"currency": null, "max": null, "min": null, "period": "monthly", "term": null}, "salary_visible": false, "title_keywords": ["purchasing officer"], "responsibilities": ["shipping documents", "communicate with", "shipping", "invoices", "tradelink", "shipment arrangement", "invoice", "inventory", "a timely manner", "coordinate with", "teams", "packing list", "monitor", "purchase", "schedule"], "requirements": {"degrees": [], "majors": [], "languages": ["english", "chinese", "mandarin"], "language_level": ["good"], "hard_skills": ["excel", "chinese word processing", "words", "sap", "erp system", "outlook"], "soft_skills": ["self-motivated", "independently", "independent", "well-organized", "attention to detail", "team player", "reliable", "positive", "work under pressure"], "languages_combined": [{"language": "english", "language_level": ["good"]}, {"language": "chinese", "language_level": []}, {"language": "mandarin", "language_level": ["good"]}]}, "experience_required": {"duration": ["minimum 5 years"], "field": ["trading", "manufacturing industry"]}}, {"job_id": "100003009031311", "location_code": "hk", "company": "Redcliff Corporation Limited", "job_title": "Merchandiser / Senior Merchandiser (5 days work/Lai Chi Kwok MTR)", "description": "Responsibilities:\n\nResponsible for\u00a0products sourcing and trading;\nLiaison with customers and suppliers to achieve\u00a0sales target;\nDevelop new suppliers and products;\nNegotiate and build relationship with buyers and sellers;\nFollow up contract issuance, shipments, payments and other trade related matters;\nLiaise with internal departments for trade operation matters.\n\nRequirements:\n\nDegree / Diploma holder in Purchasing / Trading / Sourcing / Business\u00a0related discipline preferable;\nMinimum 3 years solid trading and sourcing experience in any one of below categories: Food & beverage / FMCG;\u00a0 \u00a0\u00a0\nExperience in food associated would be an added advantage;\nHardworking, independent and self-motivated with excellent communication skills;\nCandidates with\u00a0trading experience in other categories will also be considered;\nCandidate with less experience but passionate in food & beverage industry will be considered as Assistant Trading Executive.\n\nStaff Benefit:\n\n13-month Salary\nYearly Discretionary Bonus\nMedical Insurance\nAnnual Leave\nPayable Sick Leave\nBirthday Leave\nEncourage continuing education and on-job training\nOpen office working environment\nOffer promotion opportunities and long-term career path", "employment_types": ["Full Time", "Permanent"], "selling_points": [], "locations": ["Lai Chi Kok"], "categories": ["Merchandising & Purchasing", "Furniture", "Sundries", "Others", "Trading"], "post_time": "2022-01-07T09:11:29Z", "salary": {"currency": null, "max": null, "min": null, "period": "monthly", "term": null}, "salary_visible": false, "title_keywords": ["merchandiser", "senior merchandiser"], "responsibilities": ["liaise with", "sales target", "payments", "develop"], "requirements": {"degrees": ["diploma holder", "degree"], "majors": ["business"], "languages": [], "language_level": [], "hard_skills": [], "soft_skills": ["passionate", "communication skills", "self-motivated", "independent", "hardworking"], "languages_combined": []}, "experience_required": {"duration": ["minimum 3 years"], "field": ["food", "fmcg", "trading", "beverage industry"]}}, {"job_id": "100003009026742", "location_code": "hk", "company": "TX Business Services Limited", "job_title": "\u8fa6\u516c\u5ba4\u52a9\u7406", "description": "We are a small size trading and quality control company for European and USA market, now we are sincerely invite a talent to join our dynamic team.\n\nResponsibilities:\n\nMust be strong in product development and sourcing\nStrong negotiator with fluent English and Mandarin skill\nHandling purchase orders with suppliers\u00a0\nMaintain and update order-processing system\u00a0\nFollow up production schedule\u00a0to ensure on-time delivery\u00a0\nPrepare invoices\u00a0and related documents to suppliers and clients\u00a0\nCandidates with\u00a0more experience will be considered as Senior Merchandiser\u00a0\n\nRequirements:\n\nForm 7 or above\n6 years or above merchandising experience in ceramic / gift / dinnerware / home decor & indoor furniture are definitely advantages\nProactive, independent and adaptive to a highly disciplinary company culture\nExcellent communication skill with all levels in working with customers, staff and vendors\nGood knowledge in product development & strong problem solving skill\nStrong command of spoken & written English & Mandarin\nWilling to travel\u00a0\nFamiliar with MS Office operation\nImmediate available is preferred\n\nWe offer 5-day work, MPF, Annual Leave, Medical and Bank Holiday to the right candidate. Interested parties, please send your full resume, with expected salary and availability.", "employment_types": ["Full Time"], "selling_points": [], "locations": ["Not Specified"], "categories": ["Admin & HR", "Clerical / Admin Staff", "Others", "Others", "Trading"], "post_time": "2022-01-06T08:33:51Z", "salary": {"currency": null, "max": null, "min": null, "period": "monthly", "term": null}, "salary_visible": false, "title_keywords": ["\u8fa6\u516c\u5ba4\u52a9\u7406"], "responsibilities": ["invoices", "related documents", "purchase", "maintain", "schedule"], "requirements": {"degrees": [], "majors": [], "languages": ["english", "mandarin"], "language_level": [], "hard_skills": ["problem solving", "ms office"], "soft_skills": ["communication skill", "problem solving skill", "proactive", "independent"], "languages_combined": [{"language": "english", "language_level": []}, {"language": "mandarin", "language_level": []}]}, "experience_required": {"duration": ["6 years"], "field": ["merchandising"]}}, {"job_id": "100003009025245", "location_code": "hk", "company": "Glory Top Building Materials Limited", "job_title": "Purchasing Associate", "description": "\n\u00a0 \u5de5\u4f5c\u8077\u8cac:\n\u8ca0\u8cac\u505a\u597d\u5404\u985e\u884c\u653f\u6a94\u6848\u3001\u8cc7\u6599\u7684\u6536\u767c\u8f49\u905e\u5de5\u4f5c\uff1b\u8ca0\u8cac\u4fdd\u7ba1\u6709\u95dc\u884c\u653f\u65b9\u9762\u7684\u6587\u66f8\u3001\u6a94\u6848\u6750\u6599\uff1b\u505a\u597d\u8fa6\u516c\u5ba4\u65e5\u5e38\u884c\u653f\u4e8b\u52d9\u53ca\u6587\u79d8\u5de5\u4f5c;\n\u5de5\u4f5c\u8981\u6c42:\nF5\u4ee5\u4e0a\u5b78\u6b77,\u719f\u7df4\u4f7f\u7528\u5404\u7a2e\u8fa6\u516c\u8edf\u9ad4\uff0c\u6709\u826f\u597d\u7684\u5718\u968a\u5354\u4f5c\u7cbe\u795e\u3001\u670d\u52d9\u610f\u8b58\u4ee5\u53ca\u8f03\u5f37\u7684\u4ea4\u6d41\u6e9d\u901a\u80fd\u529b\u8207\u7d44\u7e54\u5354\u8abf\u80fd\u529b;\n\u5de5\u4f5c\u6642\u9593: \u661f\u671f\u4e00\u81f3\u661f\u671f\u4e94,9:30AM-6:30PM\n\u6709\u610f\u8005\u8acb\u6309Apply Now\u7533\u8acb\n\n", "employment_types": ["Full Time"], "selling_points": ["4.5-5-day work week", "Development Opportunities", "Medical benefit"], "locations": ["Yau Tsim Mong Area"], "categories": ["Merchandising & Purchasing", "Procurement / Purchasing / Sourcing", "Others", "Trading", "Building & Construction", "Others"], "post_time": "2022-01-06T03:56:14Z", "salary": {"currency": null, "max": null, "min": null, "period": "monthly", "term": null}, "salary_visible": false, "title_keywords": ["associate"], "responsibilities": [], "requirements": {"degrees": [], "majors": [], "languages": [], "language_level": [], "hard_skills": [], "soft_skills": [], "languages_combined": []}, "experience_required": {"duration": [], "field": []}}, {"job_id": "100003009030860", "location_code": "hk", "company": "Aero Plus Corporate Management Limited", "job_title": "Secretary", "description": "Job Duties:\n\nPerform day-to-day operations including sourcing, costing, price negotiation, sampling and shipping arrangement\u00a0\nResponsible for preparing purchasing orders with overseas suppliers\nCoordinate closely with suppliers/forwarders for delivery and shipment arrangement\nWork closely with internal teams to ensure products purchased are in line with the needs of the company\nAssist in inventory control\u00a0\nProvide clerical support to all purchasing/shipment/warehouse activities\nPerform ad-hoc duties as assigned\n\nRequirements:\n\nUniversity graduate or post-secondary education with 1-2 years relevant work experience\nGood command of spoken and written English\nProficient in MS Office and Chinese Word Processing\nStrong sense of responsibility with excellent problem solving skills\nAble to work under pressure and independently\nWilling to travel to overseas suppliers (Europe and Mainland China)\nImmediate available would be an advantage\u00a0\n\nBenefits\n\nAttractive salary and career path\n4.5-5-day work week\nBank holiday, annual leave\nMedical benefit\n\nInterested parties please send your full resume indicating your expected salary and your availability by clicking \"Apply Now\".\n\nPersonal data collected will be used for recruitment purpose only.", "employment_types": ["Full Time"], "selling_points": [], "locations": ["Lai Chi Kok"], "categories": ["Others", "Trading"], "post_time": "2022-01-07T08:29:37Z", "salary": {"currency": null, "max": null, "min": null, "period": "monthly", "term": null}, "salary_visible": false, "title_keywords": ["secretary"], "responsibilities": ["provide clerical support", "price negotiation", "shipping", "shipment arrangement", "day-to-day operations", "teams", "coordinate", "inventory control", "ad-hoc duties"], "requirements": {"degrees": ["university graduate", "secondary education"], "majors": [], "languages": ["english", "chinese"], "language_level": ["good command", "proficient"], "hard_skills": ["problem solving skills", "chinese word processing", "ms office"], "soft_skills": ["work under pressure", "problem solving skills", "independently", "sense of responsibility"], "languages_combined": [{"language": "english", "language_level": ["good command"]}, {"language": "chinese", "language_level": ["proficient"]}]}, "experience_required": {"duration": ["1-2 years"], "field": ["education"]}}, {"job_id": "100003009031196", "location_code": "hk", "company": "East Asia Ornament Industrial Co Ltd", "job_title": "Merchandiser / Assistant Merchandiser", "description": "Responsibilities\n\nProvide Administrative support to CEO on business and family matters\nSchedule meetings & complex travel arrangements\nHandle expense claims for business and family reimbursements\nPrepare various type of documentations including meeting agenda, Power-point presentations, business report, etc\nMaintain records, filing and handle details of highly confidential matters\nHandle both personal and business related incoming and outgoing correspondence\nTake up ad hoc assignments as required\n\nRequirements\n\nDegree holder in any discipline\nIndependent with good multi-tasking skills\nAt least 2-3 years\u2019 experience in serving CEO position\nGood command of spoken and written English and Chinese\nStrong sense of responsibility, organized and detail-oriented\nDemonstrating high professional and personal integrity", "employment_types": ["Full Time"], "selling_points": [], "locations": ["Wong Tai Sin Area"], "categories": ["Manufacturing", "Others", "Merchandising & Purchasing", "Others", "Others", "Trading"], "post_time": "2022-01-07T09:02:39Z", "salary": {"currency": null, "max": null, "min": null, "period": "monthly", "term": null}, "salary_visible": false, "title_keywords": ["merchandiser", "assistant merchandiser"], "responsibilities": ["travel arrangements", "presentations", "maintain", "schedule", "ad hoc assignments", "provide administrative support", "report"], "requirements": {"degrees": ["degree holder"], "majors": [], "languages": ["english", "chinese"], "language_level": ["good command"], "hard_skills": [], "soft_skills": ["organized", "independent", "sense of responsibility", "integrity", "detail-oriented", "multi-tasking skills"], "languages_combined": [{"language": "english", "language_level": ["good command"]}, {"language": "chinese", "language_level": ["good command"]}]}, "experience_required": {"duration": ["at least 2-3 years"], "field": []}}, {"job_id": "100003009027046", "location_code": "hk", "company": "Ocean Well Holdings Limited", "job_title": "\u98f2\u54c1\u52a0\u5de5\u54e1**", "description": "Responsibilities:\n\nReporting to the merchandising manager, the candidate will engage in product development, sourcing, sampling,\u00a0showroom setup, photo quotation\u00a0and\u00a0order follow\u00a0up in the\u00a0seasonal ornament division.\n\nRequirements:\n\nAn ideal candidate should possess the following qualifications and competences:\u00a0\n\nSchool certificate/diploma or\u00a0degree from recognized institutions;\nMin. 2 years experience in merchandising tasks, preferably in seasonal ornament or related fields;\nSelf-motivated, responsible, diligent and organized challenger taker;\nGood communication, negotiation, and problem solving\u00a0skills;\nGood command of English and Putonghua is preferred;\nFamiliar with MS Office and Chinese Word Processing;\nKnowledge of Photoshop/AI will be an advantage.\n\nAbout us:\n\nPlease visit\u00a0www.EAornament.com.hk for our details\n\nCareer Development:\n\nRight candidate will start the career in the post of assistant merchandiser/merchandiser, and will get promote to merchandiser/senior merchandiser if he/she performs well and make contributes to the company.\u00a0\n\nOur offer:\n\nWe offer\u00a0five-day work with flexible working hours and attractive benefits including double pay, year end bonus, bank holidays, up to 16 days annual leave, medical allowance, and dental allowance.\n\nInterested candidates could apply for the above job opening by clicking APPLY NOW or\u00a0send\u00a0CV to info(at)eaornament.com.hk.\u00a0 Please\u00a0do include your current and expected salaries and date of availability in the resume.\u00a0\n\nPersonal data collected will be used for recruitment purpose only.\u00a0\u00a0", "employment_types": ["Full Time"], "selling_points": [], "locations": ["Kwai Fong"], "categories": ["Others", "Trading"], "post_time": "2022-01-06T09:03:31Z", "salary": {"currency": null, "max": null, "min": null, "period": "monthly", "term": null}, "salary_visible": false, "title_keywords": [], "responsibilities": ["reporting", "quotation", "merchandising", "setup"], "requirements": {"degrees": ["certificate", "diploma", "degree"], "majors": [], "languages": ["putonghua", "english", "chinese"], "language_level": ["good command"], "hard_skills": ["chinese word processing", "ai", "make", "problem solving skills", "ms office", "photoshop"], "soft_skills": ["flexible", "organized", "self-motivated", "negotiation", "responsible", "diligent", "communication", "problem solving skills", "ideal"], "languages_combined": [{"language": "putonghua", "language_level": ["good command"]}, {"language": "english", "language_level": ["good command"]}, {"language": "chinese", "language_level": []}]}, "experience_required": {"duration": ["2 years"], "field": ["related", "merchandising"]}}, {"job_id": "100003009027014", "location_code": "hk", "company": "A & D (Asia Pacific) Company Limited", "job_title": "Senior Administration Clerk / Administration Officer", "description": "\n\u8077\u8cac :\u8ca0\u8cac\u9910\u5ef3\u98f2\u54c1\u52a0\u5de5\u548c\u96dc\u52d9\u5de5\u4f5c\n\n\u8cc7\u6b77 :\u6c92\u6709\u5b78\u6b77\u8981\u6c42; \u4e00\u822c\u7cb5\u8a9e\u512a\u5148; \u61c2\u8b80\u5beb\u4e2d\u6587; \u53ef\u5373\u6642\u4e0a\u73ed\u512a\u5148\n\n\u5f85\u9047 :\u6bcf\u6708$15,000, \u6709\u52e4\u5de5\u734e\u91d1, \u5e74\u50479\u5929, \u751f\u65e5\u5047, \u914c\u60c5\u6027\u82b1\u7d05, \u91ab\u7642\u798f\u5229, \u5a5a\u5047, \u65b0\u4eba\u734e$3000 \u53ca\u71df\u696d\u734e\u91d1, \u4e2d\u534812\u6642\u81f3\u4e0b\u534810\u6642/ \u4e2d\u534812\u6642\u81f3\u4e0b\u534811\u6642, \u6bcf\u9031\u5de5\u4f5c5\u5929\u81f36\u5929,\u8f2a\u73ed,\u8f2a\u4f11, \u6bcf\u5929\u5de5\u4f5c 9 \u5c0f\u6642, \u6bcf\u67085\u5929\u4f11\u606f\u65e5, 1\u5c0f\u6642\u7528\u81b3\u6642\u9593\n\n\u7533\u8acb\u9808\u77e5 :\u6c42\u8077\u8005\u53ef\u81f4\u96fb60842368\u8207\u6d77\u5a01\u96c6\u5718\u6709\u9650\u516c\u53f8\u738b\u5c0f\u59d0\u806f\u7d61\u3002\n\n", "employment_types": ["Full Time"], "selling_points": [], "locations": ["Tuen Mun Area"], "categories": ["Admin & HR", "Clerical / Admin Staff", "Others", "Trading"], "post_time": "2022-01-06T09:00:43Z", "salary": {"currency": null, "max": null, "min": null, "period": "monthly", "term": null}, "salary_visible": false, "title_keywords": ["administration officer", "senior administration clerk"], "responsibilities": [], "requirements": {"degrees": [], "majors": [], "languages": [], "language_level": [], "hard_skills": [], "soft_skills": [], "languages_combined": []}, "experience_required": {"duration": [], "field": []}}, {"job_id": "100003009018892", "location_code": "hk", "company": "Oriental Partners Ltd", "job_title": "Sales Executive", "description": "Job Duties & Job Responsibilities\n\nManages and overlook all the works and jobs related to administration within the department, ensure all departments work in a coherent, traceable and well coordinated administration framework, and respecting the administration procedures\nCoordinate with internal and external parties for providing maintenance/repair/renovation services\u00a0\nAssist in departmental support as required which includes ordering supplies and handling the incoming supplies' shipment, custom clearance and following up delivery schedules\u00a0\nTo perform ad-hoc duties as assigned\n\nJob Requirements\n\nForm 5 or above with minimum\u00a02 years' relevant experience preferred\nHR experience would be an advantage\u00a0\nGood command of written and spoken English and Cantonese, proficiency in Mandarin would be an advantage\u00a0\nProficient in MS in Word, Excel, Access, PowerPoint and Chinese Word Processing\nGood interpersonal, analytical and communication skills\nMature, independent, well-organized, self-motivated and with high sense of responsibility\u00a0\nAble to work under pressure on tight schedules and willing to work overtime\u00a0\nCandidate with less experience will also be considered as Senior Administration Clerk\u00a0\nImmediate available is highly preferred\n\nWork Location: Tuen Mun (10mins distance to MTR station)\n\nWe offer attractive remuneration package to the successful candidates. Interested parties, please send full resume stating current and expected salary together with date availability by clicking \u201cApply Now\u201d. Information provided is only for recruitment purposes and will be treated with strict confidential.\u00a0", "employment_types": ["Full Time"], "selling_points": [], "locations": ["Kwai Fong"], "categories": ["Others", "Trading", "Sales, CS & Business Devpt", "Sales Administration"], "post_time": "2022-01-04T05:54:49Z", "salary": {"currency": null, "max": null, "min": null, "period": "monthly", "term": null}, "salary_visible": false, "title_keywords": ["sales executive"], "responsibilities": ["maintenance", "schedules", "internal and external parties", "coordinate with", "renovation", "administration procedures", "repair", "ad-hoc duties", "custom clearance", "administration"], "requirements": {"degrees": ["form 5 or above"], "majors": [], "languages": ["cantonese", "english", "chinese", "mandarin"], "language_level": ["advantage", "proficiency", "good command", "proficient"], "hard_skills": ["excel", "chinese word processing", "word", "powerpoint"], "soft_skills": ["communication skills", "self-motivated", "work overtime", "independent", "high sense of responsibility", "well-organized", "mature", "interpersonal", "work under pressure"], "languages_combined": [{"language": "cantonese", "language_level": ["advantage", "good command"]}, {"language": "english", "language_level": ["proficiency", "advantage", "good command"]}, {"language": "chinese", "language_level": ["proficient"]}, {"language": "mandarin", "language_level": ["proficiency", "advantage", "good command"]}]}, "experience_required": {"duration": ["minimum 2 years"], "field": ["hr", "relevant experience", "administration"]}}, {"job_id": "100003009022344", "location_code": "hk", "company": "Asian Sourcing Link Limited", "job_title": "Sales & Marketing Coordinator", "description": "What we are looking for:\n\nCollaborate with market leads, sales, design & factories for successful product launch campaigns. Support new product introduction projects to success in accordance with defined targets, strategies, and goals.\n\n\n\nWhat You Will Own & How You Will Make A Difference:\n\nLiaise with market leads, sales, design, quality, and factories on the evaluation of component & product specification and quality requirement;\nCoordinate and support sample preparation activities for packaging development, qualification test and marketing purposes, etc.;\nMonitor packaging development to meet specific packaging requirements;\nExecute project plan for the assigned projects;\nMonitor, track, and provide an update on the project progress;\nWork with related parties for project changes. Manage and execute changes to achieve project outputs and goals;\nPerform other duties as assigned.\n\n\n\nWho You Are:\n\nTertiary education or above;\n2 years or above working experience. Experiences in project management or related duties preferred but not essential;\nGood command of written and spoken in English and Chinese;\nGood communication skills and project management skills;\nProficient in MS Project, MS Word, MS Excel & MS PowerPoint.", "employment_types": ["Full Time", "Permanent"], "selling_points": ["Provide full administration & coordinate supports", "Coordination with various dept.", "with at least 4 years relevant exp"], "locations": ["Causeway Bay"], "categories": ["Merchandising & Purchasing", "Procurement / Purchasing / Sourcing", "Others", "Trading", "Sales, CS & Business Devpt", "Sales Administration"], "post_time": "2022-01-05T05:27:24Z", "salary": {"currency": null, "max": null, "min": null, "period": "monthly", "term": null}, "salary_visible": false, "title_keywords": ["marketing coordinator", "sales"], "responsibilities": ["collaborate with", "perform other duties", "sample preparation", "quality", "monitor", "design", "project plan", "coordinate", "project progress", "project management", "communication", "evaluation", "liaise with"], "requirements": {"degrees": [], "majors": [], "languages": ["english", "chinese"], "language_level": ["good command"], "hard_skills": ["make", "project management", "ms excel", "ms powerpoint", "ms word"], "soft_skills": ["communication skills", "project management", "project management skills"], "languages_combined": [{"language": "english", "language_level": ["good command"]}, {"language": "chinese", "language_level": ["good command"]}]}, "experience_required": {"duration": ["2 years"], "field": ["related", "project management"]}}, {"job_id": "100003009025766", "location_code": "hk", "company": "Pointer Investment (Hong Kong) Ltd", "job_title": "Trade assistant", "description": "\n\u8077\u8cac :\u4e00\u822c\u73a9\u5177\u6a5f\u52a0\u5de5\u54e1\u5de5\u4f5c\n\n\u8cc7\u6b77 :\u6c92\u6709\u5b78\u6b77\u8981\u6c42; \u826f\u597d\u7cb5\u8a9e\u512a\u5148; \u61c2\u8b80\u5beb\u4e2d\u6587; \u61c2\u8eca\u5e8a\u53ca\u945a\u5e8a\n\n\u5f85\u9047 :\u6bcf\u5c0f\u6642$70.00, \u6709\u6bcf\u6708\u52e4\u5de5\u734e\u91d1$1000, \u751f\u65e5\u5047 \u53ca\u54e1\u5de5\u8cfc\u7269\u512a\u60e0, \u661f\u671f\u4e00\u81f3\u516d: \u4e0a\u53488\u664245\u5206\u81f3\u4e0b\u53486\u6642\u534a, \u6bcf\u9031\u5de5\u4f5c3\u5929\u81f34\u5929, \u6bcf\u5929\u5de5\u4f5c 4 - 5 \u5c0f\u6642, \u9577\u77ed\u9031\n\n\u7533\u8acb\u9808\u77e5 :\u6c42\u8077\u8005\u53ef\u81f4\u96fb24638348\u8207\u5104\u8c50\u74b0\u7403\u5be6\u696d\u6709\u9650\u516c\u53f8\u8449\u5c0f\u59d0\u806f\u7d61\u3002\n\n", "employment_types": ["Full Time", "Contract"], "selling_points": ["Trade Assistant", "Experience in trading companies is an advantage", "Attractive salary,5-day work,Medical insurance"], "locations": ["Admiralty"], "categories": ["Others", "Trading"], "post_time": "2022-01-06T06:27:18Z", "salary": {"currency": "HKD", "max": 19999, "min": 14000, "period": "monthly", "term": null}, "salary_visible": true, "title_keywords": ["assistant"], "responsibilities": [], "requirements": {"degrees": [], "majors": [], "languages": [], "language_level": [], "hard_skills": [], "soft_skills": [], "languages_combined": []}, "experience_required": {"duration": [], "field": []}}, {"job_id": "100003009029168", "location_code": "hk", "company": "Meyer Manufacturing Co Ltd", "job_title": "Project Coordinator (Cookware)", "description": "Job Responsibilities:\n\u2022 Responsible for the proper functioning and maintenance of office, including but not limited to procurement of office supplies, printing of business cards and publication/promotional materials, outsourced IT support, and general office repairs and maintenance.\n\u2022 Provide administrative and clerical support including data entry, product certification application, filing and document control.\n\u2022 Assist Operation Manager and to discharge the routine accounting works of our company including book-keeping and bank reconciliation, etc.\nJob Requirements:\n\u2022 Bachelor\u2019s Degree or above in Accounting, Finance or related disciplines.\n\u2022 Over one year of related working experience.\n\u2022 Good command of both written and spoken English and Cantonese.\n\u2022 Immediately available is highly preferred\nWe offer 5 days work week and a competitive remuneration package to the right candidate. Interested parties please apply by sending full resume with current and expected salary and state the earliest date of availability.", "employment_types": ["Full Time", "Permanent"], "selling_points": ["Support all aspect product dev&quality requirement", "Meticulous & result-driven project co-ordinator", "Good command of written & spoken in Eng & Chi"], "locations": ["Ngau Tau Kok"], "categories": ["Manufacturing", "Product Development / Management", "Merchandising & Purchasing", "Home Appliances", "Others", "Trading"], "post_time": "2022-01-07T04:31:30Z", "salary": {"currency": null, "max": null, "min": null, "period": "monthly", "term": null}, "salary_visible": false, "title_keywords": ["project coordinator"], "responsibilities": ["control", "maintenance", "data entry", "office supplies", "bank reconciliation", "promotional materials", "book-keeping", "administrative and clerical support", "publication"], "requirements": {"degrees": ["degree or above", "bachelor"], "majors": ["related disciplines", "finance", "accounting"], "languages": ["cantonese", "english"], "language_level": ["good command"], "hard_skills": [], "soft_skills": [], "languages_combined": [{"language": "cantonese", "language_level": ["good command"]}, {"language": "english", "language_level": ["good command"]}]}, "experience_required": {"duration": ["one year"], "field": ["related"]}}, {"job_id": "100003009026890", "location_code": "hk", "company": "Yick Fung Global Industrial Limited", "job_title": "\u73a9\u5177\u6a5f\u52a0\u5de5\u54e1", "description": "\n\n\nWhat we are looking for:\n\nWe are looking for a competitive and trustworthy Sales Executive to help us maintain a good relationship with current customers and keep an eye on market trends and potentials to explore new businesses.\n\n\n\nWhat You Will Own & How You Will Make A Difference:\n\nManage existing accounts, experience in handling the US market is an advantage;\nWork closely and independently with overseas customers in sales activities;\nMeet customers regularly;\nDemonstrate and present products;\nMaintain accurate records;\nReview sales performance and explore new business potential;\nEnsure high levels of customer satisfaction;\nLiaise with internal stakeholders from concept through production stage;\nPerform such other duties as may be assigned.\n\n\nWho You Are:\n\nDiploma or above in any disciplines;\nAt least 2 years relevant experience in household merchandise;\nExperience in handling the US market is an advantage;\nStrong interpersonal and communication skills;\nGood team player, a strong sense of responsibility;\nMature, well organized, and detailed mind;\nAble to excel in a fast-paced and dynamic environment with tight deadlines;\nGood command of English & fluency in speaking English & Putonghua.\n** Candidates with more experience will be considered as Senior Sales Executive.\n\n", "employment_types": ["Part Time"], "selling_points": [], "locations": ["Tuen Mun Area"], "categories": ["Others", "Trading"], "post_time": "2022-01-06T08:49:56Z", "salary": {"currency": null, "max": null, "min": null, "period": "hourly", "term": null}, "salary_visible": false, "title_keywords": [], "responsibilities": [], "requirements": {"degrees": ["diploma or above"], "majors": ["any disciplines"], "languages": [], "language_level": [], "hard_skills": [], "soft_skills": ["communication skills", "good team player", "interpersonal", "sense of responsibility"], "languages_combined": []}, "experience_required": {"duration": ["at least 2 years"], "field": ["relevant experience"]}}, {"job_id": "100003009027391", "location_code": "hk", "company": "Tradetech Supplies Limited", "job_title": "Administrator Assistant / officer", "description": "Responsibilities:\nIdentify training needs, design, deliver training programs for front-line staff to enhance and polish customer services skill, product knowledge, and drive the Company culture;\nEvaluate training effectiveness by monitoring retail staff product knowledge through frequent shop visit;\nCreate fun and exciting learning programs or projects for team enhancement;\nAssist in developing and maintaining e-learning platforms;\nMaintain and update training materials and record, prepare training statistics and reports in regular basis;\nOther ad hoc L&D projects when necessary.\nRequirements:\nDegree holder in Human Resources Management or related discipline;\nAt least 2-3 years\u2019 relevant working experience preferably in retail;\nProactive learner with positive and can do attitude;\nResponsible, flexible and able to work in a fast-paced environment;\nProficient in video editing, Excel, PowerPoint, Chinese word processing;\nGood command of written and spoken English, Cantonese and Putonghua;\nCandidate with less experience will be considered as Assistant Training Officer.\n\nOur remuneration packages will be commensurate with your QUALITY.\n\nPlease send your application with current and expected salary, and quote the relevant reference number on the subject by clicking \"Apply Now\".\n\nAll information provided will be treated in strict confidence and used for recruitment purposes only.", "employment_types": ["Full Time"], "selling_points": ["Full Time", "Kowloon Bay", "Year End Bonnus"], "locations": ["Kowloon Bay"], "categories": ["Others", "Trading"], "post_time": "2022-01-06T16:08:22Z", "salary": {"currency": null, "max": null, "min": null, "period": "monthly", "term": null}, "salary_visible": false, "title_keywords": ["administrator", "officer", "assistant"], "responsibilities": ["ad hoc", "maintaining", "monitoring", "developing", "design", "customer services", "evaluate", "maintain", "reports"], "requirements": {"degrees": ["degree holder"], "majors": [], "languages": ["cantonese", "putonghua", "english", "chinese"], "language_level": ["good command", "proficient"], "hard_skills": ["video editing", "excel", "chinese word processing", "powerpoint"], "soft_skills": ["flexible", "confidence", "responsible", "fast-paced environment", "proactive", "positive"], "languages_combined": [{"language": "cantonese", "language_level": ["good command"]}, {"language": "putonghua", "language_level": ["good command"]}, {"language": "english", "language_level": ["good command"]}, {"language": "chinese", "language_level": ["proficient"]}]}, "experience_required": {"duration": ["at least 2-3 years"], "field": ["training", "retail", "relevant working experience"]}}, {"job_id": "100003009019599", "location_code": "hk", "company": "Meyer Manufacturing Co Ltd", "job_title": "Sales Executive (Kitchenware, Overseas Trading Sales Coordination)", "description": "Responsibilities:\n\nResponsible for\u00a0products sourcing and trading;\nLiaison with customers and suppliers to achieve\u00a0sales target;\nDevelop new suppliers and products;\nNegotiate and build relationship with buyers and sellers;\nFollow up contract issuance, shipments, payments and other trade related matters;\nLiaise with internal departments for trade operation matters.\u00a0\n\nRequirements:\n\nDegree / Diploma holder in Purchasing / Trading / Sourcing / Business\u00a0related discipline preferable;\nSolid trading and sourcing experience will be an\u00a0advantage;\nHardworking, independent and self-motivated with excellent communication skills\u00a0\n\nStaff Benefit:\n\n13-month Salary\nYearly Discretionary Bonus\nMedical Insurance\nPayable Sick Leave\nBirthday Leave", "employment_types": ["Full Time", "Permanent"], "selling_points": ["2+yrs relevant experience in household merchandise", "Exp in handling US market accounts is an advantage", "Strong leadership, interpersonal skills"], "locations": ["Ngau Tau Kok"], "categories": ["Manufacturing", "Product Development / Management", "Merchandising & Purchasing", "Home Appliances", "Others", "Trading"], "post_time": "2022-01-04T08:32:50Z", "salary": {"currency": null, "max": null, "min": null, "period": "monthly", "term": null}, "salary_visible": false, "title_keywords": ["sales", "sales executive"], "responsibilities": ["liaise with", "sales target", "payments", "develop"], "requirements": {"degrees": ["diploma holder", "degree"], "majors": ["business"], "languages": [], "language_level": [], "hard_skills": [], "soft_skills": ["communication skills", "self-motivated", "independent", "hardworking"], "languages_combined": []}, "experience_required": {"duration": [], "field": ["trading"]}}, {"job_id": "100003009026502", "location_code": "hk", "company": "Bossini Enterprises Limited", "job_title": "Training Officer", "description": "Chinese state owned listed company mainly doing import and export trading in Hong Kong for over 30 years and it\u2019 s parent company is one of the world's top 500 companies. Pointer Investment (H.K.) Limited is now urgently seeking for a high caliber to fill the position: Trade Assistant\u00a0\n\nJob description:\nPrepare trading doc e.g. contract, invoice, packing list and Certificate of Origin\nReview and make notice of the letter of credit to the sales\nMaintain good relationship with the bank, sales and other related parties\nHandle other administrative duties if necessary\u00a0\n\nJob requirements:\n\nDSE or above (Fresh graduate is also welcome)\nGraduated with major of International Trade is an advantage\nExperience in trading, import/export companies is an advantage\nGeneral command in English, Mandarin and Cantonese\nExperience in Microsoft Office is an advantage\nGood execution, communication and coordination skills\nImmediate available is highly preferred", "employment_types": ["Full Time", "Permanent"], "selling_points": ["Fashion Brand with full of fun and challenge", "Degree holder or above", "2-3 years of solid experience in training"], "locations": ["Tseung Kwan O"], "categories": ["Manufacturing", "Garment / Textile", "Sales, CS & Business Devpt", "Retail Sales", "Others", "Trading"], "post_time": "2022-01-06T08:14:38Z", "salary": {"currency": null, "max": null, "min": null, "period": "monthly", "term": null}, "salary_visible": false, "title_keywords": ["officer"], "responsibilities": ["invoice", "review", "maintain good relationship", "packing list", "certificate of origin", "administrative duties"], "requirements": {"degrees": ["fresh graduate", "dse"], "majors": [], "languages": ["cantonese", "english", "mandarin"], "language_level": [], "hard_skills": ["microsoft office"], "soft_skills": ["communication", "coordination skills"], "languages_combined": [{"language": "cantonese", "language_level": []}, {"language": "english", "language_level": []}, {"language": "mandarin", "language_level": []}]}, "experience_required": {"duration": [], "field": ["trading"]}}, {"job_id": "100003009024881", "location_code": "hk", "company": "King-Choice Group Limited", "job_title": "Assistant Sales Manager (Trims)", "description": "Industry Field: Trims Accessories Trading\n\n- Be responsible and work hard\n- Contact with customers via e-mail and phone\n- Follow up the sample order\n- Work with colleagues as teamwork\n- Work out of office sometimes\n- Report constantly to directors for sales planning", "employment_types": ["Full Time", "Permanent"], "selling_points": ["Minimum 3 years of experience", "Competitive package", "5 Days Work"], "locations": ["Shatin Area"], "categories": ["Manufacturing", "Garment / Textile", "Merchandising & Purchasing", "Woven / Knit", "Others", "Trading"], "post_time": "2022-01-06T02:48:03Z", "salary": {"currency": "HKD", "max": 24999, "min": 20000, "period": "monthly", "term": null}, "salary_visible": true, "title_keywords": ["assistant sales manager"], "responsibilities": ["planning", "contact", "report"], "requirements": {"degrees": [], "majors": [], "languages": [], "language_level": [], "hard_skills": [], "soft_skills": ["teamwork", "responsible"], "languages_combined": []}, "experience_required": {"duration": [], "field": []}}, {"job_id": "100003009029537", "location_code": "hk", "company": "Certa Limited", "job_title": "WAREHOUSE OFFICER, ADMINISTRATOR & JUNIOR ACCOUNTANT", "description": "A Sales & Marketing Coordinator will be part of a team who are responsible for planning, optimizing and executing promotional product development and sale.\n\nThe Job: Manage overseas accounts independently through the product lifecycle by coordinating enquiries, quotation, product development, order processing, safety testing and supply chain management collaborating with merchandising, quality management, creative and Global logistics departments and being the key communication conduit with the overseas sales teams.\n\n\u00a0Key responsibilities:\n\nPlan, execute, track and optimize promotional projects and campaigns for Key Account or Regional Sales Directors\nProvide timely and effective administrative support to the global sales team and Co-ordinate samples approvals\nManage all briefs submitted by the sales team. Analyse, action any queries and provide clear instructions to the ASL merchandising team as required.\nManage critical path of all projects to ensure all elements of the production, QA and shipping process are followed.\nMaintain up-to-date records and the status for accurate records for sales reports and statistics\nCreate sales documents such as Quotation Request, Sales Proposal and coordinate SO and PO in ERP system.\nCommunicate with intercompany departments on daily basis to ensure production & supply is on schedule.\nWork with internal QA department to plan and arrange Quality Management plans.\n\n\u00a0The Person:\n\nMinimum 4 - 5years\u2019 experience in Promotional Merchandising; candidates with experience in gift & premium will be at an advantage.\nExperience in working closely with Global Sales teams.\nAbility in handling product development projects independently through good communication, problem-solving skills and effective organization skills.\nMust be proactive, attentive to details with excellent analytical and numerical skills and able to meet tight deadlines.\nGood PC knowledge in using MS office applications, SAP is preference.\nGood command of language skills in both written and spoken Chinese/Mandarin and English\n\nWe offer a friendly working environment in Causeway Bay, a five day week and fringe benefits that include medical insurance and 15 days paid leave annually.\n\nInterested candidates please email full CV including previous work experience, current and expected salary by clicking 'Apply Now'\n\nPersonal data collected will be used for recruitment purpose only.", "employment_types": ["Full Time", "Permanent", "Contract", "Internship"], "selling_points": [], "locations": ["Southern Area"], "categories": ["Others", "Trading"], "post_time": "2022-01-07T05:33:16Z", "salary": {"currency": "HKD", "max": 19999, "min": 14000, "period": "monthly", "term": null}, "salary_visible": true, "title_keywords": ["junior accountant", "officer", "administrator"], "responsibilities": ["communicate with", "management", "shipping", "sales reports", "administrative support", "quotation", "merchandising", "quality", "coordinate", "maintain", "sales team", "schedule", "plan", "plans", "analyse"], "requirements": {"degrees": [], "majors": [], "languages": ["english", "chinese", "mandarin"], "language_level": ["good command"], "hard_skills": ["sap", "numerical skills", "problem-solving skills", "pc knowledge", "ms office"], "soft_skills": ["meet tight deadlines", "independently", "attentive to details", "communication", "friendly", "organization skills", "problem-solving skills", "proactive"], "languages_combined": [{"language": "english", "language_level": ["good command"]}, {"language": "chinese", "language_level": ["good command"]}, {"language": "mandarin", "language_level": ["good command"]}]}, "experience_required": {"duration": [], "field": ["merchandising"]}}, {"job_id": "100003009028805", "location_code": "hk", "company": "Enternal Cycle Productions Group Limited", "job_title": "Quality Assurance Officer (Hardgoods: Sundries, Home Decoration)", "description": "-\u00a0\u00a0\u00a0\u00a0\u00a0\u00a0\u00a0\u00a0\u00a0\u00a0\u00a0\u00a0\u00a0 Supervise QC team in China on field inspection for quality / lab test issues\n\n-\u00a0\u00a0\u00a0\u00a0\u00a0\u00a0\u00a0\u00a0\u00a0\u00a0\u00a0\u00a0\u00a0 Monitor and follow through product standards with internal / external QC & Client QC Team from sample development, production and order delivery\n\n-\u00a0\u00a0\u00a0\u00a0\u00a0\u00a0\u00a0\u00a0\u00a0\u00a0\u00a0\u00a0\u00a0 Plan, manage and review internal / external inspection schedule / inspection reports for timely production and delivery of orders\n\n-\u00a0\u00a0\u00a0\u00a0\u00a0\u00a0\u00a0\u00a0\u00a0\u00a0\u00a0\u00a0\u00a0 Lab test handling, included test inquiry, quotations, sample submission, monitor & review test result in a timely manner\n\n-\u00a0\u00a0\u00a0\u00a0\u00a0\u00a0\u00a0\u00a0\u00a0\u00a0\u00a0\u00a0\u00a0 Evaluate critical and major issues on product quality and communicate with merchandisers on quality issues / production delay\n\n-\u00a0\u00a0\u00a0\u00a0\u00a0\u00a0\u00a0\u00a0\u00a0\u00a0\u00a0\u00a0\u00a0 Perform other ad hoc duties as assigned by management\n\nRequirements\n\n-\u00a0\u00a0\u00a0\u00a0\u00a0\u00a0\u00a0\u00a0\u00a0\u00a0\u00a0\u00a0\u00a0 Degree holder or relevant level of experience\n\n-\u00a0\u00a0\u00a0\u00a0\u00a0\u00a0\u00a0\u00a0\u00a0\u00a0\u00a0\u00a0\u00a0 Minimum 5 years relevant experience in a Quality Assurance / Quality Control position. Factory inspection practice in an international sourcing company is an advantage.\n\n-\u00a0\u00a0\u00a0\u00a0\u00a0\u00a0\u00a0\u00a0\u00a0\u00a0\u00a0\u00a0\u00a0 Solid technical expertise in decor products\n\n-\u00a0\u00a0\u00a0\u00a0\u00a0\u00a0\u00a0\u00a0\u00a0\u00a0\u00a0\u00a0\u00a0 Detail orientated with a high degree of work ethics and integrity\n\n-\u00a0\u00a0\u00a0\u00a0\u00a0\u00a0\u00a0\u00a0\u00a0\u00a0\u00a0\u00a0\u00a0 Self-motivated, responsible, diligent and organized\n\n-\u00a0\u00a0\u00a0\u00a0\u00a0\u00a0\u00a0\u00a0\u00a0\u00a0\u00a0\u00a0\u00a0 Good command in written and spoken English and Chinese; Fluency in Mandarin an advantage\n\n-\u00a0 \u00a0 \u00a0 \u00a0 \u00a0 \u00a0 \u00a0 Proficient in MS Office such as Word, Excel, Chinese WP, Power point\u00a0", "employment_types": ["Full Time", "Permanent"], "selling_points": ["Min 5 years QC exp ; immediate available prefer", "Hardgoods: Sundries, Home Decoration", "5-day wk / Bonus / Bank Medical Annual Leave"], "locations": ["Tsuen Wan Area"], "categories": ["Merchandising & Purchasing", "Sundries", "Manufacturing", "Quality Assurance, Control & Testing / ISO", "Others", "Trading"], "post_time": "2022-01-07T03:13:47Z", "salary": {"currency": null, "max": null, "min": null, "period": "monthly", "term": null}, "salary_visible": false, "title_keywords": ["quality assurance officer"], "responsibilities": ["communicate with", "ad hoc duties", "management", "inspection reports", "review", "monitor", "quality", "a timely manner", "inspection", "evaluate", "schedule", "plan", "quality control"], "requirements": {"degrees": ["degree", "degree holder"], "majors": [], "languages": ["english", "chinese", "mandarin"], "language_level": ["fluency", "advantage", "good command", "proficient"], "hard_skills": ["excel", "chinese wp", "word", "power point", "ms office"], "soft_skills": ["organized", "self-motivated", "responsible", "timely", "integrity", "diligent", "detail orientated"], "languages_combined": [{"language": "english", "language_level": ["good command"]}, {"language": "chinese", "language_level": ["good command", "proficient"]}, {"language": "mandarin", "language_level": ["fluency", "advantage"]}]}, "experience_required": {"duration": ["minimum 5 years"], "field": ["relevant experience", "quality control", "quality assurance"]}}, {"job_id": "100003009021461", "location_code": "hk", "company": "Haystar Consultant Limited", "job_title": "Shipping Coordinator (Pharmaceutical Trading / 5-day work+\u5f48\u6027\u4e0a\u73ed\u6642\u9593 / $18-20K)", "description": "Duties:\n\n\nReport to the Business Manager (English-speaking)\nCollect & analyze sales data to consolidate the sales report\nHandle quotations, customer orders, invoices, I/E documents and declaration\nUpdate the order status in the system and maintain the database\nLiaise with factories to monitor production and ensure timely shipment\nHandle all transportation arrangements including ocean/airfreight as well as local transportation\u00a0\u00a0\n\nRequirements:\u00a0\u00a0\n\nOver 3 years of shipping or logistics experience in the\u00a0manufacturing/trading industry\nGood command of spoken & written English and Mandarin\nProficiency in MS Office and Chinese word processing\nFlexible, stable and pleasant personality\u00a0\u00a0\n\nThe remuneration package is commensurate with competency & experience. Interested parties please send full resume (WORD format) with expected salary and availability to HR Department.\n\nTo learn more about us, please visit our website: www.haystar.com.hk\n\nInformation provided by applicants will be treated in strict confidence and used for recruitment purposes only.", "employment_types": ["Full Time", "Permanent"], "selling_points": ["5 days work, work-life-balance work", "Solid experience in Manufacturing/Trading field", "A friendly and stable financial background company"], "locations": ["Hung Hom"], "categories": ["Transportation & Logistics", "Shipping", "Supply Chain", "Others", "Trading"], "post_time": "2022-01-05T08:51:41Z", "salary": {"currency": null, "max": null, "min": null, "period": "monthly", "term": null}, "salary_visible": false, "title_keywords": ["shipping coordinator"], "responsibilities": ["sales report", "invoices", "data", "monitor", "maintain", "database", "liaise with", "report"], "requirements": {"degrees": [], "majors": [], "languages": ["english", "chinese", "mandarin"], "language_level": ["proficiency", "good command"], "hard_skills": ["chinese word processing", "ms office"], "soft_skills": ["flexible", "stable", "pleasant"], "languages_combined": [{"language": "english", "language_level": ["good command"]}, {"language": "chinese", "language_level": ["proficiency"]}, {"language": "mandarin", "language_level": ["good command"]}]}, "experience_required": {"duration": ["3 years"], "field": ["manufacturing", "logistics", "trading"]}}, {"job_id": "100003009019617", "location_code": "hk", "company": "BST (HK) Limited", "job_title": "Junior Accountant", "description": "BST (HK) Ltd is a trading company incorporated in HK and doing trading of iron ore and coal.\u00a0 We want to recruit a junior accountant for our Account Department.\u00a0 The requirement would be as follows:\n\nHandle daily accounting functions, better can handle full set of accounts\nSupport administrative routine works\nIVE graduate with Diploma in Accountancy, or above\n1-3 years working experience in accounting related field\nGood PC skills at Excel, Word, Peachtree and Outlook\nAble to communicate in Cantonese and English, Mandarin is an advantage", "employment_types": ["Full Time"], "selling_points": [], "locations": ["North Point"], "categories": ["Accounting", "Accountant", "Admin & HR", "Clerical / Admin Staff", "Others", "Trading"], "post_time": "2022-01-05T08:10:13Z", "salary": {"currency": null, "max": null, "min": null, "period": "monthly", "term": null}, "salary_visible": false, "title_keywords": ["junior accountant"], "responsibilities": ["daily accounting", "full set of accounts"], "requirements": {"degrees": ["diploma"], "majors": ["accountancy"], "languages": ["cantonese", "english", "mandarin"], "language_level": ["advantage"], "hard_skills": ["excel", "word", "outlook", "peachtree", "pc skills"], "soft_skills": [], "languages_combined": [{"language": "cantonese", "language_level": []}, {"language": "english", "language_level": []}, {"language": "mandarin", "language_level": ["advantage"]}]}, "experience_required": {"duration": ["1-3 years"], "field": ["related", "accounting"]}}, {"job_id": "100003009024887", "location_code": "hk", "company": "King-Choice Group Limited", "job_title": "Assistant Sales Clerk", "description": "Industry Field: Trims Accessories Trading\n\n- Be responsible and work hard\n- Office Duties work\n- Contact with customers via e-mail and phone\n- Follow up the sample order\n- Work with colleagues as teamwork\n- Well communication skills", "employment_types": ["Full Time", "Permanent"], "selling_points": ["minimum 1 year of experience", "Competitive package", "5 Days Work"], "locations": ["Shatin Area"], "categories": ["Manufacturing", "Garment / Textile", "Merchandising & Purchasing", "Textiles", "Others", "Trading"], "post_time": "2022-01-06T02:48:30Z", "salary": {"currency": "HKD", "max": 13999, "min": 11000, "period": "monthly", "term": null}, "salary_visible": true, "title_keywords": ["sales clerk", "assistant"], "responsibilities": ["communication", "contact"], "requirements": {"degrees": [], "majors": [], "languages": [], "language_level": [], "hard_skills": [], "soft_skills": ["communication skills", "teamwork", "responsible"], "languages_combined": []}, "experience_required": {"duration": [], "field": []}}, {"job_id": "100003009021682", "location_code": "hk", "company": "Ever Alliance International Limited", "job_title": "Sales Executive", "description": "Responsibilities:\n\nIdentify prospective customers\nKeep management updated on market intelligence\nLiaison with operation team and oversea offices in managing the schedules and payments\n\nRequirements:\n\nDiploma or above\nExperience in Sales and Marketing / Trading in food industry is preferred, but not a must\nGood team player, mature, self-motived and outgoing\nMulti-tasking capability with good reporting and communication skills\nGood personality and be able to deal with all levels\nFluent in both written and spoken English and Chinese\n\nAn attractive remuneration package including 5 days work week, 14-18 days annual leave, dental & medical insurance, performance bonus and career development opportunities will be offered to the right candidate. If you are interested, please send your full resume, current and expected salary to\u00a0clam @ pmidistribution . com . hk.", "employment_types": ["Full Time", "Permanent"], "selling_points": [], "locations": ["Kwai Tsing Area"], "categories": ["Hospitality / F & B", "Food & Beverage", "Sales, CS & Business Devpt", "Others", "Others", "Trading"], "post_time": "2022-01-05T04:25:01Z", "salary": {"currency": null, "max": null, "min": null, "period": "monthly", "term": null}, "salary_visible": false, "title_keywords": ["sales executive"], "responsibilities": ["schedules", "management", "payments"], "requirements": {"degrees": ["diploma or above"], "majors": [], "languages": ["english", "chinese"], "language_level": ["fluent"], "hard_skills": [], "soft_skills": ["outgoing", "communication skills", "good team player", "mature", "multi-tasking"], "languages_combined": [{"language": "english", "language_level": ["fluent"]}, {"language": "chinese", "language_level": ["fluent"]}]}, "experience_required": {"duration": [], "field": ["marketing", "trading", "food industry"]}}, {"job_id": "100003009020060", "location_code": "hk", "company": "PERSOL Hong Kong", "job_title": "Shipping / Sales Coordinator(5 day/Near MTR/Stable & Sizable Company)", "description": "Our client, a sizable Japanese based MNC, is now seeking for a high caliber individual to join their team as Shipping / Sales Coordinator.\n\n\nJob Descriptions:\n\n\nFollow up order with overseas offices, customers, suppliers and internal parties\nUpdate the necessary information required for shipment and updating the internal system\u00a0\nHandle shipping-related documents, import & Export custom Declaration etc..\nPerform general administrative and clerical support\u00a0\n\nRequirements:\n\n\n3 years or above relevant working experience in shipping field\nConversational English and Mandarin\nDiploma or above\n\nInterested parties please send your application via email to\u00a0Apply Now\u00a0or\u00a0kibi_tsang @persolhk.com\u00a0For any inquiries, please do not hesitate to contact me at\u00a0(852) 2971-2513.\n\nPlease note that only short listed candidate will be notified.\n\nWe also have various job vacancies from our well-established clients in all kinds of fields, please feel free to contact us. We are always willing to give you support on your career development.\n\nOur company website:\u00a0http://www.persolhk.com\n\nAll information received will be treated in strict confidence and used for recruitment purpose only.", "employment_types": ["Full Time", "Permanent"], "selling_points": ["Convenient location,stable, global sizable company", "Double Pay,Bonus,5 day, OT Pay", "3 years experience in shipping"], "locations": ["Central & Western Area"], "categories": ["Transportation & Logistics", "Shipping", "Others", "Trading", "Sales, CS & Business Devpt", "Sales Administration"], "post_time": "2022-01-04T09:50:21Z", "salary": {"currency": null, "max": null, "min": null, "period": "monthly", "term": null}, "salary_visible": false, "title_keywords": ["shipping", "sales"], "responsibilities": ["shipping", "related documents", "custom declaration", "administrative and clerical support", "internal parties"], "requirements": {"degrees": ["diploma or above"], "majors": [], "languages": ["english", "mandarin"], "language_level": ["conversational"], "hard_skills": [], "soft_skills": [], "languages_combined": [{"language": "english", "language_level": ["conversational"]}, {"language": "mandarin", "language_level": ["conversational"]}]}, "experience_required": {"duration": ["3 years"], "field": ["relevant working experience"]}}, {"job_id": "100003009016449", "location_code": "hk", "company": "", "job_title": "Shipping  Clerk", "description": "AN EXPORT FIRM\u00a0 IN HUNG\u00a0HOM\u00a0 REQUIRES :\u00a0\n\n-\u00a0 F. 5\u00a0 Standard\n\n-\u00a0\u00a0Full set of\u00a0\u00a0shipping\u00a0document\u00a0\n\n-\u00a0 Mandarin is preferred\n\n-\u00a0 Minimum 3\u00a0 years \u00a0working experience\u00a0\n\n-\u00a0\u00a0PC knowledge including e-mail\u00a0\n\n\u00a0\u00a0\u00a0\u00a0\u00a0\u00a0\u00a0\u00a0\u00a0 For any enquiries,\u00a0 please Call\u00a0 6232-4144.\n", "employment_types": ["Full Time", "Permanent"], "selling_points": [], "locations": ["Hung Hom"], "categories": ["Others", "Trading"], "post_time": "2022-01-03T09:05:36Z", "salary": {"currency": null, "max": null, "min": null, "period": "monthly", "term": null}, "salary_visible": false, "title_keywords": ["shipping", "clerk"], "responsibilities": ["shipping document"], "requirements": {"degrees": [], "majors": [], "languages": ["mandarin"], "language_level": [], "hard_skills": ["pc knowledge", "shipping document"], "soft_skills": [], "languages_combined": [{"language": "mandarin", "language_level": []}]}, "experience_required": {"duration": [], "field": []}}, {"job_id": "100003009016867", "location_code": "hk", "company": "Puleo Asia Limited", "job_title": "Merchandiser (Seasonal, Home Decorations & Gifts)", "description": "Certa Limited, an Italian Trading in Wong Chuk Hang is looking for:\nwww.certa.com.hk\n\n1. WAREHOUSE OFFICER - SALARY $18,000 - $20,000\nTo assist Warehouse Management, to perform general warehouse duties, such as receiving, counting, sorting out, shelving, delivery goods, etc.\u00a0Responsible for carrying goods, stock taking, updating inventory records as well as arranging and tidying up warehouse.\u00a0Willing to take up physical works, good working attitude, hardworking, good listener, honest and responsible.\n\n2. ADMINISTRATOR\u00a0- SALARY $16,000 - $18,000\u00a0\nTo perform clerical duties, to help an office run smoothly and efficiently. \u00a0\u00a0Duties include answering phone calls and emails, greeting and directing office visitors to designated meeting areas and building spreadsheets or presentations for leadership staff.\n\n3. INTERN JUNIOR ACCOUNTANT -\u00a0SALARY $13,000 - $16,000\nResponsible for assisting in the preparation of financial and accounting reports, handling over all accounts and book keeping.\u00a0Gathering payroll expenses and input into appropriate entry line.\u00a0Analysing financial statements and prepare balance sheets.\n\nCompetitive salary, Medical & dental insurance, 16 days AL & Discretionary Bonus\u00a0\n\n\n", "employment_types": ["Full Time", "Permanent"], "selling_points": [], "locations": ["Hung Hom"], "categories": ["Merchandising & Purchasing", "Others", "Others", "Trading"], "post_time": "2022-01-03T10:00:45Z", "salary": {"currency": null, "max": null, "min": null, "period": "monthly", "term": null}, "salary_visible": false, "title_keywords": ["merchandiser"], "responsibilities": ["management", "expenses", "presentations", "financial statements", "reports", "insurance", "updating inventory records", "payroll", "phone calls"], "requirements": {"degrees": [], "majors": [], "languages": ["italian"], "language_level": [], "hard_skills": ["presentations"], "soft_skills": ["good working attitude", "responsible", "honest", "leadership", "hardworking"], "languages_combined": [{"language": "italian", "language_level": []}]}, "experience_required": {"duration": [], "field": []}}, {"job_id": "100003009014475", "location_code": "hk", "company": "Branford Limited", "job_title": "Shipping Clerk (13th month salary)", "description": "Responsibilities:\u00a0\n\nLiaise with overseas customers to help the supervisor in handling their inquires\nCapable to work independently with factories and internal parties, in order to help the supervisor follow-up on orders to ensure production quality and on-time delivery\nJob Requirements:\n\n\nTertiary education is preferred\nMinimum 3 years of merchandising and trading experiences is a must. Less experience will be considered as Assistant Merchandiser\nFluent in both written and spoken English and Chinese (Cantonese and Mandarin)\nWell organized, with good interpersonal and communication skill\nMature, stable, detail-minded, self-motivated and being a good team player, able to work under pressure and tight deadline\nAble to work in a fast pace environment and overtime\nExperience in working with major retailers in US & European markets is an advantage\nProficiency in on-hand computer skill : MS Excel, Chinese Word processing & Outlook Knowledge\nRequire to visit in China\nImmediate available is highly preferred\n\nWe offer competitive remuneration package. For Interested parties, please submit your resume by clicking ''Apply Now'' button as below.\u00a0\u00a0All the information provide by applicants will be used for\u00a0recruitment purpose only.\u00a0", "employment_types": ["Permanent"], "selling_points": [], "locations": ["Tsim Sha Tsui"], "categories": ["Merchandising & Purchasing", "Electronics", "Toy", "Others", "Trading"], "post_time": "2022-01-03T03:29:05Z", "salary": {"currency": null, "max": null, "min": null, "period": "monthly", "term": null}, "salary_visible": false, "title_keywords": ["shipping clerk"], "responsibilities": ["liaise with", "quality", "internal parties"], "requirements": {"degrees": [], "majors": [], "languages": ["cantonese", "english", "chinese", "mandarin"], "language_level": ["proficiency", "fluent"], "hard_skills": ["chinese word processing", "ms excel", "computer skill", "outlook"], "soft_skills": ["detail-minded", "self-motivated", "good team player", "communication skill", "well organized", "mature", "stable", "interpersonal", "work under pressure"], "languages_combined": [{"language": "cantonese", "language_level": []}, {"language": "english", "language_level": ["fluent"]}, {"language": "chinese", "language_level": ["fluent", "proficiency"]}, {"language": "mandarin", "language_level": []}]}, "experience_required": {"duration": ["minimum 3 years"], "field": ["merchandising", "trading"]}}, {"job_id": "100003009017682", "location_code": "hk", "company": "GDH Guangnan Hong Company Limited", "job_title": "\u696d\u52d9\u54e1/\u696d\u52d9\u4e3b\u7ba1", "description": "Shipping Clerk\n\nBranford Limited is an international children\u2019s toy company and we are currently looking for a talented and motivated Shipping Clerk to cope with the growth of the company.\n\nRequirements:\n\n\u00a0 \u00a0 \u00a0 \u00a0 F. 5 level / HKDSE (Grade 3+ in English or Mathematics) or above\n\u00a0\u00a0\u00a0\u00a0\u00a0\u00a0\u00a0 Minimum 3 years logistic experience\n\u00a0\u00a0\u00a0\u00a0\u00a0\u00a0\u00a0 Handle full set I/E documents and experience in ERP system is an asset\n\u00a0\u00a0\u00a0\u00a0\u00a0\u00a0\u00a0 Proficient in Microsoft Word and Excel\n\u00a0\u00a0\u00a0\u00a0\u00a0\u00a0\u00a0 Good command of English and fluent Putonghua as well as Cantonese\n\u00a0\u00a0\u00a0\u00a0\u00a0\u00a0\u00a0 Self-motivated, able to work independently and follow through on required tasks\n\u00a0\u00a0\u00a0\u00a0\u00a0\u00a0\u00a0 Good team player and good interpersonal skills\n\u00a0\u00a0\u00a0\u00a0\u00a0\u00a0\u00a0 Strong sense of responsibility\n\n\u00a0Responsibilities:\n\n\u00a0 \u00a0 \u00a0 \u00a0 Work closely with internal merchandising team and suppliers\n\u00a0\u00a0\u00a0\u00a0\u00a0\u00a0\u00a0 Coordinate and follow up delivery arrangement with forwarders and suppliers\n\u00a0\u00a0\u00a0\u00a0\u00a0\u00a0\u00a0 Handle booking, export documents and customer payment\n\u00a0\u00a0\u00a0\u00a0\u00a0\u00a0\u00a0 Assist in general office work and ad hoc tasks as required.\n\n\u00a0Benefits:\n\n\u00a0 \u00a0 \u00a0 \u00a05-days work week\n\u00a0 \u00a0 \u00a0 13th month salary\n\u00a0 \u00a0 \u00a0 Medical and detail coverage\n\nPlease feel free to visit our current Web Sites: ogdolls.com, myglittergirls.com, woodzeez.com, terrauniverse.com, mybtoys.com and battatco.com.\n\nPlease apply with full resume and expected salary though applies now.\n\nPersonal data collected will be used for recruitment purpose only.", "employment_types": ["Full Time", "Permanent"], "selling_points": ["\u4e2d\u4e94\u6216\u4ee5\u4e0a\u7a0b\u5ea6", "\u5169\u5e74\u4ee5\u4e0a\u92b7\u552e\u3001\u696d\u52d9\u62d3\u5c55\u7d93\u9a57", "\u53ef\u5373\u6642\u4e0a\u73ed\u512a\u5148\u8003\u616e"], "locations": ["Wan Chai"], "categories": ["Others", "Trading"], "post_time": "2022-01-04T01:42:12Z", "salary": {"currency": null, "max": null, "min": null, "period": "monthly", "term": null}, "salary_visible": false, "title_keywords": [], "responsibilities": ["ad hoc tasks", "merchandising", "coordinate", "payment", "booking"], "requirements": {"degrees": ["hkdse"], "majors": ["mathematics"], "languages": ["cantonese", "putonghua", "english"], "language_level": ["good command", "fluent"], "hard_skills": ["excel", "erp system", "microsoft word"], "soft_skills": ["good team player", "self-motivated", "work independently", "sense of responsibility", "interpersonal skills"], "languages_combined": [{"language": "cantonese", "language_level": ["good command"]}, {"language": "putonghua", "language_level": ["good command"]}, {"language": "english", "language_level": ["fluent", "good command"]}]}, "experience_required": {"duration": ["minimum 3 years"], "field": ["erp system"]}}, {"job_id": "100003009015081", "location_code": "hk", "company": "Union Group (1989) Limited", "job_title": "Sales Executive (Global market)", "description": "\u5de5\u4f5c\u8077\u8cac\uff1a\n\n\u62d3\u5c55\u8cbf\u6613\u3001\u6279\u767c\u6e20\u9053\uff0c\u767c\u6398\u6f5b\u5728\u4f9b\u61c9\u5546\u53ca\u5ba2\u6236\u7fa4\u9ad4\uff1b\n\u7522\u54c1\u63a8\u5ee3\uff0c\u6536\u96c6\u5e02\u5834\u8cc7\u8a0a\u5236\u5b9a\u76f8\u61c9\u7684\u92b7\u552e\u65b9\u6848\uff1b\n\u8ca0\u8cac\u696d\u52d9\u6578\u64da\u7684\u7d71\u8a08\u53ca\u5206\u6790\u5de5\u4f5c\uff1b\n\u8ca0\u8cac\u8655\u7406\u65e5\u5e38\u6587\u66f8\u5de5\u4f5c\u3002\n\u5de5\u4f5c\u8981\u6c42\uff1a\n\n\u4e2d\u4e94\u6216\u4ee5\u4e0a\u7a0b\u5ea6\uff1b\n\u5169\u5e74\u4ee5\u4e0a\u92b7\u552e\u3001\u696d\u52d9\u62d3\u5c55\u7d93\u9a57\uff0c\u719f\u6089\u570b\u969b\u8cbf\u6613\u53ca\u98df\u54c1\u6279\u767c\u696d\u52d9\u8005\u512a\u5148\uff1b\n\u826f\u597d\u7684\u7cb5\u8a9e\u3001\u666e\u901a\u8a71\u53ca\u82f1\u8a9e\u6e9d\u901a\u3001\u66f8\u5beb\u80fd\u529b\uff1b\n\u53cd\u61c9\u654f\u6377\u3001\u8a8d\u771f\u8ca0\u8cac\uff0c\u6297\u58d3\u80fd\u529b\u5f37\uff0c\u6709\u89aa\u548c\u529b\uff1b\n\u53ef\u5373\u6642\u4e0a\u73ed\u8005\u512a\u5148\u8003\u616e\u3002\n\u85aa\u916c\u798f\u5229\uff1a\n\n\u8077\u696d\u767c\u5c55\u6a5f\u5236\u53ca\u6649\u5347\u6a5f\u6703\n\u5e74\u5ea6\u96d9\u85aa\n\u5348\u81b3\u88dc\u8cbc\n\u91ab\u7642\u4fdd\u96aa\u53ca\u4eba\u58fd\u4fdd\u96aa\n\u7533\u8acb\u65b9\u5f0f\uff1a\n\n\n\u00a0 \u00a0 \u00a0 \u00a0\u6709\u610f\u8005\u8acb\u9ede\u64ca\"Apply\u00a0Now\u00a0\"\uff0c\u6295\u905e\u60a8\u7684\u4e2d\u6587\u7c21\u6b77\uff0c\u8aa0\u9080\u60a8\u52a0\u5165\u6211\u5011\uff01\n\n\n\n\nWe offer a competitive salary and fringe\u00a0benefits to the right\u00a0candidate. Interested parties please send detailed resume\u00a0(in Chinese)\u00a0with availability, current and expected salaries by clicking the\u00a0Apply\u00a0Now\u00a0button.\u00a0All applications will be treated in strict confidence and used for recruitment purpose.", "employment_types": ["Full Time"], "selling_points": [], "locations": ["Tsuen Wan Area"], "categories": ["Sales, CS & Business Devpt", "Business Development", "Channel / Distribution", "Others", "Trading"], "post_time": "2022-01-03T05:21:59Z", "salary": {"currency": null, "max": null, "min": null, "period": "monthly", "term": null}, "salary_visible": false, "title_keywords": ["sales executive"], "responsibilities": [], "requirements": {"degrees": [], "majors": [], "languages": [], "language_level": [], "hard_skills": [], "soft_skills": [], "languages_combined": []}, "experience_required": {"duration": [], "field": []}}, {"job_id": "100003009015387", "location_code": "hk", "company": "Supermoon Limited", "job_title": "\u5e97\u52d9\u52a9\u7406 Shop Assistant", "description": "Job Responsibilities:\n\nReport to Account Manager, APAC\nWorks with Account Manager to develop inspirational briefs and briefings for creatives\nGoes to lengths to gain a thorough understanding of all aspects of the brand and the motivations/behavior patterns of consumers in the marketplace\nUnderstand the market trends in Asia-Pacific\nDevelop and present marketing/promotion ideas and proposal\nMaintain contact with clients in relation to their promotional requirements\nStrong client servicing skills for day to day management and key client contact\nServe as liaison between the client and creative team, you are expected to have knowledge in project management skills to track the progression of campaigns\n\nJob Requirements:\n\nDegree in Marketing, Commerce or a related discipline\nMinimum 2 years of relevant experience in marketing, preferably in promotional or creative agency\nOverseas educated / regional exposure will be an advantage\nAbility to conceptualize, write creative presentation\nExcellent communication and presentation skills - fluent in written and spoken English and Chinese (Cantonese), Mandarin is a plus\nDetailed minded and being able to work under pressure\nA passion for creative excellence and enjoys team work\n\nWe offer a friendly working environment in Causeway Bay, a five day week and fringe benefits that include medical insurance and 15 days paid leave annually.\n\nInterested candidates please email full CV including previous work experience, current and expected salary by clicking \"Apply Now\".\n\nAll Personal data collected will be used for recruitment purpose only.", "employment_types": ["Full Time", "Permanent"], "selling_points": ["\u5e97\u52d9\u52a9\u7406", "\u91ab\u7642", "\u5e74\u7d42\u596c\u91d1 (\u914c\u60c5\u6027-\u8996\u4e4e\u8868\u73fe)"], "locations": ["Others"], "categories": ["Others", "Trading"], "post_time": "2022-01-03T06:37:17Z", "salary": {"currency": null, "max": null, "min": null, "period": "monthly", "term": null}, "salary_visible": false, "title_keywords": ["shop assistant"], "responsibilities": ["management", "ideas", "develop", "project management", "maintain", "contact", "report"], "requirements": {"degrees": ["degree"], "majors": ["marketing"], "languages": ["cantonese", "english", "chinese", "mandarin"], "language_level": ["excellent", "fluent"], "hard_skills": ["plus"], "soft_skills": ["passion for", "work under pressure", "communication", "presentation skills", "friendly", "creative", "presentation", "detailed"], "languages_combined": [{"language": "cantonese", "language_level": ["excellent", "fluent"]}, {"language": "english", "language_level": ["excellent", "fluent"]}, {"language": "chinese", "language_level": ["excellent", "fluent"]}, {"language": "mandarin", "language_level": ["excellent", "fluent"]}]}, "experience_required": {"duration": ["minimum 2 years"], "field": ["agency", "marketing", "relevant experience"]}}, {"job_id": "100003009013648", "location_code": "hk", "company": "Asian Sourcing Link Limited", "job_title": "Senior Account Executive / Account Executive", "description": "This role will play an integral part of our Finance Department by effectively and systematically provide accurate information and optimize team collaboration.\n\n\u00a0Job Description:\u00a0\n\n\nLead HK accounting team to perform day-to-day accounting functions\nResponsible for full sets of accounts\nPrepare monthly financial statements, reports and records by collecting, analyzing and summarizing account information\nReview and monitor the accounting reports of Asia offices\nPrepare monthly group consolidated and budget reports\nPrepare for financial audit and coordinate the audit process\nLiaise with auditors\nAssist in monitoring internal control system of HK & Asia offices\nEnsure compliance with relevant laws and regulations and integrity of financial data\n\n\u00a0Job Requirements:\u00a0\n\nDegree/ Diploma, major in Accounting\n6+ years working experience in accounting field, more experienced candidates will be considered as Accounting Manager\nGood in written and spoken English & Mandarin\nProficient in MS Office applications, especially Excel\nSelf motivated, good team player, high standard of accuracy\n\nWe offer good remuneration package to the right candidate including\u00a05 days work, Flexible working\u00a0hour,\u00a0Bank Holiday, 15 days annual\u00a0leaves, Medical & Dental Insurance, Bonus and Double Pay.\n\nWe are an equal opportunities employer and welcome applications from all candidates with the required skills and experience.\u00a0Interested candidates\u00a0can send resume, application letter, expected salary and date of availability through Jobs DB.\n\nPersonal data collected will be used for recruitment purpose only.\u00a0\u00a0Only qualified candidates will be contacted.\u00a0\n\nFor more information about our company, please free to visit our website:\u00a0\u00a0www.casinoglobalsourcing.com", "employment_types": ["Full Time", "Permanent"], "selling_points": ["Understand the market trends in Asia-Pacific", "Minimum 2 years of relevant experience", "Five day week, medical insurance"], "locations": ["Causeway Bay"], "categories": ["Sales, CS & Business Devpt", "Business Development", "Others", "Trading", "Sales Administration"], "post_time": "2022-01-03T02:34:18Z", "salary": {"currency": null, "max": null, "min": null, "period": "monthly", "term": null}, "salary_visible": false, "title_keywords": ["account executive", "senior account executive"], "responsibilities": ["regulations", "budget reports", "data", "review", "monitor", "audit", "monitoring", "ensure compliance", "coordinate", "prepare monthly financial statements", "reports", "liaise with", "internal control"], "requirements": {"degrees": ["diploma", "degree"], "majors": ["accounting"], "languages": ["english", "mandarin"], "language_level": ["good"], "hard_skills": ["excel", "ms office"], "soft_skills": ["self motivated", "good team player", "flexible"], "languages_combined": [{"language": "english", "language_level": ["good"]}, {"language": "mandarin", "language_level": ["good"]}]}, "experience_required": {"duration": ["6+ years"], "field": ["accounting"]}}, {"job_id": "100003009023979", "location_code": "hk", "company": "Groupe Casino Limited", "job_title": "Senior Accountant (Leader)", "description": "Job Responsibilities:\n\nHandling daily accounting operation in A/R, A/P, G/L, issuing cheque and TT payment\nProcess expenses claims and reimbursements\nHandling general administration works\nHandle ad hoc projects as assigned\n\nRequirements:\n\nLCC Level III or above\nAt least 1-2 years relevant experience\nProficient in MS office, good systems skills and PEACHTREE knowledge is preferable\nMature, responsible and able to work independently with minimal supervision\nGood communication skill and a good team player\nImmediate availability preferable\n\nPersonal data collected will be treated in strict confidence and used for recruitment purpose only. Unsuccessful applications will be deleted from our files after 6 months.", "employment_types": ["Full Time"], "selling_points": [], "locations": ["Wan Chai Area"], "categories": ["Accounting", "Accountant", "Others", "Others", "Trading"], "post_time": "2022-01-05T10:13:15Z", "salary": {"currency": null, "max": null, "min": null, "period": "monthly", "term": null}, "salary_visible": false, "title_keywords": ["senior accountant"], "responsibilities": ["expenses", "payment", "ad hoc projects", "daily accounting", "administration"], "requirements": {"degrees": [], "majors": [], "languages": [], "language_level": [], "hard_skills": ["peachtree", "lcc", "ms office"], "soft_skills": ["good team player", "work independently", "confidence", "responsible", "communication skill", "mature"], "languages_combined": []}, "experience_required": {"duration": ["at least 1-2 years"], "field": ["relevant experience"]}}, {"job_id": "100003009021441", "location_code": "hk", "company": "Heroine International Limited", "job_title": "Account Clerk", "description": "We are a leading infant and toddler product brand owner with head office located in UK and Global Procurement & Sourcing Office in Hong Kong. Our operation is across different countries and products with global distribution channels. To cope with the business growth, we are looking for a dynamic and experienced personnel to take up the position of:\n\nAssistant Supply Planning Manager\n\nJob Responsibilities:\n\n\n\n\u00a0\u00a0\u00a0\u00a0\u00a0\u00a0\u00a0\u00a0 Manage the team to monitor suppliers\u2019 production and shipping activities to ensure on time delivery to meet availability requirement\n\u00a0\u00a0\u00a0\u00a0\u00a0\u00a0\u00a0\u00a0 Daily email communication with UK team, Suppliers, internal factory.\n\u00a0\u00a0\u00a0\u00a0\u00a0\u00a0\u00a0\u00a0 Pre-alert UK Supply Planning Team for any shipment risk to minimize the impact to the business.\n\u00a0\u00a0\u00a0\u00a0\u00a0\u00a0\u00a0\u00a0 Prepare Capacity files for key suppliers based on monthly RP data\n\u00a0\u00a0\u00a0\u00a0\u00a0\u00a0\u00a0\u00a0 Coordinate with Supply Planning Team and all suppliers on re-scheduling activities (defer/expedite/cancel) to avoid out of stock and keep the stock at optimal level.\n\u00a0\u00a0\u00a0\u00a0\u00a0\u00a0\u00a0\u00a0 Work as the bridge between suppliers and UK supply Planning Team to prioritize the production in case of any capacity issue.\n\u00a0\u00a0\u00a0\u00a0\u00a0\u00a0\u00a0\u00a0 Prepare monthly report\n\nJob Requirement:\n\n\n\n\u00a0\u00a0\u00a0\u00a0\u00a0\u00a0\u00a0\u00a0 Higher Diploma or above\n\u00a0\u00a0\u00a0\u00a0\u00a0\u00a0\u00a0\u00a0 At least 5 years practical experience in Supply Planning operation\n\u00a0\u00a0\u00a0\u00a0\u00a0\u00a0\u00a0\u00a0 Working experience in buying office will be an advantage.\n\u00a0\u00a0\u00a0\u00a0\u00a0\u00a0\u00a0\u00a0 Proficiency in MS Office application (MS Word, Excel, PowerPoint, Chinese Word Processing).\n\u00a0\u00a0\u00a0\u00a0\u00a0\u00a0\u00a0\u00a0 Good command in both written and spoken English, Mandarin and Cantonese.\n\u00a0\u00a0\u00a0\u00a0\u00a0\u00a0\u00a0\u00a0 Willing to work in team environment focused on efficiency.\n\u00a0\u00a0\u00a0\u00a0\u00a0\u00a0\u00a0\u00a0 Mature and be able to work independently.\n\u00a0\u00a0\u00a0\u00a0\u00a0\u00a0\u00a0\u00a0 Immediately available is highly preferred", "employment_types": ["Full Time"], "selling_points": [], "locations": ["Tsuen Wan Area"], "categories": ["Accounting", "Accounting Clerk / Supervisor", "Admin & HR", "Clerical / Admin Staff", "Others", "Trading"], "post_time": "2022-01-05T03:59:16Z", "salary": {"currency": null, "max": null, "min": null, "period": "monthly", "term": null}, "salary_visible": false, "title_keywords": ["account clerk"], "responsibilities": ["shipping", "data", "ensure on time delivery", "monitor", "coordinate with", "communication", "scheduling", "monthly report", "planning"], "requirements": {"degrees": ["higher diploma or above"], "majors": [], "languages": ["cantonese", "english", "chinese", "mandarin"], "language_level": ["proficiency", "good command"], "hard_skills": ["supply planning", "excel", "chinese word processing", "powerpoint", "ms office", "ms word"], "soft_skills": ["mature", "work independently", "focused"], "languages_combined": [{"language": "cantonese", "language_level": ["good command"]}, {"language": "english", "language_level": ["good command"]}, {"language": "chinese", "language_level": ["proficiency"]}, {"language": "mandarin", "language_level": ["good command"]}]}, "experience_required": {"duration": ["at least 5 years"], "field": ["operation", "planning"]}}, {"job_id": "100003009006975", "location_code": "hk", "company": "Product Marketing Mayborn Ltd.", "job_title": "Assistant Supply Planning Manager", "description": "Horizon Brands, registered as ADC Solutions HK Limited, is a company which pushes the limits to add more to your everyday life. The result is a thriving and ever-expanding portfolio of uniquely useful Automotive Accessories, Consumer Electronics, and Home & Lifestyle Products for people who care about quality and value. We couldn\u2019t do any of it without our team, which is driven to bring innovation, style, and value to everyday consumer products by pushing the limits of what can be done. Join us!\u00a0\n\nWe are currently looking for TWO\u00a0QA\u00a0Specialists\u00a0to support our Quality team. The positions are located in Hong Kong.\u00a0\n\nYOUR MISSION:\u00a0\u00a0You will ensure that products and procedures adhere to our company\u2019s quality standards and regulations. You will conduct regular inspections and assessments, review document, develop comprehensive reports.\u00a0\u00a0\n\nKEY RESPONSIBILITIES:\u00a0\n\n\nHandle all technical aspects of related products\u00a0\nEnsure the technical process, quality process and prepare all testing reports\u00a0\nEnsure product control process flow\u00a0\n\nPerform quality checking on products\u00a0\n\nWork closely with internal parties for testing requirements and customer enquiries\u00a0\n\nMaintain a strong relationship with suppliers\u00a0\nPerform any other tasks as assigned by QA Manager\nREQUIREMENTS:\u00a0\u00a0\n\nHigher Diploma or above in Engineering or other relevant disciplines\u00a0\nMinimum 2 years of relevant work experience preferably in sourcing/trading/buying offices/laboratories/manufacturers\u00a0\n\nInternational Safety Standard (UL, ISTA, ASTM & AQL) background is a plus\u00a0\n\nExperience in 3rd party laboratory is a plus\u00a0\n\nStrong comprehensive ability and data mining skills\u00a0\n\nExcellent communication and organizational skills\u00a0\u00a0\n\nFast learner, detail-minded and responsible with good project management skills\u00a0\u00a0\n\nWilling to travel domestic and international, especially to China\u00a0\n\nCan work independently and in a team\u00a0\n\nGood command of written and spoken English, Cantonese and Mandarin\u00a0\n\nProficient in MS Office (Excel / Word / PowerPoint / Outlook) and Chinese typing\u00a0\nCandidates with less experience will be considered as QA Assistant\u00a0\nWHAT WE OFFER:\u00a0\n\nDouble Pay + Performance Bonus\u00a0\nMedical and Dental allowances\u00a0\n\nEducational Assistance Allowance\u00a0\nProfit Bonus Plan\n5-day work week, bank holidays", "employment_types": ["Full Time"], "selling_points": ["At least 5 years' experience in Supply Planning", "Higher diploma or above", "Flexible working between home & office"], "locations": ["Kwun Tong"], "categories": ["Transportation & Logistics", "Supply Chain", "Merchandising & Purchasing", "Others", "Others", "Trading"], "post_time": "2022-01-02T15:26:28Z", "salary": {"currency": null, "max": null, "min": null, "period": "monthly", "term": null}, "salary_visible": false, "title_keywords": ["assistant supply planning manager"], "responsibilities": ["control", "quality checking", "customer enquiries", "quality", "testing", "other tasks", "maintain", "reports", "internal parties"], "requirements": {"degrees": ["higher diploma or above"], "majors": ["engineering"], "languages": ["cantonese", "english", "chinese", "mandarin"], "language_level": ["good command", "proficient"], "hard_skills": ["excel", "plus", "word", "powerpoint", "typing", "project management", "outlook", "data mining", "ms office"], "soft_skills": ["detail-minded", "organizational skills", "work independently", "responsible", "project management skills", "communication", "comprehensive", "data mining skills", "fast learner"], "languages_combined": [{"language": "cantonese", "language_level": ["good command"]}, {"language": "english", "language_level": ["good command"]}, {"language": "chinese", "language_level": ["proficient"]}, {"language": "mandarin", "language_level": ["good command"]}]}, "experience_required": {"duration": ["minimum 2 years"], "field": ["laboratory", "trading", "buying offices", "qa"]}}, {"job_id": "100003009019220", "location_code": "hk", "company": "ADC Solutions HK Limited", "job_title": "QA Specialist (2 positions)", "description": "\n\n\nWhat We Are Looking For:\n\nTo oversee accounts and work directly with marketing companies and clients on the development of product & pricing strategy;\nTo make sure everything goes well from product development, pricing to delivery of goods;\nTo handle post-delivery issues such as quality complaints, customer chargebacks, payment;\nTo manage & maintain product and data information within company systems (Global Vision).\n\n\n\u00a0What You Will Own & How You Will Make A Difference:\n\nTo maintain & update cost/pricing files;\nTo liaise with Costing Department on product costs;\nTo prepare and submit quotations to marketing arms/direct customers;\nTo follow up Clients Day-to-Day issues;\nTo attend customers\u2019 meetings to perform duty and aid business;\nTo closely monitor customer\u2019s chargebacks & overdue payments;\nTo be responsible for supporting product development;\nTo complete forms, e.g., new customer & new item set up;\nTo define/amend product specifications on new/existing products\nTo monitor communication between marketing arms/direct customers & factories;\nTo manage & maintain product and data information within company systems;\nTo attend training/seminar to develop relevant knowledge, techniques, and skills;\nTo perform & complete jobs & projects as requested;\nTo supervise supporting staff (if any).\n\n\u00a0\nWho You Are:\u00a0\n\nUniversity graduate, min 3 years relevant working experience;\nExcellent command of both English and Chinese;\nProficiency in MS Office and PC knowledge;\nAble to work under pressure and independently;\nBe Initiative, responsible, and have a sense of leadership;\nStrong organizing capability, effective presentation and communication skills;\nGood marketing sense, creative with an analytical mind.", "employment_types": ["Full Time", "Permanent"], "selling_points": [], "locations": ["Shatin Area"], "categories": ["Manufacturing", "Quality Assurance, Control & Testing / ISO", "Others", "Trading"], "post_time": "2022-01-04T08:36:23Z", "salary": {"currency": null, "max": null, "min": null, "period": "monthly", "term": null}, "salary_visible": false, "title_keywords": ["specialist"], "responsibilities": ["cost", "delivery issues", "data", "systems", "quality", "monitor", "develop", "communication", "payment", "maintain", "payments", "specifications", "liaise with", "costs", "work under pressure"], "requirements": {"degrees": ["university graduate"], "majors": [], "languages": ["english", "chinese"], "language_level": ["excellent"], "hard_skills": ["make", "pc knowledge", "ms office"], "soft_skills": ["communication skills", "independently", "marketing sense", "responsible", "presentation", "communication", "analytical mind", "creative", "leadership", "initiative", "work under pressure"], "languages_combined": [{"language": "english", "language_level": ["excellent"]}, {"language": "chinese", "language_level": ["excellent"]}]}, "experience_required": {"duration": ["min 3 years"], "field": ["relevant working experience"]}}, {"job_id": "100003009012982", "location_code": "hk", "company": "Meyer Manufacturing Co Ltd", "job_title": "Marketing Executive", "description": "Responsibilities\n\n\nTo achieve the monthly sales target and collection budget\nManage\u00a0regional 3PL warehousing operation, perform periodically stock take with 3PL\u00a0provider\nAct as a main coordinator between the company and 3PL on delivery arrangement and order processing\nReview\u00a0internal / external customer feedback on operation issue and develop prompt and effective action plan\nDeal\u00a0with 3PL distribution partner to improve service to customer in a cost effective manner\nManage\u00a0logistics cost by conducting regular analysis and negotiating with the service provider for the best terms/condition for the Company\nMeet P&L Target for individual project and apply cost control\nOversee\u00a0the warehouse and daily operations of logistics team in alignment with internal policy and client\u2019s request\nPrepare\u00a0inventory and goods inventory reports\nConduct\u00a0stock reconciliation\nArrange import and export\nAnalyze data and reports on logistics operation performance for management review\nDaily\u00a0transaction checking and adjust accordingly\nWork with\u00a0regional sales team and establish inventory planning accordingly with consideration of lead time\nAble to handle full set of I/E & L/C documents independently\nMonitor\u00a0& track order status, to solve shipping issues with forwarders\nGood receiving in system\nOther ad-hoc assignment\n\nRequirements\n\n\nTertiary education or above in logistics or supply chain or related disciplines\nAt least\u00a05 years\u2019 experience of which 2 years were at supervisory level in logistics fields, experience of handling 3PL management is preferable\nPrevious warehouse relocation experience is an advantage\nGood command of English, Cantonese and Putonghua\nProficiency in computer software (Word, Excel, PowerPoint and Outlook) and Chinese word processing\nSensitive to data, good command of data processing and communications\nExperienced in Oracle is preferred\u00a0 \u00a0 \u00a0 \u00a0 \u00a0\u00a0\n\nWe offer attractive remuneration package, benefits packages as well as excellent opportunities for career advancement and development. Please send your application letter with FULL RESUME with PRESENT and EXPECTED SALARY\u00a0by clicking the\u00a0Apply Now\u00a0button.\u00a0\n\nFor more information about us, please visit our website at\u00a0www.asc-wines.com.\n\nFor those candidates who have not received further notice within 8 weeks may consider their application unsuccessful and their resumes will be filed by our HR department for further reference.", "employment_types": ["Full Time", "Permanent"], "selling_points": ["Oversee accounts & dev of product pricing strategy", "Good presenter, outgoing personality, meticulous", "Result-driven coordinator, product development exp"], "locations": ["Ngau Tau Kok"], "categories": ["Manufacturing", "Product Development / Management", "Merchandising & Purchasing", "Home Appliances", "Others", "Trading"], "post_time": "2022-01-03T00:45:18Z", "salary": {"currency": null, "max": null, "min": null, "period": "monthly", "term": null}, "salary_visible": false, "title_keywords": ["marketing executive"], "responsibilities": ["ad-hoc", "shipping", "inventory", "budget", "plan", "management review", "sales target", "monitor", "p&l", "stock take", "develop", "logistics", "reports", "analyze data", "warehousing", "cost", "review", "checking", "daily operations", "inventory planning", "analysis", "sales team", "order processing", "cost control"], "requirements": {"degrees": [], "majors": [], "languages": ["cantonese", "putonghua", "english", "chinese"], "language_level": ["proficiency", "good command"], "hard_skills": ["excel", "chinese word processing", "word", "powerpoint", "outlook", "3pl management", "processing", "oracle"], "soft_skills": ["sensitive to"], "languages_combined": [{"language": "cantonese", "language_level": ["good command"]}, {"language": "putonghua", "language_level": ["good command"]}, {"language": "english", "language_level": ["good command"]}, {"language": "chinese", "language_level": ["proficiency"]}]}, "experience_required": {"duration": ["2 years", "at least 5 years"], "field": ["supervisory level", "management", "logistics"]}}, {"job_id": "100003009013296", "location_code": "hk", "company": "ASC Fine Wines (Hong Kong) Trading Corp Ltd", "job_title": "Logistics Manager", "description": "Duties:\n\nSell famous brand products to overseas Importer/Wholesaler. (Computer hardware/ Audio/Electronic products / Cosmetic )\nIntensive search on internet to get your target client list every day.\nEmail broadcast, WhatsApp, cold-call is necessary.\nUpdate marketing site every day to attract incoming enquiries, eg. Exporters.SG buy & sell leads, PC exporters, Facebook, Instagram, etc.\nBusiness trip & exhibition is available after Covid-19 settled.\n\nRequirement:\n\n2 years overseas sales experience is preferred but not a must.\nOutgoing attitude and positive mind set.\nWilling to cold-call and interact with others.\nAbility to develop good relationship with clients.\nHave numerical sense and result oriented.\nProficient in English.\n\nBenefits:\n\nyear-end bonus, double pay after 1 year employment\nBank holidays\n5 days work\n10 days Annual Leave (maximum 19 days)\nMedical Insurance after probation period\n\nProspects:\n\nCandidates with good performance will be promoted to Product Manager who could handle buy and sell of a specific product category independently and enjoy an attractive commission scheme.", "employment_types": ["Full Time", "Permanent"], "selling_points": ["oversee warehouse & daily operations of logistics", "experience of handling 3PL management", "previous warehouse relocation experience"], "locations": ["Hung Hom"], "categories": ["Transportation & Logistics", "Supply Chain", "Sales, CS & Business Devpt", "Account Servicing", "Others", "Trading"], "post_time": "2022-01-03T02:00:10Z", "salary": {"currency": null, "max": null, "min": null, "period": "monthly", "term": null}, "salary_visible": false, "title_keywords": ["logistics manager"], "responsibilities": ["hardware", "audio", "facebook", "business trip"], "requirements": {"degrees": [], "majors": [], "languages": ["english"], "language_level": ["proficient"], "hard_skills": [], "soft_skills": ["outgoing", "result oriented", "positive"], "languages_combined": [{"language": "english", "language_level": ["proficient"]}]}, "experience_required": {"duration": ["2 years"], "field": []}}, {"job_id": "100003009014396", "location_code": "hk", "company": "Primal Chemical Co Ltd", "job_title": "QC Checker", "description": "\u4e3b\u8981\u8077\u8cac\ufe30\u8ca0\u8cac\u5e97\u8216\u65e5\u5e38\u904b\u4f5c\uff0c\u5305\u62ec\u7406\u8ca8\u3001\u8ca8\u54c1\u9673\u5217\u3001\u5e97\u8216\u6574\u6f54\u53ca\u9867\u5ba2\u670d\u52d9\u7b49\n\n\u5165\u8077\u8981\u6c42\ufe30\u5b78\u6b77\u53ca\u7d93\u9a57\u4e0d\u62d8\uff0c\u826f\u597d\u7cb5\u8a9e\uff0c\u61c2\u95b1\u8b80\u4e2d\u6587", "employment_types": ["Full Time", "Permanent"], "selling_points": [], "locations": ["Kwun Tong"], "categories": ["Others", "Trading"], "post_time": "2022-01-03T03:21:55Z", "salary": {"currency": null, "max": null, "min": null, "period": "monthly", "term": null}, "salary_visible": false, "title_keywords": [], "responsibilities": [], "requirements": {"degrees": [], "majors": [], "languages": [], "language_level": [], "hard_skills": [], "soft_skills": [], "languages_combined": []}, "experience_required": {"duration": [], "field": []}}, {"job_id": "100003009016387", "location_code": "hk", "company": "Texas Enterprise Limited", "job_title": "Account clerk / General clerk", "description": "Responsibility\n* Inspection for Incoming Packaging Materials, Starting Materials, In Process Control and Finished\u00a0\n\u00a0 \u00a0products.\n* Participate in quality assurance monitoring program, validation and qualification work of facilities\n\u00a0 \u00a0and equipment.\n* Ad hoc projects as assigned by QAO.\n\nRequirements\n* F5 or above. Fresh graduate will be welcomed.\n* Computer knowledge in MS office and strong communication skill.\n* Immediate available is preferred.\n\nOther benefit included: 5 working days, public holiday and performance bonus. Interest parties please\u00a0\nsend your resume with expected salary to us\u00a0for interview.\n\n", "employment_types": ["Full Time", "Permanent"], "selling_points": ["Leading company of Electric Household Appliance", "5 day work, bank holidays", "Double Pay, Discretionary Bonus, Medical"], "locations": ["Tsim Sha Tsui"], "categories": ["Accounting", "Accounting Clerk / Supervisor", "Others", "Others", "Trading"], "post_time": "2022-01-03T08:59:05Z", "salary": {"currency": null, "max": null, "min": null, "period": "monthly", "term": null}, "salary_visible": false, "title_keywords": ["general clerk", "account clerk"], "responsibilities": ["control", "monitoring", "quality", "inspection", "ad hoc projects"], "requirements": {"degrees": ["fresh graduate"], "majors": [], "languages": [], "language_level": [], "hard_skills": ["ms office"], "soft_skills": ["communication skill"], "languages_combined": []}, "experience_required": {"duration": [], "field": []}}, {"job_id": "100003009007264", "location_code": "hk", "company": "RMS Far East (HK) Limited", "job_title": "Sourcing Specialist/Sourcing Manager - Kids DIY/ Craft items/ Toys/Gifts", "description": "Job Highlights\n\nHighly competitive salary and benefits\n\n\u4e2d\u8cc7\u570b\u4f01\u80cc\u666f\n\nJob Responsibilities\n\nAudit the invoices from worldwide suppliers and forwarders\nVerify the selling prices and costs of each order.\nEnsure the margin of each order so as to avoid any loss.\nFind out any mistake in the invoices or orders and communicate with suppliers or colleagues for correction.\nMake and print out the invoices in company\u2019s ERP system.\nSend the invoices to customers and track the documents arrival.\n\nRequirements\n\nHigher diploma and above is a must.\nGood command of written and spoken English and Mandarin.\nMust be aggressive, careful, patient and independent.\nBe good at communication skills and teamwork.\nProficient in computer skills of Excel, Word, PowerPoint and ERP system.\nAt least 2 years working experience in office clerk.\u00a0\u00a0\n\n\nAttractive remuneration package will be offered to the right candidates with the following fringe benefits:\n\n\u00a0Double pay.\n\u00a0Performance bonus.\n\u00a0Medical insurance coverage.\n\u00a0OT pay.\n\nInterest parties, please email your CV with availability, current & expect salary.\n\n\n*Personal data collected will be used for recruitment purpose only.", "employment_types": ["Full Time", "Permanent"], "selling_points": [], "locations": ["Tsim Sha Tsui"], "categories": ["Merchandising & Purchasing", "Toy", "Others", "Trading"], "post_time": "2021-12-30T21:57:58Z", "salary": {"currency": null, "max": null, "min": null, "period": "monthly", "term": null}, "salary_visible": false, "title_keywords": ["specialist", "sourcing manager"], "responsibilities": [], "requirements": {"degrees": [], "majors": [], "languages": [], "language_level": [], "hard_skills": [], "soft_skills": [], "languages_combined": []}, "experience_required": {"duration": [], "field": []}}, {"job_id": "100003009010711", "location_code": "hk", "company": "JAC Recruitment Hong Kong Co., Limited", "job_title": "Japanese Speaking Sales Assistant (Increase position, up to 17K)", "description": "Requirements:\n\nForm 7 or above, with 5 years or above solid sourcing experiences in\u00a0Kids DIY/ Craft items/ Toys/Gifts\nGood command of English & Mandarin and with Good communication skills\nHas a good source of factories for USA market and understanding of product costing is a must\nExperiences in product development\nHas a good knowledge of US customer restrictions, testing, audits etc\nCan travel on a regular basis to factories for sourcing, negotiations and inspections\nDetail orientated approach to work\nWell organized, Self-motivated, initiative and able to work independently\nDiligent and willing to work overtime\n\nWe offer\u00a05-day work, good career prospects, medical & competitive remuneration packages to the right candidate.\u00a0", "employment_types": ["Full Time", "Permanent"], "selling_points": ["Japanese (N2~) speaking sales assistant", "Sales order follow up, delivery arrangement", "Energetic office, 5days, bonus, AL 12days up"], "locations": ["Admiralty"], "categories": ["Sales, CS & Business Devpt", "Account Servicing", "Others", "Trading", "Sales Administration"], "post_time": "2021-12-31T16:57:48Z", "salary": {"currency": null, "max": null, "min": null, "period": "monthly", "term": null}, "salary_visible": false, "title_keywords": ["sales assistant"], "responsibilities": ["communication", "audits", "testing"], "requirements": {"degrees": [], "majors": [], "languages": ["english", "mandarin"], "language_level": ["good command", "good"], "hard_skills": [], "soft_skills": ["communication skills", "self-motivated", "work independently", "work overtime", "well organized", "diligent", "detail orientated", "initiative"], "languages_combined": [{"language": "english", "language_level": ["good command", "good"]}, {"language": "mandarin", "language_level": ["good command", "good"]}]}, "experience_required": {"duration": ["5 years"], "field": ["toys", "product development"]}}, {"job_id": "100003009003475", "location_code": "hk", "company": "PACK & VAC LIMITED", "job_title": "Sales Assistant / Document Clerk - 5 Days -", "description": "Job Description ( Normally indoor work )\u00a0\n\n* Manage customer care - Delivery & stock ( ERP system with Indoor )\n\u00a0 ( we have driver self )\u00a0\n* base document follow up - Trading Document and ERP use\u00a0\n* Manage current customer follow up\u00a0\n* Almost document base on English\u00a0\n* Suitable for man\u00a0\n\nRequirements\n\n* Knowledge in MS word & Excel ( in Chinese * English )\n* Can communicate with Customer ( English & Cantonese )\n* If can do adobe photo shop ( basic level )\u00a0\n* 1 Year or Above Experience\n* Expected Salary must show on resume\n* Good communication skill with team\n\nBenefit\n\n* 13 month salary\u00a0\n* Team work incentive - End of year - Target with Goal", "employment_types": ["Full Time"], "selling_points": ["Food packaging material sales", "13 month salary", "development opportunities"], "locations": ["Tsuen Wan Area"], "categories": ["Admin & HR", "Clerical / Admin Staff", "Sales, CS & Business Devpt", "Sales - Sales Management", "Others", "Trading"], "post_time": "2021-12-28T09:17:53Z", "salary": {"currency": "HKD", "max": 16999, "min": 14000, "period": "monthly", "term": null}, "salary_visible": true, "title_keywords": ["clerk", "sales assistant"], "responsibilities": [], "requirements": {"degrees": [], "majors": [], "languages": ["cantonese", "english", "chinese"], "language_level": [], "hard_skills": ["excel", "adobe", "basic", "ms word"], "soft_skills": ["communication skill"], "languages_combined": [{"language": "cantonese", "language_level": []}, {"language": "english", "language_level": []}, {"language": "chinese", "language_level": []}]}, "experience_required": {"duration": ["1 year"], "field": []}}, {"job_id": "100003009008542", "location_code": "hk", "company": "G.A. Operations Hong Kong Limited", "job_title": "Costing Specialist - Footwear", "description": "Responsible for footwear product quotation review to ensure price accuracy, consistency and competitiveness amongst various suppliers in Asia.\n\nKey Responsibilities:\n\nPrepare & provide costing information based on business needs\nProvide costing insights and data to support strategic allocation of suppliers\nIdentify and validate any gap on costing data across vendors/ regions/ seasons\nPrepare regular and ad hoc reports, tracking and performance analysis for management review & decision\n\nJob requirements:\n\nBachelor's degree in / Business / Finance / Economics / Engineering\nAt least 5 years in pricing and costing in trading or manufacturing industry\nExperience in fashion sourcing field, materials and technical cost specifically good knowledge in footwear is a big plus\nStrong numerical, analytical skills, detail-minded\nFluent in written and verbal English and mandarin\nGood hands-on skills in MS Excel highly preferred", "employment_types": ["Full Time", "Permanent"], "selling_points": [], "locations": ["Kowloon Bay"], "categories": ["Others", "Trading"], "post_time": "2021-12-30T08:15:00Z", "salary": {"currency": null, "max": null, "min": null, "period": "monthly", "term": null}, "salary_visible": false, "title_keywords": ["specialist"], "responsibilities": ["ad hoc", "data", "analysis", "reports", "management review", "tracking"], "requirements": {"degrees": ["degree", "bachelor"], "majors": ["finance", "business", "economics", "engineering"], "languages": ["english", "mandarin"], "language_level": ["fluent"], "hard_skills": ["plus", "ms excel", "analytical skills"], "soft_skills": ["detail-minded", "hands-on", "analytical skills"], "languages_combined": [{"language": "english", "language_level": ["fluent"]}, {"language": "mandarin", "language_level": ["fluent"]}]}, "experience_required": {"duration": [], "field": []}}, {"job_id": "100003009006026", "location_code": "hk", "company": "China Forestry International Resource Company Limited", "job_title": "Trading Assistant", "description": "Job Responsibilities:\n\nPrepare trading doc e.g. L/C application, invoice, contract and packing list\nMaintain good relationship with bank and other related parties\nKeep track with the trend of foreign currency and marketing news\nLiaise with other subsidiaries to explore more marketing opportunities\nHandle ad-hoc assignment\n\nJob Requirements:\n\nDSE or above (Fresh graduate is also welcome)\u00a0\nSelf-motivated, proactive and detail-minded\nDetailed-oriented and ability to multi-task in a fast paced working environment\nProficient in using Microsoft words and excel\nAble to communicate in English, Chinese and Mandarin\nImmediate available is highly preferred\n\nWe\u00a0offer\u00a0attractive remuneration package to the right candidate.\u00a0Interested parties please send us your full resume with present and\u00a0expected salary by clicking 'APPLY NOW'.\u00a0", "employment_types": ["Full Time"], "selling_points": [], "locations": ["Wan Chai"], "categories": ["Banking / Finance", "Dealing & Trading", "Transportation & Logistics", "Shipping", "Others", "Trading"], "post_time": "2021-12-29T06:45:39Z", "salary": {"currency": null, "max": null, "min": null, "period": "monthly", "term": null}, "salary_visible": false, "title_keywords": ["assistant"], "responsibilities": ["ad-hoc", "invoice", "maintain good relationship", "packing list", "liaise with"], "requirements": {"degrees": ["fresh graduate", "dse"], "majors": [], "languages": ["english", "chinese", "mandarin"], "language_level": [], "hard_skills": ["excel", "words"], "soft_skills": ["detail-minded", "self-motivated", "multi-task", "proactive", "detailed"], "languages_combined": [{"language": "english", "language_level": []}, {"language": "chinese", "language_level": []}, {"language": "mandarin", "language_level": []}]}, "experience_required": {"duration": [], "field": []}}, {"job_id": "100003009007667", "location_code": "hk", "company": "Han Sheng Tang Herbal Technologies Co., Limited", "job_title": "Senior Secretary", "description": "Duties\n\n~ Provide comprehensive and high-quality secretarial tasks for Management.\n\n~ Responsible for the Chinese and English translation of documents.\n\n~ Manage schedules, appointments and meetings.\n\n~ Project follow-up, system management of documents and letters and coordinate\u00a0 project operations.\n\n~ Handling Chinese and English letters, agendas, meeting minutes and reports.\n\n~ Liaise with related businesses, documents follow-up, and support the team to deal with projects and tasks.\n\n~ Prepare materials and follow up the works or projects carried out by the management.\n\n~ Perform ad-hoc duties as assigned.\n\nRequirements\n\n~ Full-time university or above, liberal arts preferred.\n\n~ 5 years of secretary or administrative experience.\n\n~ Fluent in written and spoken Chinese and English, with average listening and speaking skills in Putonghua.\n\n~ Excellent Chinese writing and translation skills.\n\n~ Good interpersonal skills and strong understanding ability.\n\n~ Strong PC skills in Microsoft Office applications.\n\n~ Loyal, active, diligent, efficient, able to handle multiple tasks in an orderly manner.\n\n~ Immediate availability is preferred.\n\n(All personal data collected will be kept in the strictest confidence and to be used for recruitment purpose only.)", "employment_types": ["Full Time"], "selling_points": ["Full-time university or above", "5 yrs of secretary or administration experience", "Excellent Chinese writing and translation skills"], "locations": ["Central & Western Area"], "categories": ["Others", "Trading"], "post_time": "2021-12-30T03:47:51Z", "salary": {"currency": null, "max": null, "min": null, "period": "monthly", "term": null}, "salary_visible": false, "title_keywords": ["senior secretary"], "responsibilities": ["management", "schedules", "operations", "letters", "quality", "coordinate", "reports", "ad-hoc duties", "liaise with", "support the team"], "requirements": {"degrees": [], "majors": [], "languages": ["putonghua", "english", "chinese"], "language_level": ["excellent", "average", "fluent"], "hard_skills": ["translation", "pc skills", "microsoft office"], "soft_skills": ["efficient", "confidence", "orderly", "diligent", "handle multiple tasks", "interpersonal skills", "loyal", "active"], "languages_combined": [{"language": "putonghua", "language_level": ["average", "fluent"]}, {"language": "english", "language_level": ["average", "fluent"]}, {"language": "chinese", "language_level": ["excellent", "average", "fluent"]}]}, "experience_required": {"duration": ["5 years"], "field": ["administrative"]}}, {"job_id": "100003009003020", "location_code": "hk", "company": "Speed Top (Hong Kong) Limited", "job_title": "Warehouse Officer", "description": "Our company, Speed Top (Hong Kong) Limited is now seeking a capable person to control our warehouse/Inventory department in construction materials. He or She should process the following requirements.\n\nl\u00a0\u00a0 F.5 or above & minimum 3 years\u2019 experience in construction materials\n\nl\u00a0\u00a0 Good skill to operate computer\n\nl\u00a0\u00a0 Actual shipping & trade link knowledge is a must\n\nl\u00a0\u00a0 Should be responsible, honest, self-motivated & willing to learn\n\nWe offer an attractive remuneration package to the right candidate:\n\n-\u00a0\u00a0\u00a0\u00a0\u00a0\u00a0\u00a0\u00a0\u00a0 Basic salary & performance bonus\n\n-\u00a0\u00a0\u00a0\u00a0\u00a0\u00a0\u00a0\u00a0\u00a0 Medical benefits\n\n-\u00a0\u00a0\u00a0\u00a0\u00a0\u00a0\u00a0\u00a0\u00a0 5 days work\n\nFor interested parties, please send full resume with salary expectation email by clicking \"Apply Now\"\n\nPersonal data collected will be used for recruitment purpose only.", "employment_types": ["Full Time", "Permanent"], "selling_points": ["5 days work / bonus / medical benefits", "Shipping & Tradelink knowledge is a must", "Experience in construction material"], "locations": ["Not Specified"], "categories": ["Building & Construction", "Building / Construction / QS", "Others", "Trading", "Others"], "post_time": "2021-12-28T07:59:04Z", "salary": {"currency": null, "max": null, "min": null, "period": "monthly", "term": null}, "salary_visible": false, "title_keywords": ["officer"], "responsibilities": ["shipping", "control", "inventory"], "requirements": {"degrees": [], "majors": [], "languages": [], "language_level": [], "hard_skills": [], "soft_skills": ["self-motivated", "capable", "responsible", "willing to learn", "honest"], "languages_combined": []}, "experience_required": {"duration": ["minimum 3 years"], "field": ["construction"]}}, {"job_id": "100003009011153", "location_code": "hk", "company": "Asian Sourcing Link Limited", "job_title": "ACCOUNTANT", "description": "Position Responsibilities:\n-\u00a0 \u00a0 \u00a0 \u00a0\u00a0Responsible for accounting operations, including billing, invoicing, AR, AP, GL. Active role in month-end closing, cash management, performance of controls\n-\u00a0\u00a0\u00a0\u00a0\u00a0\u00a0\u00a0 Coordinate with subsidiaries' finance team within the region, gather and review financial reports and information on regular basis\n\nRequirements:\n-\u00a0 \u00a0 \u00a0 \u00a0Degree in Accounting, Finance or related discipline\n-\u00a0\u00a0\u00a0\u00a0\u00a0\u00a0\u00a0 5 years\u2019 experience in audit and accounting\n-\u00a0\u00a0\u00a0\u00a0\u00a0\u00a0\u00a0 Knowledge of accounting standards and taxation in PRC is preferred\n-\u00a0\u00a0\u00a0\u00a0\u00a0\u00a0\u00a0 Ability to work cross-functionally in a fast-paced environment\n-\u00a0\u00a0\u00a0\u00a0\u00a0\u00a0\u00a0 Self-initiatives, good interpersonal skills, hands on and willing to work under pressure\n-\u00a0\u00a0\u00a0\u00a0\u00a0\u00a0\u00a0 Competency in Excel and ERP system\n-\u00a0\u00a0\u00a0\u00a0\u00a0\u00a0\u00a0 Excellent command of both written and spoken English and Chinese including Mandarin\n\nWe offer a friendly working environment in Causeway Bay, a five day week and fringe benefits that include medical insurance and 15 days paid leave annually.\n\nInterested candidates please email full CV including previous work experience, current and expected salary by clicking \"Apply Now\".\n\nPersonal data will be used for recruitment purpose only.", "employment_types": ["Full Time", "Permanent"], "selling_points": ["Responsible for accounting operations", "Coordinate with subsidiaries' finance team", "Degree in Accounting, Finance or related disciplin"], "locations": ["Causeway Bay"], "categories": ["Accounting", "Accountant", "Others", "Others", "Trading"], "post_time": "2021-12-31T06:35:21Z", "salary": {"currency": null, "max": null, "min": null, "period": "monthly", "term": null}, "salary_visible": false, "title_keywords": ["accountant"], "responsibilities": ["ap", "management", "financial reports", "ar", "operations", "review", "coordinate with", "invoicing", "month-end closing", "finance team"], "requirements": {"degrees": ["degree"], "majors": ["finance", "accounting"], "languages": ["english", "chinese", "mandarin"], "language_level": ["excellent"], "hard_skills": ["excel", "erp system"], "soft_skills": ["fast-paced environment", "hands on", "interpersonal skills", "friendly", "work under pressure"], "languages_combined": [{"language": "english", "language_level": ["excellent"]}, {"language": "chinese", "language_level": ["excellent"]}, {"language": "mandarin", "language_level": ["excellent"]}]}, "experience_required": {"duration": ["5 years"], "field": ["accounting", "audit"]}}, {"job_id": "100003009003735", "location_code": "hk", "company": "PERSOLKELLY Hong Kong Limited", "job_title": "Japanese Speaking Sales Coordinator(Near MTR/Stable & fast growing company/~23K)", "description": "Our client, a Japanese company, is now seeking for a high caliber individual to join their team as Japanese Speaking Sales Coordinator.\n\nJob Descriptions:\n\nPrepare Quotation, Purchase Order etc.\nFollow-up order details with vendors, customers and internal parties to ensure customer satisfaction and on-time delivery.\nArrange and monitor the shipment schedule with vendors, forwarders, and customers\nInventory control, liaise with Japan head office\n\nRequirements:\n\n3 years or above relevant sales coordinating experience\nConversational Japanese (JLPT N2 or above) English and Mandarin\nDiploma or above\n\nInterested parties please send your application via email to\u00a0Apply Now\u00a0or\u00a0kibi_tsang @persolhk.com\u00a0For any inquiries, please do not hesitate to contact me at\u00a0(852) 2971-2513.\n\nPlease note that only short listed candidate will be notified.\n\nWe also have various job vacancies from our well-established clients in all kinds of fields, please feel free to contact us. We are always willing to give you support on your career development.\n\nOur company website:\u00a0http://www.persolhk.com\n\nAll information received will be treated in strict confidence and used for recruitment purpose only.", "employment_types": ["Full Time", "Permanent"], "selling_points": ["Convenient location, stable company", "Japanese JLPT N2 or above", "minimum 3 years experience in sale co"], "locations": ["Eastern Area"], "categories": ["Others", "Trading", "Sales, CS & Business Devpt", "Sales Administration"], "post_time": "2021-12-28T10:25:10Z", "salary": {"currency": null, "max": null, "min": null, "period": "monthly", "term": null}, "salary_visible": false, "title_keywords": ["sales"], "responsibilities": ["quotation", "monitor", "purchase", "inventory control", "schedule", "liaise with", "internal parties"], "requirements": {"degrees": ["diploma or above"], "majors": [], "languages": ["japanese", "english", "mandarin"], "language_level": ["conversational"], "hard_skills": [], "soft_skills": [], "languages_combined": [{"language": "japanese", "language_level": []}, {"language": "english", "language_level": ["conversational"]}, {"language": "mandarin", "language_level": ["conversational"]}]}, "experience_required": {"duration": ["3 years"], "field": []}}, {"job_id": "100003009011556", "location_code": "hk", "company": "China Construction Bank (Asia) Corporation Limited", "job_title": "Internal Control Professional - Treasury", "description": "Job Descriptions:\n\nPerform challenging role with large exposure in Treasury products with changing associated risks and requirements from regulators / Head Office.\nInterpret regulations, review trading/ sales authorities, policies and procedures;\nAssist in identify, analyze and control potential unauthorized trading risks;\nCoordinate and liaise with different stakeholders to ensure business and operations are conducted in accordance with relevant requirements;\nManage treasury trading systems, including user permissions and folder management of trading systems\nAd hoc assignments could be involved, partnership with stakeholders within Treasury Division, internal or external parties to deliver driving result on different topics/ projects.\n\nRequirements:\u00a0\n\nDegree holder or above, preferable in Banking or Finance.\nMinimum 2-5 years' relevant experience in financial markets, candidates from internal control/ risk/ audit/ treasury settlement or related areas would be welcome and considered.\nGood knowledge of the related business practice and principles.\nFast Learner with good working attitude and commitment.\nExcellent communication and people skills to work with others of different levels within the Bank.\nMulti-tasking with strong organizational skill and paying attention to details.\nBe enthusiastic and able to work in a team environment.\nProficient in Microsoft applications (Excel, Word and PowerPoint).\nGood in written and spoken English, Cantonese & Putonghua.\nQualification for Enhanced Competency Framework on Treasury Management is preferable.\n\nApplicants who are not contacted within 8 weeks may consider their applications unsuccessful and their personal data will be retained by the bank for a period up to two years.\n\nAll information provided by applicants will be used for recruitment purposes only and will be used strictly in accordance with the bank's personal data policies, a copy of which will be provided upon request.", "employment_types": ["Full Time", "Permanent"], "selling_points": ["Treasury internal control", "Trading/ sales authorities, policies & procedures", "Identify, analyze & control potential unauthorize"], "locations": ["Central"], "categories": ["Banking / Finance", "Treasury", "Others", "Trading"], "post_time": "2021-12-31T07:47:05Z", "salary": {"currency": null, "max": null, "min": null, "period": "monthly", "term": null}, "salary_visible": false, "title_keywords": [], "responsibilities": ["regulations", "control", "management", "policies", "operations", "review", "procedures", "systems", "external parties", "coordinate", "ad hoc assignments", "liaise with"], "requirements": {"degrees": ["degree holder"], "majors": ["finance"], "languages": ["cantonese", "putonghua", "english"], "language_level": ["good"], "hard_skills": ["excel", "microsoft applications", "word", "powerpoint", "internal control"], "soft_skills": ["good working attitude", "organizational skill", "communication", "multi-tasking", "attention to details", "enthusiastic", "fast learner"], "languages_combined": [{"language": "cantonese", "language_level": ["good"]}, {"language": "putonghua", "language_level": ["good"]}, {"language": "english", "language_level": ["good"]}]}, "experience_required": {"duration": ["minimum 2-5 years"], "field": ["related", "financial markets", "relevant experience", "audit"]}}, {"job_id": "100003008999363", "location_code": "hk", "company": "Hongkong Xinming Limited", "job_title": "Oil Trading Contract Operation / Cargo Operation", "description": "Responsibilities:\n\n\u00a01.\u00a0Contract Review/Preparations and Management of contract documentation, i.e. purchase contract, sales contract, etc.\n\n2.\u00a0Operation\u00a0of oil trading contract, including purchase and sales contract operation, vessel chartering contract operation, etc.\n\n3.\u00a0Monitor the whole operation process, prepare documentation, orders, invoice and other documents if necessary.\n\n4.\u00a0Support in Trade Finance process (L/C issuance, negotiation/discounting and presentation)\n\n5.\u00a0Responsible for vessel chartering activities and handles the chartering operations of shipments with chartered vessels\n\n6.\u00a0Issues voyage orders, loading and discharge instructions\n\n7.\u00a0Checks freight invoice and endorses to Management and Finance for approval and payment\n\n8.\u00a0Monitors vessel status and sends updates to concerned parties\n\n9.\u00a0Prepares demurrage computation for timely submission, follow up for collection to counterparties\u00a0\n\nRequirements:\n\n1.\u00a0Minimum diploma in business, maritime study or equivalent.\n\n2.\u00a0Minimum 3 years working experiences in oil trading field, maritime industry, or relevant.\n\n3.\u00a0Good understanding of oil trading business, contract operation, chartering, etc.\n\n4.\u00a0Meticulous, pro-active with positive attitude, strong communication and negotiation skills.\n\n5.\u00a0Excellent speaking and writing in English, Mandarin, Cantonese.", "employment_types": ["Full Time"], "selling_points": [], "locations": ["Wan Chai Area"], "categories": ["Others", "Trading"], "post_time": "2021-12-24T07:02:51Z", "salary": {"currency": null, "max": null, "min": null, "period": "monthly", "term": null}, "salary_visible": false, "title_keywords": [], "responsibilities": ["management", "invoice", "operations", "review", "monitor", "purchase", "contract documentation", "payment", "documentation"], "requirements": {"degrees": ["diploma"], "majors": ["business"], "languages": ["cantonese", "english", "mandarin"], "language_level": ["excellent"], "hard_skills": [], "soft_skills": ["meticulous", "positive attitude", "communication", "negotiation skills", "pro-active"], "languages_combined": [{"language": "cantonese", "language_level": ["excellent"]}, {"language": "english", "language_level": ["excellent"]}, {"language": "mandarin", "language_level": ["excellent"]}]}, "experience_required": {"duration": ["minimum 3 years"], "field": ["trading"]}}, {"job_id": "100003008999021", "location_code": "hk", "company": "JAC Recruitment Hong Kong Co., Limited", "job_title": "URGENT - Japanese Speaking Sales Executive (Fresh grad OK! trading co)", "description": "COMPANY OVERVIEW\nOur client, a Japanese electric parts trading company is looking for a Japanese Speaking Sales Executive.\n\nJOB RESPONSIBILITIES\n\nHandle existing client and business development of EU, USA, ASEAN markets\nLiaise with clients, factories and Japan HQ\nPrepare quotation, forecast, monthly sales report\nSales & delivery support\nBusiness trip (mainly day trip) is required after lockdown\n\nJOB REQUIREMENTS\n\nHigher Diploma or above\n1yr sales experience in electronics field is preferred\nFresh graduate is also considered!!\nGood command of Japanese, English and Mandarin\nProficient in MS Office\nGood team player, proactive\n\nBENEFITS\n\nDouble pay\nDiscretionary bonus\nMedical scheme\nLocation: NT\n5days, Mon-Fri\nSalary: Up to 18K depending on experience\u00a0\n\nPersonal data collected will be used for employment-related purposes only. We regret to inform that only shortlisted candidates will be notified.", "employment_types": ["Full Time", "Permanent"], "selling_points": ["Japanese speaking Sales, trading co.", "Existing client, quotation, sales report", "up to 18K, 13mths, bonus, medical"], "locations": ["Shatin Area"], "categories": ["Sales, CS & Business Devpt", "Account Servicing", "Others", "Trading", "Direct Sales"], "post_time": "2021-12-26T16:21:01Z", "salary": {"currency": null, "max": null, "min": null, "period": "monthly", "term": null}, "salary_visible": false, "title_keywords": ["japanese speaking sales executive"], "responsibilities": ["liaise with clients", "quotation", "business trip", "forecast", "monthly sales report"], "requirements": {"degrees": ["higher diploma or above", "fresh graduate"], "majors": [], "languages": ["japanese", "english", "mandarin"], "language_level": ["good command"], "hard_skills": ["ms office"], "soft_skills": ["good team player", "proactive"], "languages_combined": [{"language": "japanese", "language_level": ["good command"]}, {"language": "english", "language_level": ["good command"]}, {"language": "mandarin", "language_level": ["good command"]}]}, "experience_required": {"duration": [], "field": []}}, {"job_id": "100003009006031", "location_code": "hk", "company": "Groupe Casino Limited", "job_title": "Senior Accounting Clerk / Assistant Accountant", "description": "This role will play an integral part of our Finance Department by effectively and systematically provide accurate information and optimize team collaboration.\n\n\u00a0Job Description:\u00a0\n\nPrepare vouchers and breakdown\nResponsible for general accounting routines and data entries\nPrepare monthly billing\nAssist in preparing monthly financial statements\nMaintain filing systems\nAssist in month-end closing, bank reconciliation & year-end audit\u00a0\nHandle ad-hoc tasks\n\nJob Requirements:\u00a0\n\nDegree/ Diploma, major in Accounting\n4+ years working experience in accounting field, less experience will consider as Senior accounting clerk\nGood in written and spoken English & Mandarin\nProficient in MS Office applications, especially Excel\nSelf motivated, good team player, high standard of accuracy\nImmediately available or short noticed candidate is highly preferred\n\nWe offer good remuneration package to the right candidate including\u00a05 days work, Flexible working\u00a0hour,\u00a0Bank Holiday, 15 days annual\u00a0leaves, Medical & Dental Insurance, Bonus and Double Pay.\n\nWe are an equal opportunities employer and welcome applications from all candidates with the required skills and experience.\u00a0Interested candidates\u00a0can send resume, application letter, expected salary and date of availability through Jobs DB.\n\nPersonal data collected will be used for recruitment purpose only.\u00a0\u00a0Only qualified candidates will be contacted.\u00a0\n\nFor more information about our company, please free to visit our website:\u00a0\u00a0www.casinoglobalsourcing.com", "employment_types": ["Full Time"], "selling_points": [], "locations": ["Wan Chai Area"], "categories": ["Accounting", "Accountant", "Accounting Clerk / Supervisor", "Others", "Trading"], "post_time": "2021-12-29T06:46:01Z", "salary": {"currency": null, "max": null, "min": null, "period": "monthly", "term": null}, "salary_visible": false, "title_keywords": ["accounting clerk", "assistant accountant"], "responsibilities": ["year-end", "data", "ad-hoc tasks", "systems", "monthly financial statements", "bank reconciliation", "audit", "month-end closing", "maintain"], "requirements": {"degrees": ["diploma", "degree"], "majors": ["accounting"], "languages": ["english", "mandarin"], "language_level": ["good"], "hard_skills": ["excel", "ms office"], "soft_skills": ["self motivated", "good team player", "flexible"], "languages_combined": [{"language": "english", "language_level": ["good"]}, {"language": "mandarin", "language_level": ["good"]}]}, "experience_required": {"duration": ["4+ years"], "field": ["accounting"]}}]